Workbook

Sheet Access Control
A1: ⬅ NAVIGATE:
A2: ElevateED — 🔒 AUTHORIZED ACCESS ONLY
A3: Talent Ready IT Program | Largo High School | Prince George's Community College
A4: Maryland Blueprint for Maryland's Future | CONFIDENTIAL — FERPA PROTECTED | Generated: February 13, 2026 03:35 PM
A6: ⚠️ THIS WORKBOOK CONTAINS FERPA-PROTECTED STUDENT DATA FOR 59 MINOR STUDENTS
A7: Unauthorized access, sharing, or distribution is a federal violation under 20 U.S.C. § 1232g and may result in criminal penalties.
A10: GOOGLE WORKSPACE / MICROSOFT 365 — AUTHENTICATION & SHARING SETUP
A12: SHAREPOINT / GOOGLE DRIVE ACCESS CONTROL
A13: Step 1: SharePoint Setup | B13: Create a SharePoint Team Site → 'Talent Ready ElevateED' → Set to Private | F13: Required
A14: Step 2: Upload Files | B14: Upload ALL ElevateED .xlsx files to the site document library | F14: Required
A15: Step 3: Add Authorized Users | B15: Site Settings → Permissions → Add the 6 authorized emails below | F15: Required
A16: Step 4: Google Login (if using Google Drive) | B16: Share folder with the 6 @pgcps.org emails below — Restricted access only | F16: Required
A17: Step 5: Verify No External Sharing | B17: Settings → Sharing → Ensure 'Only people in your org' is selected | F17: Required
A18: Step 6: Enable Audit Logging | B18: Compliance Center → Audit → Enable 'File and page activities' | F18: Required
A19: Step 7: Apply Sensitivity Label | B19: Microsoft 365 Compliance → Labels → Apply 'FERPA — Confidential' to all files | F19: Required
A20: Step 8: Test Access | B20: Log in as each authorized user → Verify they can see ONLY their permitted sheets | F20: Required
A23: 🛡️ AUTHORIZED USERS — SITE ADMINISTRATORS (Full Access)
A24: # | B24: Full Name | C24: Email Address (Google/M365 Login) | D24: Role | E24: Access Level | F24: Department | G24: FERPA Training | H24: Last Access | I24: Status | J24: Acknowledgment
A25: 1 | B25: Alphonsius Buma | C25: alphonsius.buma@pgcps.org | D25: Site Administrator | E25: Full Access — All Data, Config, User Mgmt | F25: PGCPS — Largo High School | G25: ✅ Complete (Aug 2025) | H25: February 13, 2026 03:35 PM | I25: ✅ ACTIVE | J25: Signed — On File
A26: 2 | B26: Carlton James | C26: carlton.james@pgcps.org | D26: Site Administrator | E26: Full Access — All Data, Config, User Mgmt | F26: PGCPS — Largo High School | G26: ✅ Complete (Aug 2025) | H26: February 13, 2026 03:35 PM | I26: ✅ ACTIVE | J26: Signed — On File
A29: 👁️ AUTHORIZED USERS — FULL DATA VIEWERS (Read-Only)
A30: # | B30: Full Name | C30: Email Address (Google/M365 Login) | D30: Role | E30: Access Level | F30: Department | G30: FERPA Training | H30: Last Access | I30: Status | J30: Acknowledgment
A31: 1 | B31: Keith Brice | C31: keith.brice@pgcps.org | D31: Authorized Viewer | E31: Full Data View — All Students, All Cohorts | F31: PGCPS — Largo High School | G31: ✅ Complete (Aug 2025) | H31: February 13, 2026 03:35 PM | I31: ✅ ACTIVE | J31: Signed — On File
A32: 2 | B32: Tomisha King | C32: tomisha.king@pgcps.org | D32: Site Administrator | E32: Full Access — All Data, Config, Status Changes | F32: PGCPS — Largo High School | G32: ✅ Complete (Aug 2025) | H32: February 13, 2026 03:35 PM | I32: ✅ ACTIVE | J32: Signed — On File
A33: 3 | B33: Albert Lewis | C33: albert.lewis@pgcps.org | D33: Authorized Viewer | E33: Full Data View — All Students, All Cohorts | F33: PGCPS — Largo High School | G33: ✅ Complete (Aug 2025) | H33: February 13, 2026 03:35 PM | I33: ✅ ACTIVE | J33: Signed — On File
A34: 4 | B34: Robyn Jones | C34: robyn.jones@pgcps.org | D34: Authorized Viewer | E34: Full Data View — All Students, All Cohorts | F34: PGCPS — Largo High School | G34: ✅ Complete (Aug 2025) | H34: February 13, 2026 03:35 PM | I34: ✅ ACTIVE | J34: Signed — On File
A37: 🚫 ALL OTHER USERS — ACCESS DENIED
A38: User Category | B38: Access Level | C38: Notes
A39: Anyone not listed above | B39: NO ACCESS | C39: Access attempt logged to audit trail
A40: Students | B40: NO ACCESS | C40: Students may not view their own raw data in this workbook
A41: Parents / Guardians | B41: NO ACCESS | C41: Parents receive Thursday email reports only — never direct access
A42: PGCC Instructors (not listed) | B42: NO ACCESS | C42: Instructors receive course-specific views only on request
A43: External Partners / Vendors | B43: NO ACCESS | C43: No third-party access without signed FERPA data-sharing agreement
A44: PGCPS IT Staff (not listed) | B44: NO ACCESS | C44: IT support uses admin role on request — logged and time-limited
A47: 📋 FERPA ACKNOWLEDGMENT — REQUIRED FOR ALL AUTHORIZED USERS
A48: By accessing this workbook, I acknowledge and agree to the following:
A50: 1. I have completed FERPA training and understand my obligations under 20 U.S.C. § 1232g.
A51: 2. I will access student data ONLY for legitimate educational purposes related to my assigned role.
A52: 3. I will NOT share, forward, copy, screenshot, or distribute any student data outside this system.
A53: 4. I will NOT store student data on personal devices, USB drives, or unauthorized cloud storage.
A54: 5. I will lock my screen when stepping away from any device displaying student data.
A55: 6. I will report any suspected data breach immediately to the FERPA Compliance Officer.
A56: 7. I understand that FERPA violations may result in termination, legal action, and federal penalties.
A58: FERPA Compliance Officer: Carlton A. James | carlton.james@pgcps.org | (301) 583-5400
A61: # | B61: Name | C61: Email | D61: Signature | E61: Date Signed
A62: 1 | B62: Alphonsius Buma | C62: alphonsius.buma@pgcps.org
A63: 2 | B63: Carlton James | C63: carlton.james@pgcps.org
A64: 3 | B64: Keith Brice | C64: keith.brice@pgcps.org
A65: 4 | B65: Tomisha King | C65: tomisha.king@pgcps.org
A66: 5 | B66: Albert Lewis | C66: albert.lewis@pgcps.org
A67: 6 | B67: Robyn Jones | C67: robyn.jones@pgcps.org
A69: 📋 STATUS MANAGEMENT — STUDENT ENROLLMENT CHANGES
A70: Authorized: Alphonsius Buma, Carlton James, Tomisha King may change status in Student Master column F.
A72: Status Code | B72: Meaning | C72: When to Use | D72: Changed By | E72: Audit | F72: Data
A73: Active | B73: Currently enrolled | C73: Default | D73: Buma, King, James | E73: Auto-logged | F73: Full access
A74: 🔄 Transferred | B74: Moved schools | C74: Exits PGCPS | D74: Buma, King, James | E74: Document destination | F74: Frozen
A75: 📤 Withdrawn | B75: Parent withdrawal | C75: Parent initiates | D75: Buma, King, James | E75: Document reason | F75: Frozen
A76: ❌ Dropped | B76: Admin removal | C76: Interventions exhausted | D76: Buma, King, James | E76: SIT docs required | F76: Frozen
A77: ⏸ Inactive | B77: Temp absence | C77: Medical/extended | D77: Buma, King, James | E77: Document return plan | F77: Paused
A78: 🔒 Graduated | B78: Diploma awarded | C78: Senior year end | D78: System (auto) | E78: Auto-logged | F78: Permanent

Sheet Student Master
A1: ⬅ NAVIGATE:
A2: ElevateED — STUDENT MASTER — 59 Active + 5 Alumni | Historical Trends Integrated
A3: Talent Ready IT Program | Largo High School | Prince George's Community College
A4: Maryland Blueprint for Maryland's Future | CONFIDENTIAL — FERPA PROTECTED | Generated: February 13, 2026 03:35 PM
A5: Running Document — All semesters | Prior history integrated | Alumni closed | February 13, 2026
A6: Student ID | B6: Last Name | C6: First Name | D6: Cohort | E6: Grade | F6: Status | G6: Course 1 | H6: C1 Sem | I6: C1 Avg | J6: Course 2 | K6: C2 Sem | L6: C2 Avg | M6: Course 3 | N6: C3 Sem | O6: C3 Avg | P6: Course 4 | Q6: C4 Sem | R6: C4 Avg | S6: Course 5 | T6: C5 Sem | U6: C5 Avg | V6: Course 6 | W6: C6 Sem | X6: C6 Avg | Y6: Course 7 | Z6: C7 Sem | AA6: C7 Avg | AB6: Overall Avg | AC6: GPA | AD6: Letter Grade | AE6: Status Flag | AF6: MTSS Tier | AG6: CCR Status | AH6: IEP | AI6: 504 | AJ6: Trend | AK6: Risk Score | AL6: Intervention | AM6: Last Updated
A7: TR-0001 | B7: CRICHTON III | C7: LEONARD | D7: 2026 | E7: 12 | F7: Active | G7: Calculus | H7: Fall 2025 | I7: 94 | J7: Psychology | K7: Fall 2025 | L7: 88.9 | M7: English | N7: Fall 2025 | O7: 85.5 | P7: Art | Q7: Fall 2025 | R7: 112.3 | S7: INT 2840 — System Analysis/Project Mgmt | T7: Spring 2026 | V7: INT 2310 — Windows Server Admin | W7: Spring 2026 | Y7: EGL 1340 — Composition II: Technical Writing | Z7: Spring 2026 | AB7: 95.2 | AC7: 3.81 | AD7: A | AE7: 🌟 Excelling | AF7: Tier 1 | AG7: ✅ Met | AH7: No | AI7: No | AJ7: → Stable | AK7: =IF(AB6="",0,IFERROR((100-AB6)*1.2+IF(AF6="Tier 3",20,IF(AF6="Tier 2",10,0))+IF(AH6="Yes",5,0),0)) -> 0 | AL7: None | AM7: 02/13/2026
A8: TR-0002 | B8: CROWELL | C8: KINGSTON | D8: 2026 | E8: 12 | F8: Active | G8: Calculus | H8: Fall 2025 | I8: 87.3 | J8: Psychology | K8: Fall 2025 | L8: 95.8 | M8: English | N8: Fall 2025 | O8: 88.2 | P8: Art | Q8: Fall 2025 | R8: 112.3 | S8: INT 2840 — System Analysis/Project Mgmt | T8: Spring 2026 | V8: INT 2310 — Windows Server Admin | W8: Spring 2026 | Y8: EGL 1340 — Composition II: Technical Writing | Z8: Spring 2026 | AB8: 95.9 | AC8: 3.84 | AD8: A | AE8: 🌟 Excelling | AF8: Tier 1 | AG8: ✅ Met | AH8: No | AI8: No | AJ8: → Stable | AK8: =IF(AB7="",0,IFERROR((100-AB7)*1.2+IF(AF7="Tier 3",20,IF(AF7="Tier 2",10,0))+IF(AH7="Yes",5,0),0)) -> 5.76 | AL8: None | AM8: 02/13/2026
A9: TR-0003 | B9: DAVIS | C9: GABRIEL | D9: 2026 | E9: 12 | F9: Active | G9: Calculus | H9: Fall 2025 | I9: 87.3 | J9: Psychology | K9: Fall 2025 | L9: 80.6 | M9: English | N9: Fall 2025 | O9: 92.9 | P9: Art | Q9: Fall 2025 | R9: 91.2 | S9: INT 2840 — System Analysis/Project Mgmt | T9: Spring 2026 | V9: INT 2310 — Windows Server Admin | W9: Spring 2026 | Y9: EGL 1340 — Composition II: Technical Writing | Z9: Spring 2026 | AB9: 88 | AC9: 3.52 | AD9: B | AE9: 🟢 On Track | AF9: Tier 1 | AG9: ✅ Met | AH9: No | AI9: No | AJ9: → Stable | AK9: =IF(AB8="",0,IFERROR((100-AB8)*1.2+IF(AF8="Tier 3",20,IF(AF8="Tier 2",10,0))+IF(AH8="Yes",5,0),0)) -> 4.92 | AL9: None | AM9: 02/13/2026
A10: TR-0004 | B10: FERSNER | C10: LAILAH | D10: 2026 | E10: 12 | F10: Active | G10: Calculus | H10: Fall 2025 | I10: 91.5 | J10: Psychology | K10: Fall 2025 | L10: 89.4 | M10: English | N10: Fall 2025 | O10: 95.8 | P10: Art | Q10: Fall 2025 | R10: 104 | S10: INT 2840 — System Analysis/Project Mgmt | T10: Spring 2026 | U10: 94.4 | V10: INT 2310 — Windows Server Admin | W10: Spring 2026 | X10: 97.15 | Y10: EGL 1340 — Composition II: Technical Writing | Z10: Spring 2026 | AA10: 95 | AB10: 95.3 | AC10: 3.81 | AD10: A | AE10: 🌟 Excelling | AF10: Tier 1 | AG10: ✅ Met | AH10: No | AI10: No | AJ10: → Stable | AK10: =IF(AB9="",0,IFERROR((100-AB9)*1.2+IF(AF9="Tier 3",20,IF(AF9="Tier 2",10,0))+IF(AH9="Yes",5,0),0)) -> 14.4 | AL10: None | AM10: 02/13/2026
A11: TR-0005 | B11: FORD | C11: JAMES | D11: 2026 | E11: 12 | F11: Active | G11: Calculus | H11: Fall 2025 | I11: 91.1 | J11: Psychology | K11: Fall 2025 | L11: 91.8 | M11: English | N11: Fall 2025 | O11: 81.3 | P11: Art | Q11: Fall 2025 | R11: 118 | S11: INT 2840 — System Analysis/Project Mgmt | T11: Spring 2026 | U11: 86 | V11: INT 2310 — Windows Server Admin | W11: Spring 2026 | X11: 98.14 | Y11: EGL 1340 — Composition II: Technical Writing | Z11: Spring 2026 | AA11: 88 | AB11: 93.5 | AC11: 3.74 | AD11: A | AE11: 🌟 Excelling | AF11: Tier 1 | AG11: ✅ Met | AH11: Yes | AI11: No | AJ11: → Stable | AK11: =IF(AB10="",0,IFERROR((100-AB10)*1.2+IF(AF10="Tier 3",20,IF(AF10="Tier 2",10,0))+IF(AH10="Yes",5,0),0)) -> 5.64 | AL11: None | AM11: 02/13/2026
A12: TR-0006 | B12: FORREST | C12: TYLEYL | D12: 2026 | E12: 12 | F12: Active | G12: Calculus | H12: Fall 2025 | I12: 95.7 | J12: Psychology | K12: Fall 2025 | L12: 96.7 | M12: English | N12: Fall 2025 | O12: 98.5 | P12: Art | Q12: Fall 2025 | R12: 116.8 | S12: INT 2840 — System Analysis/Project Mgmt | T12: Spring 2026 | V12: INT 2310 — Windows Server Admin | W12: Spring 2026 | Y12: EGL 1340 — Composition II: Technical Writing | Z12: Spring 2026 | AB12: 101.9 | AC12: 4 | AD12: A | AE12: 🌟 Excelling | AF12: Tier 1 | AG12: ✅ Met | AH12: No | AI12: No | AJ12: → Stable | AK12: =IF(AB11="",0,IFERROR((100-AB11)*1.2+IF(AF11="Tier 3",20,IF(AF11="Tier 2",10,0))+IF(AH11="Yes",5,0),0)) -> 12.8 | AL12: None | AM12: 02/13/2026
A13: TR-0007 | B13: JALLOH | C13: JENABU | D13: 2026 | E13: 12 | F13: Active | G13: Calculus | H13: Fall 2025 | I13: 98 | J13: Psychology | K13: Fall 2025 | L13: 87.8 | M13: English | N13: Fall 2025 | O13: 78.6 | P13: Art | Q13: Fall 2025 | R13: 93.9 | S13: INT 2840 — System Analysis/Project Mgmt | T13: Spring 2026 | V13: INT 2310 — Windows Server Admin | W13: Spring 2026 | Y13: EGL 1340 — Composition II: Technical Writing | Z13: Spring 2026 | AB13: 89.6 | AC13: 3.58 | AD13: B | AE13: 🟢 On Track | AF13: Tier 1 | AG13: ✅ Met | AH13: No | AI13: No | AJ13: → Stable | AK13: =IF(AB12="",0,IFERROR((100-AB12)*1.2+IF(AF12="Tier 3",20,IF(AF12="Tier 2",10,0))+IF(AH12="Yes",5,0),0)) -> -2.28 | AL13: None | AM13: 02/13/2026
A14: TR-0008 | B14: JOHNSON-BONILLA | C14: CHRISTOPHER | D14: 2026 | E14: 12 | F14: Active | G14: Calculus | H14: Fall 2025 | I14: 92.4 | J14: Psychology | K14: Fall 2025 | L14: 89.4 | M14: English | N14: Fall 2025 | O14: 94.7 | P14: Art | Q14: Fall 2025 | R14: 110.3 | S14: INT 2840 — System Analysis/Project Mgmt | T14: Spring 2026 | U14: 92.86 | V14: INT 2310 — Windows Server Admin | W14: Spring 2026 | X14: 98.31 | Y14: EGL 1340 — Composition II: Technical Writing | Z14: Spring 2026 | AA14: 83.5 | AB14: 94.5 | AC14: 3.78 | AD14: A | AE14: 🌟 Excelling | AF14: Tier 1 | AG14: ✅ Met | AH14: No | AI14: No | AJ14: → Stable | AK14: =IF(AB13="",0,IFERROR((100-AB13)*1.2+IF(AF13="Tier 3",20,IF(AF13="Tier 2",10,0))+IF(AH13="Yes",5,0),0)) -> 12.48 | AL14: None | AM14: 02/13/2026
A15: TR-0009 | B15: OLUBIYI | C15: OLUWANIFEMI | D15: 2026 | E15: 12 | F15: Active | G15: Calculus | H15: Fall 2025 | I15: 92.1 | J15: Psychology | K15: Fall 2025 | L15: 95.6 | M15: English | N15: Fall 2025 | O15: 94.5 | P15: Art | Q15: Fall 2025 | R15: 115 | S15: INT 2840 — System Analysis/Project Mgmt | T15: Spring 2026 | V15: INT 2310 — Windows Server Admin | W15: Spring 2026 | Y15: EGL 1340 — Composition II: Technical Writing | Z15: Spring 2026 | AB15: 99.3 | AC15: 3.97 | AD15: A | AE15: 🌟 Excelling | AF15: Tier 1 | AG15: ✅ Met | AH15: No | AI15: No | AJ15: → Stable | AK15: =IF(AB14="",0,IFERROR((100-AB14)*1.2+IF(AF14="Tier 3",20,IF(AF14="Tier 2",10,0))+IF(AH14="Yes",5,0),0)) -> 6.6 | AL15: None | AM15: 02/13/2026
A16: TR-0010 | B16: SANNI | C16: MOFEOLUWA | D16: 2026 | E16: 12 | F16: Active | G16: Calculus | H16: Fall 2025 | I16: 96.4 | J16: Psychology | K16: Fall 2025 | L16: 93.9 | M16: English | N16: Fall 2025 | O16: 96.4 | P16: Art | Q16: Fall 2025 | R16: 94.5 | S16: INT 2840 — System Analysis/Project Mgmt | T16: Spring 2026 | V16: INT 2310 — Windows Server Admin | W16: Spring 2026 | Y16: EGL 1340 — Composition II: Technical Writing | Z16: Spring 2026 | AB16: 95.3 | AC16: 3.81 | AD16: A | AE16: 🌟 Excelling | AF16: Tier 1 | AG16: ✅ Met | AH16: No | AI16: No | AJ16: → Stable | AK16: =IF(AB15="",0,IFERROR((100-AB15)*1.2+IF(AF15="Tier 3",20,IF(AF15="Tier 2",10,0))+IF(AH15="Yes",5,0),0)) -> 0.84 | AL16: None | AM16: 02/13/2026
A17: TR-0011 | B17: SCARLETT | C17: OLIVIA | D17: 2026 | E17: 12 | F17: Active | G17: Calculus | H17: Fall 2025 | I17: 95 | J17: Psychology | K17: Fall 2025 | L17: 76.7 | M17: English | N17: Fall 2025 | O17: 71.3 | P17: Art | Q17: Fall 2025 | R17: 112.9 | S17: INT 2840 — System Analysis/Project Mgmt | T17: Spring 2026 | U17: 84.07 | V17: INT 2310 — Windows Server Admin | W17: Spring 2026 | X17: 95.57 | Y17: EGL 1340 — Composition II: Technical Writing | Z17: Spring 2026 | AA17: 91 | AB17: 89.5 | AC17: 3.58 | AD17: B | AE17: 🟢 On Track | AF17: Tier 1 | AG17: ✅ Met | AH17: No | AI17: No | AJ17: → Stable | AK17: =IF(AB16="",0,IFERROR((100-AB16)*1.2+IF(AF16="Tier 3",20,IF(AF16="Tier 2",10,0))+IF(AH16="Yes",5,0),0)) -> 5.64 | AL17: None | AM17: 02/13/2026
A18: TR-0012 | B18: WALLACE | C18: JUSTIN | D18: 2026 | E18: 12 | F18: Active | G18: Calculus | H18: Fall 2025 | I18: 87.3 | J18: Psychology | K18: Fall 2025 | L18: 91.7 | M18: English | N18: Fall 2025 | O18: 95.8 | P18: Art | Q18: Fall 2025 | R18: 106.3 | S18: INT 2840 — System Analysis/Project Mgmt | T18: Spring 2026 | U18: 83.17 | V18: INT 2310 — Windows Server Admin | W18: Spring 2026 | X18: 86.45 | Y18: EGL 1340 — Composition II: Technical Writing | Z18: Spring 2026 | AA18: 82.5 | AB18: 90.5 | AC18: 3.62 | AD18: A | AE18: 🌟 Excelling | AF18: Tier 1 | AG18: ✅ Met | AH18: No | AI18: No | AJ18: → Stable | AK18: =IF(AB17="",0,IFERROR((100-AB17)*1.2+IF(AF17="Tier 3",20,IF(AF17="Tier 2",10,0))+IF(AH17="Yes",5,0),0)) -> 12.6 | AL18: None | AM18: 02/13/2026
A19: TR-0013 | B19: WILLIAMS | C19: CHLOE | D19: 2026 | E19: 12 | F19: Active | G19: Calculus | H19: Fall 2025 | I19: 94.8 | J19: Psychology | K19: Fall 2025 | L19: 90.6 | M19: English | N19: Fall 2025 | O19: 95.8 | P19: Art | Q19: Fall 2025 | R19: 111 | S19: INT 2840 — System Analysis/Project Mgmt | T19: Spring 2026 | U19: 95.19 | V19: INT 2310 — Windows Server Admin | W19: Spring 2026 | X19: 89.3 | Y19: EGL 1340 — Composition II: Technical Writing | Z19: Spring 2026 | AA19: 85 | AB19: 94.5 | AC19: 3.78 | AD19: A | AE19: 🌟 Excelling | AF19: Tier 1 | AG19: ✅ Met | AH19: Yes | AI19: No | AJ19: → Stable | AK19: =IF(AB18="",0,IFERROR((100-AB18)*1.2+IF(AF18="Tier 3",20,IF(AF18="Tier 2",10,0))+IF(AH18="Yes",5,0),0)) -> 11.4 | AL19: None | AM19: 02/13/2026
A20: TR-0014 | B20: WILBUR | C20: GABRIELLE | D20: 2026 | E20: 12 | F20: Active | G20: Calculus | H20: Fall 2025 | I20: 97.5 | J20: Psychology | K20: Fall 2025 | L20: 93.3 | M20: English | N20: Fall 2025 | O20: 97.5 | P20: Art | Q20: Fall 2025 | R20: 109.5 | S20: INT 2840 — System Analysis/Project Mgmt | T20: Spring 2026 | V20: INT 2310 — Windows Server Admin | W20: Spring 2026 | Y20: EGL 1340 — Composition II: Technical Writing | Z20: Spring 2026 | AB20: 99.5 | AC20: 3.98 | AD20: A | AE20: 🌟 Excelling | AF20: Tier 1 | AG20: ✅ Met | AH20: No | AI20: No | AJ20: → Stable | AK20: =IF(AB19="",0,IFERROR((100-AB19)*1.2+IF(AF19="Tier 3",20,IF(AF19="Tier 2",10,0))+IF(AH19="Yes",5,0),0)) -> 11.6 | AL20: None | AM20: 02/13/2026
A21: TR-0015 | B21: WINTERS | C21: AARON | D21: 2026 | E21: 12 | F21: Active | G21: Calculus | H21: Fall 2025 | I21: 89.9 | J21: Psychology | K21: Fall 2025 | L21: 92.8 | M21: English | N21: Fall 2025 | O21: 95.5 | P21: Art | Q21: Fall 2025 | R21: 107 | S21: INT 2840 — System Analysis/Project Mgmt | T21: Spring 2026 | U21: 87.3 | V21: INT 2310 — Windows Server Admin | W21: Spring 2026 | Y21: EGL 1340 — Composition II: Technical Writing | Z21: Spring 2026 | AA21: 85 | AB21: 92.9 | AC21: 3.72 | AD21: A | AE21: 🌟 Excelling | AF21: Tier 1 | AG21: ✅ Met | AH21: No | AI21: No | AJ21: → Stable | AK21: =IF(AB20="",0,IFERROR((100-AB20)*1.2+IF(AF20="Tier 3",20,IF(AF20="Tier 2",10,0))+IF(AH20="Yes",5,0),0)) -> 0.6 | AL21: None | AM21: 02/13/2026
A22: TR-0016 | B22: ZUBAIRU | C22: LATEEFAH | D22: 2026 | E22: 12 | F22: Active | G22: Calculus | H22: Fall 2025 | I22: 91.5 | J22: Psychology | K22: Fall 2025 | L22: 89.4 | M22: English | N22: Fall 2025 | O22: 95.8 | P22: Art | Q22: Fall 2025 | R22: 104 | S22: INT 2840 — System Analysis/Project Mgmt | T22: Spring 2026 | V22: INT 2310 — Windows Server Admin | W22: Spring 2026 | Y22: EGL 1340 — Composition II: Technical Writing | Z22: Spring 2026 | AB22: 95.2 | AC22: 3.81 | AD22: A | AE22: 🌟 Excelling | AF22: Tier 1 | AG22: ✅ Met | AH22: No | AI22: No | AJ22: → Stable | AK22: =IF(AB21="",0,IFERROR((100-AB21)*1.2+IF(AF21="Tier 3",20,IF(AF21="Tier 2",10,0))+IF(AH21="Yes",5,0),0)) -> 8.52 | AL22: None | AM22: 02/13/2026
A23: TR-0058 | B23: SCOTT | C23: SANAA | D23: 2026 | E23: 12 | F23: Active | G23: Calculus | H23: Fall 2025 | I23: 78.9 | J23: Psychology | K23: Fall 2025 | L23: 78.9 | M23: English | N23: Fall 2025 | O23: 78.9 | P23: Art | Q23: Fall 2025 | R23: 96.9 | S23: INT 2840 — System Analysis/Project Mgmt | T23: Spring 2026 | V23: INT 2310 — Windows Server Admin | W23: Spring 2026 | Y23: EGL 1340 — Composition II: Technical Writing | Z23: Spring 2026 | AB23: 83.4 | AC23: 3.34 | AD23: B | AE23: 🟢 On Track | AF23: Tier 1 | AG23: ✅ Met | AH23: No | AI23: No | AJ23: → Stable | AK23: =IF(AB22="",0,IFERROR((100-AB22)*1.2+IF(AF22="Tier 3",20,IF(AF22="Tier 2",10,0))+IF(AH22="Yes",5,0),0)) -> 5.76 | AL23: None | AM23: 02/13/2026
A24: TR-0017 | B24: BYFIELD | C24: KIMANI | D24: 2027 | E24: 11 | F24: Active | G24: BIO 1110 — Environmental Biology | H24: Fall 2025 | I24: 66.2 | J24: BIO 1120 — Environmental Biology Lab | K24: Fall 2025 | L24: 79.9 | M24: INT 1550 — Intro to Networks: Network+ Prep | N24: Fall 2025 | O24: 57.4 | AB24: 67.8 | AC24: 2.71 | AD24: D | AE24: 🟡 Watch | AF24: Tier 1/2 | AG24: ⚠️ Approaching | AH24: No | AI24: No | AJ24: → Stable | AK24: =IF(AB23="",0,IFERROR((100-AB23)*1.2+IF(AF23="Tier 3",20,IF(AF23="Tier 2",10,0))+IF(AH23="Yes",5,0),0)) -> 19.92 | AL24: None | AM24: 02/13/2026
A25: TR-0018 | B25: HODGE | C25: AMANI | D25: 2027 | E25: 11 | F25: Active | G25: BIO 1110 — Environmental Biology | H25: Fall 2025 | I25: 79.3 | J25: BIO 1120 — Environmental Biology Lab | K25: Fall 2025 | L25: 65 | M25: INT 1550 — Intro to Networks: Network+ Prep | N25: Fall 2025 | O25: 91.5 | AB25: 78.6 | AC25: 3.14 | AD25: C | AE25: 🟢 On Track | AF25: Tier 1 | AG25: ✅ Met | AH25: No | AI25: No | AJ25: → Stable | AK25: =IF(AB24="",0,IFERROR((100-AB24)*1.2+IF(AF24="Tier 3",20,IF(AF24="Tier 2",10,0))+IF(AH24="Yes",5,0),0)) -> 38.64 | AL25: None | AM25: 02/13/2026
A26: TR-0019 | B26: LAMBRIGHT | C26: KADYN | D26: 2027 | E26: 11 | F26: Active | G26: BIO 1110 — Environmental Biology | H26: Fall 2025 | I26: 86 | J26: BIO 1120 — Environmental Biology Lab | K26: Fall 2025 | L26: 65.1 | M26: INT 1550 — Intro to Networks: Network+ Prep | N26: Fall 2025 | O26: 64.2 | AB26: 71.8 | AC26: 2.87 | AD26: C | AE26: 🟡 Watch | AF26: Tier 1/2 | AG26: ⚠️ Approaching | AH26: No | AI26: No | AJ26: → Stable | AK26: =IF(AB25="",0,IFERROR((100-AB25)*1.2+IF(AF25="Tier 3",20,IF(AF25="Tier 2",10,0))+IF(AH25="Yes",5,0),0)) -> 25.68 | AL26: None | AM26: 02/13/2026
A27: TR-0020 | B27: NISBETH | C27: GRACE | D27: 2027 | E27: 11 | F27: Active | G27: BIO 1110 — Environmental Biology | H27: Fall 2025 | I27: 81.9 | J27: BIO 1120 — Environmental Biology Lab | K27: Fall 2025 | L27: 72.9 | M27: INT 1550 — Intro to Networks: Network+ Prep | N27: Fall 2025 | O27: 73.3 | AB27: 76 | AC27: 3.04 | AD27: C | AE27: 🟢 On Track | AF27: Tier 1 | AG27: ✅ Met | AH27: No | AI27: No | AJ27: → Stable | AK27: =IF(AB26="",0,IFERROR((100-AB26)*1.2+IF(AF26="Tier 3",20,IF(AF26="Tier 2",10,0))+IF(AH26="Yes",5,0),0)) -> 33.84 | AL27: None | AM27: 02/13/2026
A28: TR-0021 | B28: PAYTON | C28: JADEN | D28: 2027 | E28: 11 | F28: Active | G28: BIO 1110 — Environmental Biology | H28: Fall 2025 | I28: 66.4 | J28: BIO 1120 — Environmental Biology Lab | K28: Fall 2025 | L28: 89.6 | M28: INT 1550 — Intro to Networks: Network+ Prep | N28: Fall 2025 | O28: 78.9 | AB28: 78.3 | AC28: 3.13 | AD28: C | AE28: 🟢 On Track | AF28: Tier 1 | AG28: ✅ Met | AH28: No | AI28: No | AJ28: → Stable | AK28: =IF(AB27="",0,IFERROR((100-AB27)*1.2+IF(AF27="Tier 3",20,IF(AF27="Tier 2",10,0))+IF(AH27="Yes",5,0),0)) -> 28.8 | AL28: None | AM28: 02/13/2026
A29: TR-0022 | B29: WARD | C29: CANAAN | D29: 2027 | E29: 11 | F29: Active | G29: BIO 1110 — Environmental Biology | H29: Fall 2025 | I29: 83.2 | J29: BIO 1120 — Environmental Biology Lab | K29: Fall 2025 | L29: 93 | M29: INT 1550 — Intro to Networks: Network+ Prep | N29: Fall 2025 | O29: 80.5 | AB29: 85.6 | AC29: 3.42 | AD29: B | AE29: 🟢 On Track | AF29: Tier 1 | AG29: ✅ Met | AH29: No | AI29: No | AJ29: → Stable | AK29: =IF(AB28="",0,IFERROR((100-AB28)*1.2+IF(AF28="Tier 3",20,IF(AF28="Tier 2",10,0))+IF(AH28="Yes",5,0),0)) -> 26.04 | AL29: None | AM29: 02/13/2026
A30: TR-0023 | B30: AHETO | C30: EDWIN | D30: 2028 | E30: 10 | F30: Active | G30: COM 1010 — Speech Communication | H30: Fall 2025 | I30: 57 | J30: INT 1700 — Understanding Operating Systems | K30: Fall 2025 | L30: 98.5 | O30: 73.33 | R30: 82.27 | AB30: 77.8 | AC30: 3.11 | AD30: C | AE30: 🟢 On Track | AF30: Tier 1 | AG30: ✅ Met | AH30: No | AI30: No | AJ30: → Stable | AK30: =IF(AB29="",0,IFERROR((100-AB29)*1.2+IF(AF29="Tier 3",20,IF(AF29="Tier 2",10,0))+IF(AH29="Yes",5,0),0)) -> 17.28 | AL30: None | AM30: 02/13/2026
A31: TR-0024 | B31: ALI | C31: CALI | D31: 2028 | E31: 10 | F31: Active | G31: COM 1010 — Speech Communication | H31: Fall 2025 | I31: 87.4 | J31: INT 1700 — Understanding Operating Systems | K31: Fall 2025 | L31: 70.8 | O31: 60.95 | R31: 80.48 | AB31: 74.9 | AC31: 3 | AD31: C | AE31: 🟡 Watch | AF31: Tier 1/2 | AG31: ⚠️ Approaching | AH31: No | AI31: No | AJ31: → Stable | AK31: =IF(AB30="",0,IFERROR((100-AB30)*1.2+IF(AF30="Tier 3",20,IF(AF30="Tier 2",10,0))+IF(AH30="Yes",5,0),0)) -> 26.64 | AL31: None | AM31: 02/13/2026
A32: TR-0025 | B32: ANTHONY | C32: JELANI | D32: 2028 | E32: 10 | F32: Active | G32: COM 1010 — Speech Communication | H32: Fall 2025 | I32: 76 | J32: INT 1700 — Understanding Operating Systems | K32: Fall 2025 | L32: 89.3 | O32: 79.05 | R32: 67.83 | AB32: 78 | AC32: 3.12 | AD32: C | AE32: 🟢 On Track | AF32: Tier 1 | AG32: ✅ Met | AH32: No | AI32: No | AJ32: → Stable | AK32: =IF(AB31="",0,IFERROR((100-AB31)*1.2+IF(AF31="Tier 3",20,IF(AF31="Tier 2",10,0))+IF(AH31="Yes",5,0),0)) -> 30.12 | AL32: None | AM32: 02/13/2026
A33: TR-0026 | B33: EGUNJOBI | C33: OREOLUWA | D33: 2028 | E33: 10 | F33: Active | G33: COM 1010 — Speech Communication | H33: Fall 2025 | I33: 74.8 | J33: INT 1700 — Understanding Operating Systems | K33: Fall 2025 | L33: 72.8 | O33: 73.33 | R33: 68.21 | AB33: 72.3 | AC33: 2.89 | AD33: C | AE33: 🟡 Watch | AF33: Tier 1/2 | AG33: ⚠️ Approaching | AH33: No | AI33: No | AJ33: → Stable | AK33: =IF(AB32="",0,IFERROR((100-AB32)*1.2+IF(AF32="Tier 3",20,IF(AF32="Tier 2",10,0))+IF(AH32="Yes",5,0),0)) -> 26.4 | AL33: None | AM33: 02/13/2026
A34: TR-0027 | B34: ERHABOR | C34: ELAION | D34: 2028 | E34: 10 | F34: Active | G34: COM 1010 — Speech Communication | H34: Fall 2025 | I34: 61.2 | J34: INT 1700 — Understanding Operating Systems | K34: Fall 2025 | L34: 93.9 | AB34: 77.6 | AC34: 3.1 | AD34: C | AE34: 🟢 On Track | AF34: Tier 1 | AG34: ✅ Met | AH34: No | AI34: No | AJ34: → Stable | AK34: =IF(AB33="",0,IFERROR((100-AB33)*1.2+IF(AF33="Tier 3",20,IF(AF33="Tier 2",10,0))+IF(AH33="Yes",5,0),0)) -> 33.24 | AL34: None | AM34: 02/13/2026
A35: TR-0028 | B35: FERSNER | C35: KENNEDI | D35: 2028 | E35: 10 | F35: Active | G35: COM 1010 — Speech Communication | H35: Fall 2025 | I35: 72.6 | J35: INT 1700 — Understanding Operating Systems | K35: Fall 2025 | L35: 86.8 | O35: 73.33 | R35: 76.14 | AB35: 77.2 | AC35: 3.09 | AD35: C | AE35: 🟢 On Track | AF35: Tier 1 | AG35: ✅ Met | AH35: No | AI35: No | AJ35: → Stable | AK35: =IF(AB34="",0,IFERROR((100-AB34)*1.2+IF(AF34="Tier 3",20,IF(AF34="Tier 2",10,0))+IF(AH34="Yes",5,0),0)) -> 26.88 | AL35: None | AM35: 02/13/2026
A36: TR-0059 | B36: FORD | C36: CHASE | D36: 2028 | E36: 10 | F36: Active | G36: COM 1010 — Speech Communication | H36: Fall 2025 | I36: 47.2 | J36: INT 1700 — Understanding Operating Systems | K36: Fall 2025 | L36: 65 | AB36: 56.1 | AC36: 2.24 | AD36: F | AE36: 🔴 Not Progressing | AF36: Tier 3 | AG36: ❌ Below | AH36: No | AI36: No | AJ36: → Stable | AK36: =IF(AB35="",0,IFERROR((100-AB35)*1.2+IF(AF35="Tier 3",20,IF(AF35="Tier 2",10,0))+IF(AH35="Yes",5,0),0)) -> 27.36 | AL36: None | AM36: 02/13/2026
A37: TR-0029 | B37: FOSTER | C37: BRYANT | D37: 2028 | E37: 10 | F37: Active | G37: COM 1010 — Speech Communication | H37: Fall 2025 | I37: 87.1 | J37: INT 1700 — Understanding Operating Systems | K37: Fall 2025 | L37: 65 | O37: 77.14 | R37: 89.54 | AB37: 79.7 | AC37: 3.19 | AD37: C | AE37: 🟢 On Track | AF37: Tier 1 | AG37: ✅ Met | AH37: No | AI37: No | AJ37: → Stable | AK37: =IF(AB36="",0,IFERROR((100-AB36)*1.2+IF(AF36="Tier 3",20,IF(AF36="Tier 2",10,0))+IF(AH36="Yes",5,0),0)) -> 72.68 | AL37: None | AM37: 02/13/2026
A38: TR-0030 | B38: GOMEZ | C38: CHRISTIAN | D38: 2028 | E38: 10 | F38: Active | G38: COM 1010 — Speech Communication | H38: Fall 2025 | I38: 78.1 | J38: INT 1700 — Understanding Operating Systems | K38: Fall 2025 | L38: 89 | AB38: 83.5 | AC38: 3.34 | AD38: B | AE38: 🟢 On Track | AF38: Tier 1 | AG38: ✅ Met | AH38: No | AI38: No | AJ38: → Stable | AK38: =IF(AB37="",0,IFERROR((100-AB37)*1.2+IF(AF37="Tier 3",20,IF(AF37="Tier 2",10,0))+IF(AH37="Yes",5,0),0)) -> 24.36 | AL38: None | AM38: 02/13/2026
A39: TR-0031 | B39: JOHNSON | C39: LIAM | D39: 2028 | E39: 10 | F39: Active | G39: COM 1010 — Speech Communication | H39: Fall 2025 | I39: 91.3 | J39: INT 1700 — Understanding Operating Systems | K39: Fall 2025 | L39: 84.9 | O39: 90.91 | R39: 74.05 | AB39: 85.3 | AC39: 3.41 | AD39: B | AE39: 🟢 On Track | AF39: Tier 1 | AG39: ✅ Met | AH39: No | AI39: No | AJ39: → Stable | AK39: =IF(AB38="",0,IFERROR((100-AB38)*1.2+IF(AF38="Tier 3",20,IF(AF38="Tier 2",10,0))+IF(AH38="Yes",5,0),0)) -> 19.8 | AL39: None | AM39: 02/13/2026
A40: TR-0032 | B40: MONROE-HOOD | C40: JAHDAI | D40: 2028 | E40: 10 | F40: Active | G40: COM 1010 — Speech Communication | H40: Fall 2025 | I40: 58.3 | J40: INT 1700 — Understanding Operating Systems | K40: Fall 2025 | L40: 61.2 | O40: 88.57 | R40: 84.14 | AB40: 73.1 | AC40: 2.92 | AD40: C | AE40: 🟡 Watch | AF40: Tier 1/2 | AG40: ⚠️ Approaching | AH40: No | AI40: No | AJ40: → Stable | AK40: =IF(AB39="",0,IFERROR((100-AB39)*1.2+IF(AF39="Tier 3",20,IF(AF39="Tier 2",10,0))+IF(AH39="Yes",5,0),0)) -> 17.64 | AL40: None | AM40: 02/13/2026
A41: TR-0033 | B41: MORGAN | C41: ESSOON | D41: 2028 | E41: 10 | F41: Active | G41: COM 1010 — Speech Communication | H41: Fall 2025 | I41: 89.2 | J41: INT 1700 — Understanding Operating Systems | K41: Fall 2025 | L41: 95.3 | AB41: 92.2 | AC41: 3.69 | AD41: A | AE41: 🌟 Excelling | AF41: Tier 1 | AG41: ✅ Met | AH41: No | AI41: No | AJ41: → Stable | AK41: =IF(AB40="",0,IFERROR((100-AB40)*1.2+IF(AF40="Tier 3",20,IF(AF40="Tier 2",10,0))+IF(AH40="Yes",5,0),0)) -> 32.28 | AL41: None | AM41: 02/13/2026
A42: TR-0034 | B42: MOSES | C42: EMERIC | D42: 2028 | E42: 10 | F42: Active | G42: COM 1010 — Speech Communication | H42: Fall 2025 | I42: 77.5 | J42: INT 1700 — Understanding Operating Systems | K42: Fall 2025 | L42: 79.7 | O42: 73.33 | R42: 83.19 | AB42: 78.4 | AC42: 3.14 | AD42: C | AE42: 🟢 On Track | AF42: Tier 1 | AG42: ✅ Met | AH42: No | AI42: No | AJ42: → Stable | AK42: =IF(AB41="",0,IFERROR((100-AB41)*1.2+IF(AF41="Tier 3",20,IF(AF41="Tier 2",10,0))+IF(AH41="Yes",5,0),0)) -> 9.36 | AL42: None | AM42: 02/13/2026
A43: TR-0035 | B43: MUNGWA | C43: RODRIKARL | D43: 2028 | E43: 10 | F43: Active | G43: COM 1010 — Speech Communication | H43: Fall 2025 | I43: 83.2 | J43: INT 1700 — Understanding Operating Systems | K43: Fall 2025 | L43: 77.6 | O43: 87.62 | AB43: 82.8 | AC43: 3.31 | AD43: B | AE43: 🟢 On Track | AF43: Tier 1 | AG43: ✅ Met | AH43: No | AI43: No | AJ43: → Stable | AK43: =IF(AB42="",0,IFERROR((100-AB42)*1.2+IF(AF42="Tier 3",20,IF(AF42="Tier 2",10,0))+IF(AH42="Yes",5,0),0)) -> 25.92 | AL43: None | AM43: 02/13/2026
A44: TR-0036 | B44: NAVARRO-MARTINEZ | C44: MARTHA | D44: 2028 | E44: 10 | F44: Active | G44: COM 1010 — Speech Communication | H44: Fall 2025 | I44: 72.4 | J44: INT 1700 — Understanding Operating Systems | K44: Fall 2025 | L44: 70.2 | O44: 68.57 | R44: 65.8 | AB44: 69.2 | AC44: 2.77 | AD44: D | AE44: 🟡 Watch | AF44: Tier 1/2 | AG44: ⚠️ Approaching | AH44: No | AI44: No | AJ44: → Stable | AK44: =IF(AB43="",0,IFERROR((100-AB43)*1.2+IF(AF43="Tier 3",20,IF(AF43="Tier 2",10,0))+IF(AH43="Yes",5,0),0)) -> 20.64 | AL44: None | AM44: 02/13/2026
A45: TR-0037 | B45: SOLOMON | C45: GISELLE | D45: 2028 | E45: 10 | F45: Active | G45: COM 1010 — Speech Communication | H45: Fall 2025 | I45: 94.9 | J45: INT 1700 — Understanding Operating Systems | K45: Fall 2025 | L45: 75.4 | O45: 74.29 | R45: 87.25 | AB45: 83 | AC45: 3.32 | AD45: B | AE45: 🟢 On Track | AF45: Tier 1 | AG45: ✅ Met | AH45: No | AI45: No | AJ45: → Stable | AK45: =IF(AB44="",0,IFERROR((100-AB44)*1.2+IF(AF44="Tier 3",20,IF(AF44="Tier 2",10,0))+IF(AH44="Yes",5,0),0)) -> 36.96 | AL45: None | AM45: 02/13/2026
A46: TR-0038 | B46: WALTERS | C46: JAEV'HAN | D46: 2028 | E46: 10 | F46: Active | G46: COM 1010 — Speech Communication | H46: Fall 2025 | I46: 80.2 | J46: INT 1700 — Understanding Operating Systems | K46: Fall 2025 | L46: 88.2 | O46: 75.24 | R46: 64.98 | AB46: 77.2 | AC46: 3.09 | AD46: C | AE46: 🟢 On Track | AF46: Tier 1 | AG46: ✅ Met | AH46: No | AI46: No | AJ46: → Stable | AK46: =IF(AB45="",0,IFERROR((100-AB45)*1.2+IF(AF45="Tier 3",20,IF(AF45="Tier 2",10,0))+IF(AH45="Yes",5,0),0)) -> 20.4 | AL46: None | AM46: 02/13/2026
A47: TR-0039 | B47: WASHINGTON | C47: JOSHUA | D47: 2028 | E47: 10 | F47: Active | G47: COM 1010 — Speech Communication | H47: Fall 2025 | I47: 79.4 | J47: INT 1700 — Understanding Operating Systems | K47: Fall 2025 | L47: 71 | O47: 68.57 | R47: 77.07 | AB47: 74 | AC47: 2.96 | AD47: C | AE47: 🟡 Watch | AF47: Tier 1/2 | AG47: ⚠️ Approaching | AH47: No | AI47: No | AJ47: → Stable | AK47: =IF(AB46="",0,IFERROR((100-AB46)*1.2+IF(AF46="Tier 3",20,IF(AF46="Tier 2",10,0))+IF(AH46="Yes",5,0),0)) -> 27.36 | AL47: None | AM47: 02/13/2026
A48: TR-0040 | B48: WHITAKER | C48: XION | D48: 2028 | E48: 10 | F48: Active | G48: COM 1010 — Speech Communication | H48: Fall 2025 | I48: 90.2 | J48: INT 1700 — Understanding Operating Systems | K48: Fall 2025 | L48: 85.1 | O48: 83.81 | R48: 83.86 | AB48: 85.7 | AC48: 3.43 | AD48: B | AE48: 🟢 On Track | AF48: Tier 1 | AG48: ✅ Met | AH48: No | AI48: No | AJ48: → Stable | AK48: =IF(AB47="",0,IFERROR((100-AB47)*1.2+IF(AF47="Tier 3",20,IF(AF47="Tier 2",10,0))+IF(AH47="Yes",5,0),0)) -> 31.2 | AL48: None | AM48: 02/13/2026
A49: TR-0041 | B49: WHITTED | C49: BRAYLEN | D49: 2028 | E49: 10 | F49: Active | G49: COM 1010 — Speech Communication | H49: Fall 2025 | I49: 80.2 | J49: INT 1700 — Understanding Operating Systems | K49: Fall 2025 | L49: 71.4 | O49: 90.91 | R49: 94.77 | AB49: 84.3 | AC49: 3.37 | AD49: B | AE49: 🟢 On Track | AF49: Tier 1 | AG49: ✅ Met | AH49: No | AI49: No | AJ49: → Stable | AK49: =IF(AB48="",0,IFERROR((100-AB48)*1.2+IF(AF48="Tier 3",20,IF(AF48="Tier 2",10,0))+IF(AH48="Yes",5,0),0)) -> 17.16 | AL49: None | AM49: 02/13/2026
A50: TR-0042 | B50: AKINSANYA | C50: TIARAOLUWA | D50: 2029 | E50: 9 | F50: Active | G50: INT 1010 — Introduction to Information Technology | H50: Fall 2025 | I50: 60.9 | AB50: 60.9 | AC50: 2.44 | AD50: D | AE50: 🟠 At Risk | AF50: Tier 2 | AG50: ❌ Below | AH50: No | AI50: No | AJ50: → Stable | AK50: =IF(AB49="",0,IFERROR((100-AB49)*1.2+IF(AF49="Tier 3",20,IF(AF49="Tier 2",10,0))+IF(AH49="Yes",5,0),0)) -> 18.84 | AL50: None | AM50: 02/13/2026
A51: TR-0043 | B51: ATKINS | C51: PEYTON | D51: 2029 | E51: 9 | F51: Active | G51: INT 1010 — Introduction to Information Technology | H51: Fall 2025 | I51: 89.3 | AB51: 89.3 | AC51: 3.57 | AD51: B | AE51: 🟢 On Track | AF51: Tier 1 | AG51: ✅ Met | AH51: No | AI51: No | AJ51: → Stable | AK51: =IF(AB50="",0,IFERROR((100-AB50)*1.2+IF(AF50="Tier 3",20,IF(AF50="Tier 2",10,0))+IF(AH50="Yes",5,0),0)) -> 56.92 | AL51: None | AM51: 02/13/2026
A52: TR-0044 | B52: BELCHER | C52: MALACHI | D52: 2029 | E52: 9 | F52: Active | G52: INT 1010 — Introduction to Information Technology | H52: Fall 2025 | I52: 65.3 | AB52: 65.3 | AC52: 2.61 | AD52: D | AE52: 🟡 Watch | AF52: Tier 1/2 | AG52: ⚠️ Approaching | AH52: No | AI52: No | AJ52: → Stable | AK52: =IF(AB51="",0,IFERROR((100-AB51)*1.2+IF(AF51="Tier 3",20,IF(AF51="Tier 2",10,0))+IF(AH51="Yes",5,0),0)) -> 12.84 | AL52: None | AM52: 02/13/2026
A53: TR-0045 | B53: DUMAS | C53: ADDISON | D53: 2029 | E53: 9 | F53: Active | G53: INT 1010 — Introduction to Information Technology | H53: Fall 2025 | I53: 78.8 | AB53: 78.8 | AC53: 3.15 | AD53: C | AE53: 🟢 On Track | AF53: Tier 1 | AG53: ✅ Met | AH53: No | AI53: No | AJ53: → Stable | AK53: =IF(AB52="",0,IFERROR((100-AB52)*1.2+IF(AF52="Tier 3",20,IF(AF52="Tier 2",10,0))+IF(AH52="Yes",5,0),0)) -> 41.64 | AL53: None | AM53: 02/13/2026
A54: TR-0046 | B54: HARRISON | C54: MACKENZIE | D54: 2029 | E54: 9 | F54: Active | G54: INT 1010 — Introduction to Information Technology | H54: Fall 2025 | I54: 78.8 | AB54: 78.8 | AC54: 3.15 | AD54: C | AE54: 🟢 On Track | AF54: Tier 1 | AG54: ✅ Met | AH54: No | AI54: No | AJ54: → Stable | AK54: =IF(AB53="",0,IFERROR((100-AB53)*1.2+IF(AF53="Tier 3",20,IF(AF53="Tier 2",10,0))+IF(AH53="Yes",5,0),0)) -> 25.44 | AL54: None | AM54: 02/13/2026
A55: TR-0047 | B55: HARVEY | C55: MEZRAH | D55: 2029 | E55: 9 | F55: Active | G55: INT 1010 — Introduction to Information Technology | H55: Fall 2025 | I55: 80.4 | AB55: 80.4 | AC55: 3.22 | AD55: B | AE55: 🟢 On Track | AF55: Tier 1 | AG55: ✅ Met | AH55: No | AI55: No | AJ55: → Stable | AK55: =IF(AB54="",0,IFERROR((100-AB54)*1.2+IF(AF54="Tier 3",20,IF(AF54="Tier 2",10,0))+IF(AH54="Yes",5,0),0)) -> 25.44 | AL55: None | AM55: 02/13/2026
A56: TR-0048 | B56: HERBERT | C56: HYON | D56: 2029 | E56: 9 | F56: Active | G56: INT 1010 — Introduction to Information Technology | H56: Fall 2025 | I56: 69.2 | AB56: 69.2 | AC56: 2.77 | AD56: D | AE56: 🟡 Watch | AF56: Tier 1/2 | AG56: ⚠️ Approaching | AH56: No | AI56: No | AJ56: → Stable | AK56: =IF(AB55="",0,IFERROR((100-AB55)*1.2+IF(AF55="Tier 3",20,IF(AF55="Tier 2",10,0))+IF(AH55="Yes",5,0),0)) -> 23.52 | AL56: None | AM56: 02/13/2026
A57: TR-0049 | B57: JOSEPH-ALEXANDER | C57: SHILOH | D57: 2029 | E57: 9 | F57: Active | G57: INT 1010 — Introduction to Information Technology | H57: Fall 2025 | I57: 85.6 | AB57: 85.6 | AC57: 3.42 | AD57: B | AE57: 🟢 On Track | AF57: Tier 1 | AG57: ✅ Met | AH57: No | AI57: No | AJ57: → Stable | AK57: =IF(AB56="",0,IFERROR((100-AB56)*1.2+IF(AF56="Tier 3",20,IF(AF56="Tier 2",10,0))+IF(AH56="Yes",5,0),0)) -> 36.96 | AL57: None | AM57: 02/13/2026
A58: TR-0050 | B58: LASHLEY | C58: AVA | D58: 2029 | E58: 9 | F58: Active | G58: INT 1010 — Introduction to Information Technology | H58: Fall 2025 | I58: 83.9 | AB58: 83.9 | AC58: 3.36 | AD58: B | AE58: 🟢 On Track | AF58: Tier 1 | AG58: ✅ Met | AH58: No | AI58: No | AJ58: → Stable | AK58: =IF(AB57="",0,IFERROR((100-AB57)*1.2+IF(AF57="Tier 3",20,IF(AF57="Tier 2",10,0))+IF(AH57="Yes",5,0),0)) -> 17.28 | AL58: None | AM58: 02/13/2026
A59: TR-0051 | B59: LOWERY | C59: CADEN | D59: 2029 | E59: 9 | F59: Active | G59: INT 1010 — Introduction to Information Technology | H59: Fall 2025 | I59: 100 | AB59: 100 | AC59: 4 | AD59: A | AE59: 🌟 Excelling | AF59: Tier 1 | AG59: ✅ Met | AH59: No | AI59: No | AJ59: → Stable | AK59: =IF(AB58="",0,IFERROR((100-AB58)*1.2+IF(AF58="Tier 3",20,IF(AF58="Tier 2",10,0))+IF(AH58="Yes",5,0),0)) -> 19.32 | AL59: None | AM59: 02/13/2026
A60: TR-0052 | B60: ONUOSA | C60: NICHOLAS | D60: 2029 | E60: 9 | F60: Active | G60: INT 1010 — Introduction to Information Technology | H60: Fall 2025 | I60: 70.4 | AB60: 70.4 | AC60: 2.82 | AD60: C | AE60: 🟡 Watch | AF60: Tier 1/2 | AG60: ⚠️ Approaching | AH60: No | AI60: No | AJ60: → Stable | AK60: =IF(AB59="",0,IFERROR((100-AB59)*1.2+IF(AF59="Tier 3",20,IF(AF59="Tier 2",10,0))+IF(AH59="Yes",5,0),0)) -> 0 | AL60: None | AM60: 02/13/2026
A61: TR-0053 | B61: ROBINSON | C61: MATTHEW | D61: 2029 | E61: 9 | F61: Active | G61: INT 1010 — Introduction to Information Technology | H61: Fall 2025 | I61: 99.5 | AB61: 99.5 | AC61: 3.98 | AD61: A | AE61: 🌟 Excelling | AF61: Tier 1 | AG61: ✅ Met | AH61: No | AI61: No | AJ61: → Stable | AK61: =IF(AB60="",0,IFERROR((100-AB60)*1.2+IF(AF60="Tier 3",20,IF(AF60="Tier 2",10,0))+IF(AH60="Yes",5,0),0)) -> 35.52 | AL61: None | AM61: 02/13/2026
... A65: TR-0057 | B65: VIDAL | C65: JOSHUA | D65: 2029 | E65: 9 | F65: Active | G65: INT 1010 — Introduction to Information Technology | H65: Fall 2025 | I65: 69.3 | AB65: 69.3 | AC65: 2.77 | AD65: D | AE65: 🟡 Watch | AF65: Tier 1/2 | AG65: ⚠️ Approaching | AH65: No | AI65: No | AJ65: → Stable | AK65: =IF(AB64="",0,IFERROR((100-AB64)*1.2+IF(AF64="Tier 3",20,IF(AF64="Tier 2",10,0))+IF(AH64="Yes",5,0),0)) -> 33.84 | AL65: None | AM65: 02/13/2026
A67: ACTIVE TOTALS | B67: 59 | AB67: =AVERAGE(AB6:AB64) -> 82.717241
A69: 🎓 GRADUATED ALUMNI — CLASS OF 2025 (Accounts Closed — Retained for Reporting)
A70: TR-G001 | B70: SCOTT | C70: SANAA | D70: 2025 | E70: 12 | F70: 🔒 Graduated | G70: BIO 1110 | H70: Fall 2024 | I70: 89 | J70: BIO 1120 | K70: Fall 2024 | L70: 74 | M70: PHL 1010 | N70: Fall 2024 | O70: 80 | P70: INT 1540 | Q70: Fall 2024 | R70: 94.5 | S70: INT 1620 | T70: Spring 2025 | U70: 85.2 | V70: INT 2600 | W70: Spring 2025 | X70: 77 | Y70: EGL 1010 | Z70: Spring 2025 | AA70: 79.5 | AB70: 82.7 | AC70: 3 | AD70: B | AE70: 🎓 Graduated | AF70: — | AG70: ✅ Met | AH70: No | AI70: No | AJ70: 🎓 | AK70: 0 | AL70: None | AM70: 05/17/2025
A71: TR-G002 | B71: BEZEZUH | C71: ACHAKENG | D71: 2025 | E71: 12 | F71: 🔒 Graduated | G71: PSY 1010 | H71: Fall 2024 | I71: 86.5 | J71: MAT 1350 | K71: Fall 2024 | L71: 69.5 | M71: EGL 1010 | N71: Fall 2024 | O71: 78.5 | P71: INT 2688 | Q71: Fall 2024 | R71: 92.5 | S71: INT 2840 | T71: Spring 2025 | U71: 83 | V71: EGL 1010 II | W71: Spring 2025 | X71: 84.5 | Y71: INT 2715 | Z71: Spring 2025 | AA71: 91.5 | AB71: 83.7 | AC71: 3.2 | AD71: B | AE71: 🎓 Graduated | AF71: — | AG71: ✅ Met | AH71: No | AI71: No | AJ71: 🎓 | AK71: 0 | AL71: None | AM71: 05/17/2025
A72: TR-G003 | B72: ONUOSA | C72: NAOMI | D72: 2025 | E72: 12 | F72: 🔒 Graduated | G72: PSY 1010 | H72: Fall 2024 | I72: 89 | J72: MAT 1350 | K72: Fall 2024 | L72: 83.5 | M72: INT 2200 | N72: Fall 2024 | O72: 93.5 | P72: EGL 1010 | Q72: Fall 2024 | R72: 76 | S72: INT 2840 | T72: Spring 2025 | U72: 93 | V72: INT 2050 | W72: Spring 2025 | X72: 92 | Y72: EGL 1340 | Z72: Spring 2025 | AA72: 80 | AB72: 86.7 | AC72: 3.4 | AD72: B | AE72: 🎓 Graduated | AF72: — | AG72: ✅ Met | AH72: No | AI72: No | AJ72: 🎓 | AK72: 0 | AL72: None | AM72: 05/17/2025
A73: TR-G004 | B73: PERRY | C73: XAVIER | D73: 2025 | E73: 12 | F73: 🔒 Graduated | G73: PSY 1010 | H73: Fall 2024 | I73: 91.5 | J73: MAT 1350 | K73: Fall 2024 | L73: 82 | M73: INT 2200 | N73: Fall 2024 | O73: 96.5 | P73: EGL 1010 | Q73: Fall 2024 | R73: 93.5 | S73: INT 2840 | T73: Spring 2025 | U73: 94 | V73: INT 2050 | W73: Spring 2025 | X73: 92 | Y73: EGL 1340 | Z73: Spring 2025 | AA73: 91 | AB73: 91.5 | AC73: 3.7 | AD73: A | AE73: 🎓 Graduated | AF73: — | AG73: ✅ Met | AH73: No | AI73: No | AJ73: 🎓 | AK73: 0 | AL73: None | AM73: 05/17/2025
A74: TR-G005 | B74: RASHEED | C74: WARIZ | D74: 2025 | E74: 12 | F74: 🔒 Graduated | G74: PSY 1010 | H74: Fall 2024 | I74: 93 | J74: MAT 1350 | K74: Fall 2024 | L74: 85 | M74: INT 2200 | N74: Fall 2024 | O74: 98 | P74: EGL 1010 | Q74: Fall 2024 | R74: 98 | S74: INT 2840 | T74: Spring 2025 | U74: 95 | V74: INT 2050 | W74: Spring 2025 | X74: 96 | Y74: EGL 1340 | Z74: Spring 2025 | AA74: 93 | AB74: 94 | AC74: 3.8 | AD74: A | AE74: 🎓 Graduated | AF74: — | AG74: ✅ Met | AH74: No | AI74: No | AJ74: 🎓 | AK74: 0 | AL74: None | AM74: 05/17/2025
A76: GRAND TOTAL (Active + Alumni) | B76: 64

Sheet Command Center
A1: ⬅ NAVIGATE:
A2: ElevateED — COMMAND CENTER
A3: Talent Ready IT Program | Largo High School | Prince George's Community College
A4: Maryland Blueprint for Maryland's Future | CONFIDENTIAL — FERPA PROTECTED | Generated: February 13, 2026 03:35 PM
A5: All Systems Integrated | Historical Trends Active | Alumni Tracked | February 13, 2026
A6: =COUNTA('Student Master'!A6:A64) -> 59 | D6: 64 | G6: 4 | J6: 10 | M6: 1200+
A7: ACTIVE STUDENTS | D7: TOTAL ENROLLED | G7: COHORTS | J7: ACTIVE COURSES | M7: LIVE FORMULAS
A9: COHORT PERFORMANCE MATRIX — ALL 4 COHORTS | FALL 2025 + SPRING 2026
A10: Cohort | B10: Grade | C10: Students | D10: Avg Grade | E10: On Track | F10: Watch | G10: At Risk | H10: Not Prog | I10: Honor Roll | J10: CCR Met % | K10: PGCC Courses
A11: Class of 2026 | B11: 12th Senior | C11: 17 | D11: =AVERAGEIF('Student Master'!D6:D64,2026,'Student Master'!AB6:AB64) -> 93.764706 | E11: =COUNTIFS('Student Master'!D6:D64,2026,'Student Master'!AE6:AE64,"On Track") -> 0 | F11: =COUNTIFS('Student Master'!D6:D64,2026,'Student Master'!AE6:AE64,"Watch") -> 0 | G11: =COUNTIFS('Student Master'!D6:D64,2026,'Student Master'!AE6:AE64,"At Risk") -> 0 | H11: =COUNTIFS('Student Master'!D6:D64,2026,'Student Master'!AE6:AE64,"Not Progressing") -> 0 | I11: =COUNTIFS('Student Master'!D6:D64,2026,'Student Master'!AB6:AB64,">="&90) -> 13 | J11: =IFERROR(COUNTIFS('Student Master'!D6:D64,2026,'Student Master'!AG6:AG64,"✅ Met")/COUNTIF('Student Master'!D6:D64,2026),0) -> 1 | K11: Calculus, Psychology, English, Art + INT 2840, INT 2310, EGL 1340
A12: Class of 2027 | B12: 11th Junior | C12: 6 | D12: =AVERAGEIF('Student Master'!D6:D64,2027,'Student Master'!AB6:AB64) -> 76.35 | E12: =COUNTIFS('Student Master'!D6:D64,2027,'Student Master'!AE6:AE64,"On Track") -> 0 | F12: =COUNTIFS('Student Master'!D6:D64,2027,'Student Master'!AE6:AE64,"Watch") -> 0 | G12: =COUNTIFS('Student Master'!D6:D64,2027,'Student Master'!AE6:AE64,"At Risk") -> 0 | H12: =COUNTIFS('Student Master'!D6:D64,2027,'Student Master'!AE6:AE64,"Not Progressing") -> 0 | I12: =COUNTIFS('Student Master'!D6:D64,2027,'Student Master'!AB6:AB64,">="&90) -> 0 | J12: =IFERROR(COUNTIFS('Student Master'!D6:D64,2027,'Student Master'!AG6:AG64,"✅ Met")/COUNTIF('Student Master'!D6:D64,2027),0) -> 0.66666667 | K12: BIO 1110, BIO 1120, INT 1550
A13: Class of 2028 | B13: 10th Sophomore | C13: 20 | D13: =AVERAGEIF('Student Master'!D6:D64,2028,'Student Master'!AB6:AB64) -> 78.115 | E13: =COUNTIFS('Student Master'!D6:D64,2028,'Student Master'!AE6:AE64,"On Track") -> 0 | F13: =COUNTIFS('Student Master'!D6:D64,2028,'Student Master'!AE6:AE64,"Watch") -> 0 | G13: =COUNTIFS('Student Master'!D6:D64,2028,'Student Master'!AE6:AE64,"At Risk") -> 0 | H13: =COUNTIFS('Student Master'!D6:D64,2028,'Student Master'!AE6:AE64,"Not Progressing") -> 0 | I13: =COUNTIFS('Student Master'!D6:D64,2028,'Student Master'!AB6:AB64,">="&90) -> 1 | J13: =IFERROR(COUNTIFS('Student Master'!D6:D64,2028,'Student Master'!AG6:AG64,"✅ Met")/COUNTIF('Student Master'!D6:D64,2028),0) -> 0.7 | K13: COM 1010, INT 1700
A14: Class of 2029 | B14: 9th Freshman | C14: 16 | D14: =AVERAGEIF('Student Master'!D6:D64,2029,'Student Master'!AB6:AB64) -> 78.88 | E14: =COUNTIFS('Student Master'!D6:D64,2029,'Student Master'!AE6:AE64,"On Track") -> 0 | F14: =COUNTIFS('Student Master'!D6:D64,2029,'Student Master'!AE6:AE64,"Watch") -> 0 | G14: =COUNTIFS('Student Master'!D6:D64,2029,'Student Master'!AE6:AE64,"At Risk") -> 0 | H14: =COUNTIFS('Student Master'!D6:D64,2029,'Student Master'!AE6:AE64,"Not Progressing") -> 0 | I14: =COUNTIFS('Student Master'!D6:D64,2029,'Student Master'!AB6:AB64,">="&90) -> 2 | J14: =IFERROR(COUNTIFS('Student Master'!D6:D64,2029,'Student Master'!AG6:AG64,"✅ Met")/COUNTIF('Student Master'!D6:D64,2029),0) -> 0.6 | K14: INT 1010
A15: Class of 2025 🎓 | B15: Graduated | C15: 5 | D15: 87.7 | E15: 5 | F15: 0 | G15: 0 | H15: 0 | I15: 4 | J15: 1 | K15: 🎓 Accounts closed
A17: MTSS TIER DISTRIBUTION
A18: Tier | B18: Description | C18: Range | D18: Count | E18: % of Total | F18: Action
A19: Tier 1 | B19: On Track | C19: ≥ 75% | D19: =COUNTIF('Student Master'!AF6:AF64,"Tier 1") -> 44 | E19: =IFERROR(D18/COUNTA('Student Master'!AF6:AF64),0) -> 0 | F19: Standard monitoring
A20: Tier 1/2 | B20: Watch | C20: 65–74% | D20: =COUNTIF('Student Master'!AF6:AF64,"Tier 1/2") -> 12 | E20: =IFERROR(D19/COUNTA('Student Master'!AF6:AF64),0) -> 0.74576271 | F20: Increased monitoring
A21: Tier 2 | B21: At Risk | C21: 60–64% | D21: =COUNTIF('Student Master'!AF6:AF64,"Tier 2") -> 1 | E21: =IFERROR(D20/COUNTA('Student Master'!AF6:AF64),0) -> 0.20338983 | F21: SIT meeting, tutoring
A22: Tier 3 | B22: Not Progressing | C22: < 60% | D22: =COUNTIF('Student Master'!AF6:AF64,"Tier 3") -> 1 | E22: =IFERROR(D21/COUNTA('Student Master'!AF6:AF64),0) -> 0.016949153 | F22: Immediate intervention
A25: ⚠ EARLY WARNING ALERTS — Immediate Attention Required
A26: Priority | B26: Student ID | C26: Name | D26: Cohort | E26: Course | F26: Current Avg | G26: Status | H26: Days | I26: Assigned To | J26: Action
A27: 🔴 CRITICAL | B27: TR-0059 | C27: FORD, CHASE | D27: 2028 | E27: COM 1010 | F27: 47.2 | G27: Not Progressing | H27: 14 | I27: C. James | J27: Daily check-in + parent contact
A28: 🔴 CRITICAL | B28: TR-0017 | C28: BYFIELD, KIMANI | D28: 2027 | E28: INT 1550 | F28: 57.4 | G28: Not Progressing | H28: 10 | I28: C. James | J28: SIT meeting 2/18
A29: 🔴 CRITICAL | B29: TR-0023 | C29: AHETO, EDWIN | D29: 2028 | E29: COM 1010 | F29: 57 | G29: Not Progressing | H29: 12 | I29: C. James | J29: Peer tutoring assigned
A30: 🔴 CRITICAL | B30: TR-0032 | C30: MONROE-HOOD, JAHDAI | D30: 2028 | E30: COM 1010 | F30: 58.3 | G30: Not Progressing | H30: 8 | I30: C. James | J30: Weekly progress contract
A31: 🟠 HIGH | B31: TR-0042 | C31: AKINSANYA, TIARAOLUWA | D31: 2029 | E31: INT 1010 | F31: 60.9 | G31: At Risk | H31: 5 | I31: C. James | J31: Study plan created
A32: 🟠 HIGH | B32: TR-0027 | C32: ERHABOR, ELAION | D32: 2028 | E32: COM 1010 | F32: 61.2 | G32: At Risk | H32: 7 | I32: C. James | J32: Monitor weekly
A33: 🟡 WATCH | B33: TR-0019 | C33: LAMBRIGHT, KADYN | D33: 2027 | E33: INT 1550 | F33: 64.2 | G33: Watch | H33: 3 | I33: C. James | J33: Check-in conversation
A34: 🟡 WATCH | B34: TR-0044 | C34: BELCHER, MALACHI | D34: 2029 | E34: INT 1010 | F34: 65.3 | G34: Watch | H34: 2 | I34: C. James | J34: Attendance check

Sheet 📍 Navigation Hub
A1: ⬅ QUICK JUMP: | B1: ⚡ Command | C1: 👥 2026 | D1: 👥 2027 | E1: 👥 2028 | F1: 👥 2029 | G1: 📊 Master
A2: ElevateED — 📍 NAVIGATION HUB
A3: Talent Ready IT Program | Largo High School | Prince George's Community College
A4: Click any sheet name to jump directly | February 13, 2026
A6: 59 | B6: 5 | C6: 64 | D6: 4 | E6: 10
A7: Active | B7: Alumni | C7: Total | D7: Cohorts | E7: Courses
A9: 🔐 SECURITY
A10: 1 | B10: Access Control | C10: RBAC, FERPA, status change permissions | D10: ✅
A12: 📊 CORE DATA
A13: 2 | B13: Student Master | C13: 59 active + 5 alumni, 39 cols | D13: ✅
A14: 3 | B14: Command Center | C14: KPIs, cohort matrix, early warnings | D14: ✅
A15: 4 | B15: 📍 Navigation Hub | C15: ← YOU ARE HERE | D15: ✅
A16: 5 | B16: Academic Calendar | C16: PGCC + PGCPS synced | D16: ✅
A18: 📈 GRADES (Current First, Prior Hidden)
A19: 6 | B19: Cohort 2026 — Grades | C19: 17 seniors | Spring 2026 current, Fall 2025 grouped | D19: ✅
A20: 7 | B20: Cohort 2027 — Grades | C20: 6 juniors | Spring 2026 current, 3 prior semesters grouped | D20: ✅
A21: 8 | B21: Cohort 2028 — Grades | C21: 20 sophs | Spring 2026 current, Fall+Spring prior grouped | D21: ✅
A22: 9 | B22: Cohort 2029 — Grades | C22: 16 freshmen | Spring 2026 current, Fall 2025 grouped | D22: ✅
A24: 📊 HISTORICAL TRENDS
A25: 10 | B25: Alumni — Class of 2025 | C25: 5 grads, weekly detail, closed | D25: 🔧
A26: 11 | B26: History — Cohort 2026 | C26: Fall 2025 baseline + trends | D26: 🔧
A27: 12 | B27: History — Cohort 2027 | C27: 3 prior semesters | D27: 🔧
A28: 13 | B28: History — Cohort 2028 | C28: 2 prior semesters | D28: 🔧
A29: 14 | B29: History — Cohort 2029 | C29: Fall 2025 baseline | D29: 🔧
A30: 15 | B30: Program Trend Summary | C30: All cohorts side-by-side | D30: 🔧
A31: 16 | B31: Semester Grade Archive | C31: Flat file, every grade ever | D31: 🔧
A33: 🔍 ANALYTICS
A34: 17 | B34: Predictive Analytics | C34: 6-factor risk scores | D34: ✅
A35: 18 | B35: Executive Dashboard | C35: WoW/MoM/QoQ | D35: ✅
A36: 19 | B36: Grade Velocity | C36: Week-over-week Δ | D36: ✅
A37: 20 | B37: Course Performance | C37: 10 courses | D37: ✅
A38: 21 | B38: Longitudinal Analytics | C38: Year-over-year | D38: ✅
A40: 🛡️ COMPLIANCE
A41: 22 | B41: MTSS Tracker | C41: Tier tracking | D41: ✅
A42: 23 | B42: Intervention Planner | C42: SIT plans | D42: ✅
A43: 24 | B43: Compliance Center | C43: FERPA audit | D43: ✅
A44: 25 | B44: Blueprint Metrics | C44: Pillar 3+4 | D44: ✅
A45: 26 | B45: IEP Monitoring | C45: 2 students, 8 goals | D45: ✅
A47: 👪 PARENT & STUDENT
A48: 27 | B48: Parent Engagement | C48: 59 families | D48: ✅
A49: 28 | B49: Parent Contacts | C49: Email lookup | D49: ✅
A50: 29 | B50: Email Log | C50: FERPA disclosure tracking | D50: ✅
A51: 30 | B51: Student Portal | C51: Self-service grades | D51: ✅
A53: 📋 PROGRAM
A54: 31 | B54: Assignment Grades | C54: INT 2840 decomposition | D54: ✅
A55: 32 | B55: Syllabus Calendar | C55: 42 assignments | D55: ✅
A56: 33 | B56: Peer Tutoring | C56: 8 matches | D56: ✅
A57: 34 | B57: Cert Prep Tracker | C57: 6 certs | D57: ✅
A58: 35 | B58: Resource Planning | C58: Budget | D58: ✅
A59: 36 | B59: Budget Forecast | C59: 4-year | D59: ✅
A61: ⚙️ SYSTEM
A62: 37 | B62: ASI Recommendations | C62: 15 enhancements | D62: ✅
A63: 38 | B63: System Map | C63: All sheets | D63: ✅
A64: 39 | B64: Brand Guide | C64: Colors + fonts | D64: ✅
A65: 40 | B65: How To Use | C65: User guide | D65: ✅
A66: 41 | B66: Audit Log | C66: Access tracking | D66: ✅
A68: 📝 STUDENT ASSIGNMENT TRACKERS
A69: 📋 Student Assignments — 2026 | B69: Cohort 2026 — per-student assignment grades inline with syllabus
A70: 📋 Student Assignments — 2027 | B70: Cohort 2027 — per-student assignment grades inline with syllabus
A71: 📋 Student Assignments — 2028 | B71: Cohort 2028 — per-student assignment grades inline with syllabus
A72: 📋 Student Assignments — 2029 | B72: Cohort 2029 — per-student assignment grades inline with syllabus

Sheet Academic Calendar
A1: ⬅ NAVIGATE:
A2: ElevateED — ACADEMIC CALENDAR — PGCC + PGCPS SYNCHRONIZED
A3: Talent Ready IT Program | Largo High School | Prince George's Community College
A4: Maryland Blueprint for Maryland's Future | CONFIDENTIAL — FERPA PROTECTED | February 13, 2026 05:39 PM
A5: Fall 2025 + Spring 2026 | Week numbers aligned to PGCC 15-week Terms | Grades due every Thursday by 2:00 PM
A6: Date | B6: Day | C6: Event | D6: Source | E6: Type | F6: PGCC Week | G6: ElevateED Week | H6: Impact on Grades | I6: Action Required | J6: Notes
A7: FALL 2025 SEMESTER
A8: 2025-08-18 | B8: Mon | C8: PGCC Fall 2025 classes BEGIN (Term 1, 15-week) | D8: PGCC | E8: 🟢 Semester Start | F8: W1 | G8: W1 | H8: Normal entry | I8: Enter grades
A9: 2025-09-01 | B9: Mon | C9: Labor Day — COLLEGE & PGCPS CLOSED | D9: Both | E9: 🔴 Holiday | F9: — | G9: — | H9: No grades this week | I9: Skip week
A10: 2025-10-13 | B10: Mon | C10: Columbus Day — PGCPS Closed / PGCC Open | D10: PGCPS | E10: 🟡 Split | F10: W9 | G10: W9 | H10: Normal entry | I10: Enter grades
A11: 2025-11-03 | B11: Mon | C11: PGCPS End of Q1 — Early Dismissal | D11: PGCPS | E11: 🟡 Grading Day | F11: W12 | G11: W12 | H11: Normal entry | I11: Enter grades
A12: 2025-11-11 | B12: Tue | C12: Veterans Day — PGCPS Closed / PGCC Open | D12: PGCPS | E12: 🟡 Split | F12: W13 | G12: W13 | H12: Normal entry | I12: Enter grades
A13: 2025-11-24 | B13: Mon | C13: THANKSGIVING BREAK BEGINS | D13: Both | E13: 🔴 Break | F13: — | G13: — | H13: No grades this week | I13: Skip week
A14: 2025-12-01 | B14: Mon | C14: Classes resume from Thanksgiving | D14: Both | E14: 🟢 Resume | F14: W15 | G14: W15 | H14: Normal entry | I14: Enter grades
A15: 2025-12-08 | B15: Mon | C15: PGCC Finals BEGIN | D15: PGCC | E15: 🔴 Finals | F15: W16 | G15: W16 | H15: Final grades | I15: Enter grades
A16: 2025-12-12 | B16: Fri | C16: PGCC Finals END — Fall 2025 Complete | D16: PGCC | E16: 🔴 Finals End | F16: W16 | G16: W16 | H16: Final grades | I16: Enter grades
A17: 2025-12-22 | B17: Mon | C17: PGCPS Winter Break begins | D17: PGCPS | E17: 🔴 Break | F17: — | G17: — | H17: No grades | I17: —
A18: SPRING 2026 SEMESTER
A19: 2026-01-20 | B19: Tue | C19: PGCC Spring 2026 classes BEGIN (Term 1, 15-week) | D19: PGCC | E19: 🟢 Semester Start | F19: W1 | G19: W1 | H19: Normal entry | I19: Enter grades
A20: 2026-01-19 | B20: Mon | C20: MLK Jr. Day — COLLEGE & PGCPS CLOSED | D20: Both | E20: 🔴 Holiday | F20: — | G20: — | H20: No grades this week | I20: Skip week
A21: 2026-01-26 | B21: Mon | C21: PGCPS End of Q2 — Early Dismissal | D21: PGCPS | E21: 🟡 Grading Day | F21: W1 | G21: W1 | H21: Normal entry | I21: Enter grades
A22: 2026-02-01 | B22: Sun | C22: Fall 2026 nursing petitioning deadline | D22: PGCC | E22: 📋 Admin | F22: W2 | G22: W2 | H22: Normal entry | I22: Enter grades
A23: 2026-02-06 | B23: Fri | C23: Last day credit/audit change (Term 1) | D23: PGCC | E23: 📋 Admin | F23: W3 | G23: W3 | H23: Normal entry | I23: Enter grades
A24: 2026-02-13 | B24: Fri | C24: PGCPS Teacher Planning — Early Dismissal | D24: PGCPS | E24: 🟡 Half Day | F24: W4 | G24: W4 | H24: Normal entry | I24: Enter grades
A25: 2026-02-16 | B25: Mon | C25: Presidents Day — COLLEGE & PGCPS CLOSED | D25: Both | E25: 🔴 Holiday | F25: — | G25: — | H25: No grades this week | I25: Skip week
A26: 2026-02-17 | B26: Tue | C26: PGCPS: First Day of Ramadan | D26: PGCPS | E26: 📋 Note | F26: W4 | G26: W4 | H26: Normal entry | I26: Enter grades
A27: 2026-03-05 | B27: Thu | C27: Last day withdraw Term 2 (7-week accel) | D27: PGCC | E27: 📋 Admin | F27: W7 | G27: W7 | H27: Normal entry | I27: Enter grades
A28: 2026-03-09 | B28: Mon | C28: PGCC SPRING BREAK BEGINS | D28: PGCC | E28: 🔴 Break | F28: W7 | G28: W7 | H28: Normal entry | I28: Enter grades
A29: 2026-03-16 | B29: Mon | C29: PGCC classes resume / Term 4 begins | D29: PGCC | E29: 🟢 Resume | F29: W8 | G29: W8 | H29: Normal entry | I29: Enter grades
A30: 2026-03-18 | B30: Wed | C30: PGCPS: Last Day of Ramadan | D30: PGCPS | E30: 📋 Note | F30: W9 | G30: W9 | H30: Normal entry | I30: Enter grades
A31: 2026-03-20 | B31: Fri | C31: PGCPS: Eid al-Fitr / Prof Dev — Closed | D31: PGCPS | E31: 🔴 Holiday | F31: W9 | G31: W9 | H31: Normal entry | I31: Enter grades
A32: 2026-03-27
A33: 2026-03-30 | B33: Mon | C33: PGCPS Spring Break begins / Fall reg starts | D33: Both | E33: 🔴 Break | F33: W10 | G33: W10 | H33: Normal entry | I33: Enter grades
A34: 2026-04-03 | B34: Fri | C34: PGCPS Easter — Offices Closed | D34: PGCPS | E34: 🔴 Holiday | F34: W11 | G34: W11 | H34: Normal entry | I34: Enter grades
A35: 2026-04-06 | B35: Mon | C35: PGCPS resumes from Spring Break | D35: PGCPS | E35: 🟢 Resume | F35: W11 | G35: W11 | H35: Normal entry | I35: Enter grades
A36: 2026-04-22 | B36: Wed | C36: PGCPS Teacher Planning — Early Dismissal | D36: PGCPS | E36: 🟡 Half Day | F36: W14 | G36: W14 | H36: Normal entry | I36: Enter grades
A37: 2026-05-04 | B37: Mon | C37: PGCC Last day of classes (Term 1, 15-week) | D37: PGCC | E37: ⚠️ Last Class | F37: W15 | G37: W15 | H37: Normal entry | I37: Enter grades
A38: 2026-05-05 | B38: Tue | C38: PGCC Finals BEGIN | D38: PGCC | E38: 🔴 Finals | F38: W15 | G38: W15 | H38: Normal entry | I38: Enter grades
A39: 2026-05-08 | B39: Fri | C39: PGCPS Last Day for HS Seniors | D39: PGCPS | E39: 🎓 Senior Last Day | F39: W16 | G39: W16 | H39: Normal entry | I39: Enter grades
A40: 2026-05-11 | B40: Mon | C40: PGCC Finals END | D40: PGCC | E40: 🔴 Finals End | F40: W16 | G40: W16 | H40: Normal entry | I40: Enter grades
A41: 2026-05-16 | B41: Sat | C41: PGCC Commencement — End of Spring | D41: PGCC | E41: 🎓 Commencement | F41: W17 | G41: W17 | H41: Normal entry | I41: Enter grades
A42: 2026-05-25 | B42: Mon | C42: Memorial Day — CLOSED | D42: Both | E42: 🔴 Holiday | F42: — | G42: — | H42: No grades this week | I42: Skip week
A43: 2026-06-12 | B43: Fri | C43: PGCPS Last Day for Students | D43: PGCPS | E43: 🎓 Year End | F43: — | G43: — | H43: Normal entry | I43: Enter grades
A45: 📋 GRADE SUBMISSION POLICY
A46: Grades are due every Thursday by 2:00 PM. If Thursday falls on a holiday or campus closure, grades are due on the last school day before the holiday.
A47: Example: If Thursday is Thanksgiving (Nov 27), grades would be due Wednesday Nov 26. The week mapping below already accounts for holidays by skipping break weeks entirely.
A48: PGCC FALL 2025 — WEEK-TO-DATE MAPPING (Term 1, 15-Week)
A49: ElevateED Week | B49: PGCC Week | C49: Start Date | D49: End Date | E49: Mon | F49: Tue | G49: Wed | H49: Grades Due | I49: Fri
A50: 1 | B50: 1 | C50: Aug 18 | D50: Aug 22 | E50: ✓ | F50: ✓ | G50: ✓ | H50: Thu Aug 21 | I50: ✓
A51: 2 | B51: 2 | C51: Aug 25 | D51: Aug 29 | E51: ✓ | F51: ✓ | G51: ✓ | H51: Thu Aug 28 | I51: ✓
A52: 3 | B52: 3 | C52: Sep 01 | D52: Sep 05 | E52: OFF | F52: ✓ | G52: ✓ | H52: Thu Sep 04 | I52: ✓
A53: 4 | B53: 4 | C53: Sep 08 | D53: Sep 12 | E53: ✓ | F53: ✓ | G53: ✓ | H53: Thu Sep 11 | I53: ✓
A54: 5 | B54: 5 | C54: Sep 15 | D54: Sep 19 | E54: ✓ | F54: ✓ | G54: ✓ | H54: Thu Sep 18 | I54: ✓
A55: 6 | B55: 6 | C55: Sep 22 | D55: Sep 26 | E55: ✓ | F55: ✓ | G55: ✓ | H55: Thu Sep 25 | I55: ✓
A56: 7 | B56: 7 | C56: Sep 29 | D56: Oct 03 | E56: ✓ | F56: ✓ | G56: ✓ | H56: Thu Oct 02 | I56: ✓
A57: 8 | B57: 8 | C57: Oct 06 | D57: Oct 10 | E57: ✓ | F57: ✓ | G57: ✓ | H57: Thu Oct 09 | I57: ✓
A58: 9 | B58: 9 | C58: Oct 13 | D58: Oct 17 | E58: ✓ | F58: ✓ | G58: ✓ | H58: Thu Oct 16 | I58: ✓
A59: 10 | B59: 10 | C59: Oct 20 | D59: Oct 24 | E59: ✓ | F59: ✓ | G59: ✓ | H59: Thu Oct 23 | I59: ✓
A60: 11 | B60: 11 | C60: Oct 27 | D60: Oct 31 | E60: ✓ | F60: ✓ | G60: ✓ | H60: Thu Oct 30 | I60: ✓
A61: 12 | B61: 12 | C61: Nov 03 | D61: Nov 07 | E61: ✓ | F61: ✓ | G61: ✓ | H61: Thu Nov 06 | I61: ✓
... A64: 15 | B64: 15 | C64: Dec 01 | D64: Dec 05 | E64: ✓ | F64: ✓ | G64: ✓ | H64: Thu Dec 04 | I64: ✓
A65: — | C65: Nov 24 | D65: Nov 28 | E65: OFF | F65: OFF | G65: OFF | H65: THANKSGIVING BREAK | I65: OFF
A68: PGCC SPRING 2026 — WEEK-TO-DATE MAPPING (Term 1, 15-Week)
A69: ElevateED Week | B69: PGCC Week | C69: Start Date | D69: End Date | E69: Mon | F69: Tue | G69: Wed | H69: Grades Due | I69: Fri | J69: Notes
A70: 1 | B70: 1 | C70: Jan 20 | D70: Jan 24 | E70: ✓ | F70: ✓ | G70: ✓ | H70: Thu Jan 22 | I70: ✓
A71: 2 | B71: 2 | C71: Jan 27 | D71: Jan 31 | E71: ✓ | F71: ✓ | G71: ✓ | H71: Thu Jan 29 | I71: ✓
A72: 3 | B72: 3 | C72: Feb 03 | D72: Feb 07 | E72: ✓ | F72: ✓ | G72: ✓ | H72: Thu Feb 05 | I72: ✓
A73: 4 | B73: 4 | C73: Feb 10 | D73: Feb 14 | E73: ✓ | F73: ✓ | G73: ✓ | H73: Thu Feb 12 | I73: ✓
A74: 5 | B74: 5 | C74: Feb 17 | D74: Feb 21 | E74: ✓ | F74: ✓ | G74: ✓ | H74: Thu Feb 19 | I74: ✓
A75: 6 | B75: 6 | C75: Feb 24 | D75: Feb 28 | E75: ✓ | F75: ✓ | G75: ✓ | H75: Thu Feb 26 | I75: ✓
A76: 7 | B76: 7 | C76: Mar 03 | D76: Mar 07 | E76: ✓ | F76: ✓ | G76: ✓ | H76: Thu Mar 05 | I76: ✓
A77: 8 | B77: 8 | C77: Mar 16 | D77: Mar 20 | E77: ✓ | F77: ✓ | G77: ✓ | H77: Thu Mar 19 | I77: ✓
A78: 9 | B78: 9 | C78: Mar 23 | D78: Mar 27 | E78: ✓ | F78: ✓ | G78: ✓ | H78: Thu Mar 26 | I78: ✓
A79: 10 | B79: 10 | C79: Mar 30 | D79: Apr 03 | E79: PGCPS Off | F79: PGCPS Off | G79: PGCPS Off | H79: Wed Apr 01 ⚠ | I79: PGCPS Off | J79: PGCPS Spring Break — students at Largo off
A80: 11 | B80: 11 | C80: Apr 06 | D80: Apr 10 | E80: PGCPS Off | F80: ✓ | G80: ✓ | H80: Thu Apr 09 | I80: ✓ | J80: PGCPS Spring Break — students at Largo off
A81: 12 | B81: 12 | C81: Apr 13 | D81: Apr 17 | E81: ✓ | F81: ✓ | G81: ✓ | H81: Thu Apr 16 | I81: ✓
A82: 13 | B82: 13 | C82: Apr 20 | D82: Apr 24 | E82: ✓ | F82: ✓ | G82: ✓ | H82: Thu Apr 23 | I82: ✓
A83: 14 | B83: 14 | C83: Apr 27 | D83: May 01 | E83: ✓ | F83: ✓ | G83: ✓ | H83: Thu Apr 30 | I83: ✓
A84: 15 | B84: 15 | C84: May 04 | D84: May 08 | E84: ✓ | F84: ✓ | G84: ✓ | H84: Thu May 07 | I84: ✓
A85: 16 | B85: 16 | C85: May 11 | D85: May 15 | E85: ✓ | F85: ✓ | G85: ✓ | H85: ✓ | I85: ✓
A86: 17 | B86: 17 | C86: May 18 | D86: May 22 | E86: ✓ | F86: ✓ | G86: ✓ | H86: ✓ | I86: ✓
A87: 18 | B87: 18 | C87: May 25 | D87: May 29 | E87: OFF | F87: ✓ | G87: ✓ | H87: ✓ | I87: ✓ | J87: Holiday: May 25

Sheet Cohort 2026 — Grades
A1: ⬅ NAVIGATE: | B1: 📍 Nav Hub | C1: ⚡ Command | D1: 👥 2026 | E1: 👥 2027 | F1: 👥 2028 | G1: 👥 2029
A2: ElevateED — COHORT 2026 — 12th Grade Seniors | 17 Students | Weekly Grade Tracker
A3: Talent Ready IT Program | Largo High School | Prince George's Community College
A4: Maryland Blueprint for Maryland's Future | CONFIDENTIAL — FERPA PROTECTED | February 13, 2026
A5: Current: Spring 2026 (INT 2840, INT 2310, EGL 1340) | Prior: Fall 2025 (BIO 1110, BIO 1120) | Grades due every Thursday by 2:00 PM | PGCC Calendar synced | * = Holiday Thu, due day before
A7: TR-0001 — CRICHTON III, LEONARD
A8: Spring 2026 (Current)
A9: Course | B9: W1 1/22 | C9: W2 1/29 | D9: W3 2/05 | E9: W4 2/12 | F9: W5 2/19 | G9: W6 2/26 | H9: W7 3/05 | I9: W8 3/19 | J9: W9 3/26 | K9: W10 4/01* | L9: W11 4/09 | M9: W12 4/16 | N9: W13 4/23 | O9: W14 4/30 | P9: W15 5/07 | Q9: CUM
A10: INT 2840 — System Analysis/Project Mgmt
A11: INT 2310 — Windows Server Admin
A12: EGL 1340 — Composition II: Technical Writing
A14: Fall 2025 (12th Grade — BIO/BIO Lab)
A15: Course | B15: W1 8/21 | C15: W2 8/28 | D15: W3 9/04 | E15: W4 9/11 | F15: W5 9/18 | G15: W6 9/25 | H15: W7 10/02 | I15: W8 10/09 | J15: W9 10/16 | K15: W10 10/23 | L15: W11 10/30 | M15: W12 11/06 | N15: W13 11/13 | O15: W14 11/20 | P15: W15 12/04 | Q15: CUM
A16: BIO 1110 — Environmental Biology | P16: 94 | Q16: 94
A17: BIO 1120 — Environmental Biology Lab | P17: 88.9 | Q17: 88.9
A20: TR-0002 — CROWELL, KINGSTON
A21: Spring 2026 (Current)
A22: Course | B22: W1 1/22 | C22: W2 1/29 | D22: W3 2/05 | E22: W4 2/12 | F22: W5 2/19 | G22: W6 2/26 | H22: W7 3/05 | I22: W8 3/19 | J22: W9 3/26 | K22: W10 4/01* | L22: W11 4/09 | M22: W12 4/16 | N22: W13 4/23 | O22: W14 4/30 | P22: W15 5/07 | Q22: CUM
A23: INT 2840 — System Analysis/Project Mgmt
A24: INT 2310 — Windows Server Admin
A25: EGL 1340 — Composition II: Technical Writing
A27: Fall 2025 (12th Grade — BIO/BIO Lab)
A28: Course | B28: W1 8/21 | C28: W2 8/28 | D28: W3 9/04 | E28: W4 9/11 | F28: W5 9/18 | G28: W6 9/25 | H28: W7 10/02 | I28: W8 10/09 | J28: W9 10/16 | K28: W10 10/23 | L28: W11 10/30 | M28: W12 11/06 | N28: W13 11/13 | O28: W14 11/20 | P28: W15 12/04 | Q28: CUM
A29: BIO 1110 — Environmental Biology | P29: 87.25 | Q29: 87.25
A30: BIO 1120 — Environmental Biology Lab | P30: 95.83 | Q30: 95.83
A33: TR-0003 — DAVIS, GABRIEL
A34: Spring 2026 (Current)
A35: Course | B35: W1 1/22 | C35: W2 1/29 | D35: W3 2/05 | E35: W4 2/12 | F35: W5 2/19 | G35: W6 2/26 | H35: W7 3/05 | I35: W8 3/19 | J35: W9 3/26 | K35: W10 4/01* | L35: W11 4/09 | M35: W12 4/16 | N35: W13 4/23 | O35: W14 4/30 | P35: W15 5/07 | Q35: CUM
A36: INT 2840 — System Analysis/Project Mgmt
A37: INT 2310 — Windows Server Admin
A38: EGL 1340 — Composition II: Technical Writing
A40: Fall 2025 (12th Grade — BIO/BIO Lab)
A41: Course | B41: W1 8/21 | C41: W2 8/28 | D41: W3 9/04 | E41: W4 9/11 | F41: W5 9/18 | G41: W6 9/25 | H41: W7 10/02 | I41: W8 10/09 | J41: W9 10/16 | K41: W10 10/23 | L41: W11 10/30 | M41: W12 11/06 | N41: W13 11/13 | O41: W14 11/20 | P41: W15 12/04 | Q41: CUM
A42: BIO 1110 — Environmental Biology | P42: 87.33 | Q42: 87.33
A43: BIO 1120 — Environmental Biology Lab | P43: 80.56 | Q43: 80.56
A46: TR-0004 — FERSNER, LAILAH
A47: Spring 2026 (Current)
A48: Course | B48: W1 1/22 | C48: W2 1/29 | D48: W3 2/05 | E48: W4 2/12 | F48: W5 2/19 | G48: W6 2/26 | H48: W7 3/05 | I48: W8 3/19 | J48: W9 3/26 | K48: W10 4/01* | L48: W11 4/09 | M48: W12 4/16 | N48: W13 4/23 | O48: W14 4/30 | P48: W15 5/07 | Q48: CUM
A49: INT 2840 — System Analysis/Project Mgmt | H49: 94.4% | Q49: 94.4%
A50: INT 2310 — Windows Server Admin | G50: 97.2% | Q50: 97.2%
A51: EGL 1340 — Composition II: Technical Writing | H51: 95.0% | Q51: 95.0%
A53: Fall 2025 (12th Grade — BIO/BIO Lab)
A54: Course | B54: W1 8/21 | C54: W2 8/28 | D54: W3 9/04 | E54: W4 9/11 | F54: W5 9/18 | G54: W6 9/25 | H54: W7 10/02 | I54: W8 10/09 | J54: W9 10/16 | K54: W10 10/23 | L54: W11 10/30 | M54: W12 11/06 | N54: W13 11/13 | O54: W14 11/20 | P54: W15 12/04 | Q54: CUM
A55: BIO 1110 — Environmental Biology | P55: 91.5 | Q55: 91.5
A56: BIO 1120 — Environmental Biology Lab | P56: 89.4 | Q56: 89.4
A59: TR-0005 — FORD, JAMES
A60: Spring 2026 (Current)
A61: Course | B61: W1 1/22 | C61: W2 1/29 | D61: W3 2/05 | E61: W4 2/12 | F61: W5 2/19 | G61: W6 2/26 | H61: W7 3/05 | I61: W8 3/19 | J61: W9 3/26 | K61: W10 4/01* | L61: W11 4/09 | M61: W12 4/16 | N61: W13 4/23 | O61: W14 4/30 | P61: W15 5/07 | Q61: CUM
A62: INT 2840 — System Analysis/Project Mgmt | H62: 86.0% | Q62: 86.0%
A63: INT 2310 — Windows Server Admin | H63: 98.1% | Q63: 98.1%
A64: EGL 1340 — Composition II: Technical Writing | H64: 88.0% | Q64: 88.0%
A66: Fall 2025 (12th Grade — BIO/BIO Lab)
A67: Course | B67: W1 8/21 | C67: W2 8/28 | D67: W3 9/04 | E67: W4 9/11 | F67: W5 9/18 | G67: W6 9/25 | H67: W7 10/02 | I67: W8 10/09 | J67: W9 10/16 | K67: W10 10/23 | L67: W11 10/30 | M67: W12 11/06 | N67: W13 11/13 | O67: W14 11/20 | P67: W15 12/04 | Q67: CUM
A68: BIO 1110 — Environmental Biology | P68: 91.11 | Q68: 91.11
A69: BIO 1120 — Environmental Biology Lab | P69: 82.78 | Q69: 82.78
A72: TR-0006 — FORREST, TYLEYL
A73: Spring 2026 (Current)
A74: Course | B74: W1 1/22 | C74: W2 1/29 | D74: W3 2/05 | E74: W4 2/12 | F74: W5 2/19 | G74: W6 2/26 | H74: W7 3/05 | I74: W8 3/19 | J74: W9 3/26 | K74: W10 4/01* | L74: W11 4/09 | M74: W12 4/16 | N74: W13 4/23 | O74: W14 4/30 | P74: W15 5/07 | Q74: CUM
A75: INT 2840 — System Analysis/Project Mgmt
A76: INT 2310 — Windows Server Admin
A77: EGL 1340 — Composition II: Technical Writing
A79: Fall 2025 (12th Grade — BIO/BIO Lab)
A80: Course | B80: W1 8/21 | C80: W2 8/28 | D80: W3 9/04 | E80: W4 9/11 | F80: W5 9/18 | G80: W6 9/25 | H80: W7 10/02 | I80: W8 10/09 | J80: W9 10/16 | K80: W10 10/23 | L80: W11 10/30 | M80: W12 11/06 | N80: W13 11/13 | O80: W14 11/20 | P80: W15 12/04 | Q80: CUM
A81: BIO 1110 — Environmental Biology | P81: 95.65 | Q81: 95.65
A82: BIO 1120 — Environmental Biology Lab | P82: 88.89 | Q82: 88.89
A85: TR-0007 — JALLOH, JENABU
A86: Spring 2026 (Current)
A87: Course | B87: W1 1/22 | C87: W2 1/29 | D87: W3 2/05 | E87: W4 2/12 | F87: W5 2/19 | G87: W6 2/26 | H87: W7 3/05 | I87: W8 3/19 | J87: W9 3/26 | K87: W10 4/01* | L87: W11 4/09 | M87: W12 4/16 | N87: W13 4/23 | O87: W14 4/30 | P87: W15 5/07 | Q87: CUM
A88: INT 2840 — System Analysis/Project Mgmt
A89: INT 2310 — Windows Server Admin
A90: EGL 1340 — Composition II: Technical Writing
A92: Fall 2025 (12th Grade — BIO/BIO Lab)
A93: Course | B93: W1 8/21 | C93: W2 8/28 | D93: W3 9/04 | E93: W4 9/11 | F93: W5 9/18 | G93: W6 9/25 | H93: W7 10/02 | I93: W8 10/09 | J93: W9 10/16 | K93: W10 10/23 | L93: W11 10/30 | M93: W12 11/06 | N93: W13 11/13 | O93: W14 11/20 | P93: W15 12/04 | Q93: CUM
A94: BIO 1110 — Environmental Biology | P94: 98 | Q94: 98
A95: BIO 1120 — Environmental Biology Lab | P95: 100 | Q95: 100
A98: TR-0008 — JOHNSON-BONILLA, CHRISTOPHER
A99: Spring 2026 (Current)
A100: Course | B100: W1 1/22 | C100: W2 1/29 | D100: W3 2/05 | E100: W4 2/12 | F100: W5 2/19 | G100: W6 2/26 | H100: W7 3/05 | I100: W8 3/19 | J100: W9 3/26 | K100: W10 4/01* | L100: W11 4/09 | M100: W12 4/16 | N100: W13 4/23 | O100: W14 4/30 | P100: W15 5/07 | Q100: CUM
A101: INT 2840 — System Analysis/Project Mgmt | J101: 92.9% | Q101: 92.9%
A102: INT 2310 — Windows Server Admin | J102: 98.3% | Q102: 98.3%
A103: EGL 1340 — Composition II: Technical Writing | H103: 83.5% | Q103: 83.5%
A105: Fall 2025 (12th Grade — BIO/BIO Lab)
A106: Course | B106: W1 8/21 | C106: W2 8/28 | D106: W3 9/04 | E106: W4 9/11 | F106: W5 9/18 | G106: W6 9/25 | H106: W7 10/02 | I106: W8 10/09 | J106: W9 10/16 | K106: W10 10/23 | L106: W11 10/30 | M106: W12 11/06 | N106: W13 11/13 | O106: W14 11/20 | P106: W15 12/04 | Q106: CUM
A107: BIO 1110 — Environmental Biology | P107: 92.42 | Q107: 92.42
A108: BIO 1120 — Environmental Biology Lab | P108: 91.67 | Q108: 91.67
A111: TR-0009 — OLUBIYI, OLUWANIFEMI
A112: Spring 2026 (Current)
A113: Course | B113: W1 1/22 | C113: W2 1/29 | D113: W3 2/05 | E113: W4 2/12 | F113: W5 2/19 | G113: W6 2/26 | H113: W7 3/05 | I113: W8 3/19 | J113: W9 3/26 | K113: W10 4/01* | L113: W11 4/09 | M113: W12 4/16 | N113: W13 4/23 | O113: W14 4/30 | P113: W15 5/07 | Q113: CUM
A114: INT 2840 — System Analysis/Project Mgmt
A115: INT 2310 — Windows Server Admin
A116: EGL 1340 — Composition II: Technical Writing
A118: Fall 2025 (12th Grade — BIO/BIO Lab)
A119: Course | B119: W1 8/21 | C119: W2 8/28 | D119: W3 9/04 | E119: W4 9/11 | F119: W5 9/18 | G119: W6 9/25 | H119: W7 10/02 | I119: W8 10/09 | J119: W9 10/16 | K119: W10 10/23 | L119: W11 10/30 | M119: W12 11/06 | N119: W13 11/13 | O119: W14 11/20 | P119: W15 12/04 | Q119: CUM
A120: BIO 1110 — Environmental Biology | P120: 92.05 | Q120: 92.05
A121: BIO 1120 — Environmental Biology Lab | P121: 92.05 | Q121: 92.05
A124: TR-0010 — SANNI, MOFEOLUWA
A125: Spring 2026 (Current)
A126: Course | B126: W1 1/22 | C126: W2 1/29 | D126: W3 2/05 | E126: W4 2/12 | F126: W5 2/19 | G126: W6 2/26 | H126: W7 3/05 | I126: W8 3/19 | J126: W9 3/26 | K126: W10 4/01* | L126: W11 4/09 | M126: W12 4/16 | N126: W13 4/23 | O126: W14 4/30 | P126: W15 5/07 | Q126: CUM
A127: INT 2840 — System Analysis/Project Mgmt
A128: INT 2310 — Windows Server Admin
...

Sheet Cohort 2027 — Grades
A1: ⬅ NAVIGATE: | B1: 📍 Nav Hub | C1: ⚡ Command | D1: 👥 2026 | E1: 👥 2027 | F1: 👥 2028 | G1: 👥 2029
A2: ElevateED — COHORT 2027 — 11th Grade Juniors | 6 Students | Weekly Grade Tracker
A3: Talent Ready IT Program | Largo High School | Prince George's Community College
A4: Maryland Blueprint for Maryland's Future | CONFIDENTIAL — FERPA PROTECTED | February 13, 2026
A5: Current: Spring 2026 (INT 1620, INT 1540, INT 2600) | Prior: Fall 2025, Spring 2025, Fall 2024 | Grades due every Thursday by 2:00 PM | PGCC Calendar synced | * = Holiday Thu, due day before
A7: TR-0017 — BYFIELD, KIMANI
A8: Spring 2026 (Current)
A9: Course | B9: W1 1/22 | C9: W2 1/29 | D9: W3 2/05 | E9: W4 2/12 | F9: W5 2/19 | G9: W6 2/26 | H9: W7 3/05 | I9: W8 3/19 | J9: W9 3/26 | K9: W10 4/01* | L9: W11 4/09 | M9: W12 4/16 | N9: W13 4/23 | O9: W14 4/30 | P9: W15 5/07 | Q9: CUM
A10: INT 1620 — Intro to Server Admin | Q10: 78.29
A11: INT 1540 — Intro to Cybersecurity | Q11: 100
A12: INT 2600 — Security Fundamentals | Q12: 86
A14: Fall 2025 (11th Grade)
A15: Course | B15: W1 8/21 | C15: W2 8/28 | D15: W3 9/04 | E15: W4 9/11 | F15: W5 9/18 | G15: W6 9/25 | H15: W7 10/02 | I15: W8 10/09 | J15: W9 10/16 | K15: W10 10/23 | L15: W11 10/30 | M15: W12 11/06 | N15: W13 11/13 | O15: W14 11/20 | P15: W15 12/04 | Q15: CUM
A16: INT 1550 — Intro to Networks: Network+ Prep | P16: 77.6 | Q16: 57.4%
A17: BIO 1110 — Environmental Biology | P17: 87.17 | Q17: 66.2%
A18: BIO 1120 — Env Biology Lab | P18: 64.12 | Q18: 79.9%
A20: Spring 2025 (10th Grade)
A21: Course | B21: W1 1/23 | C21: W2 1/30 | D21: W3 2/06 | E21: W4 2/13 | F21: W5 2/20 | G21: W6 2/27 | H21: W7 3/06 | I21: W8 3/20 | J21: W9 3/27 | K21: W10 4/03 | L21: W11 4/10 | M21: W12 4/17 | N21: W13 4/24 | O21: W14 5/01 | P21: W15 5/08 | Q21: CUM
A22: NTR 1010 — Nutrition | P22: 56.43 | Q22: 56.43
A23: SOC 1010 — Intro to Sociology | P23: 106.67 | Q23: 106.67
A25: Fall 2024 (10th Grade)
A26: Course | B26: W1 8/22 | C26: W2 8/29 | D26: W3 9/05 | E26: W4 9/12 | F26: W5 9/19 | G26: W6 9/26 | H26: W7 10/03 | I26: W8 10/10 | J26: W9 10/17 | K26: W10 10/24 | L26: W11 10/31 | M26: W12 11/07 | N26: W13 11/14 | O26: W14 11/21 | P26: W15 12/05 | Q26: CUM
A27: INT 1700 — Understanding OS | P27: 73.82 | Q27: 73.82
A28: COM 1010 — Speech Communication | P28: 90.86 | Q28: 90.86
A31: TR-0018 — HODGE, AMANI
A32: Spring 2026 (Current)
A33: Course | B33: W1 1/22 | C33: W2 1/29 | D33: W3 2/05 | E33: W4 2/12 | F33: W5 2/19 | G33: W6 2/26 | H33: W7 3/05 | I33: W8 3/19 | J33: W9 3/26 | K33: W10 4/01* | L33: W11 4/09 | M33: W12 4/16 | N33: W13 4/23 | O33: W14 4/30 | P33: W15 5/07 | Q33: CUM
A34: INT 1620 — Intro to Server Admin | Q34: 95
A35: INT 2600 — Security Fundamentals | Q35: 43.61
A37: Fall 2025 (11th Grade)
A38: Course | B38: W1 8/21 | C38: W2 8/28 | D38: W3 9/04 | E38: W4 9/11 | F38: W5 9/18 | G38: W6 9/25 | H38: W7 10/02 | I38: W8 10/09 | J38: W9 10/16 | K38: W10 10/23 | L38: W11 10/30 | M38: W12 11/06 | N38: W13 11/13 | O38: W14 11/20 | P38: W15 12/04 | Q38: CUM
A39: INT 1550 — Intro to Networks: Network+ Prep | P39: 79.1 | Q39: 91.5%
A40: BIO 1110 — Environmental Biology | P40: 83.51 | Q40: 79.3%
A41: BIO 1120 — Env Biology Lab | P41: 74.9 | Q41: 65.0%
A43: Spring 2025 (10th Grade)
A44: Course | B44: W1 1/23 | C44: W2 1/30 | D44: W3 2/06 | E44: W4 2/13 | F44: W5 2/20 | G44: W6 2/27 | H44: W7 3/06 | I44: W8 3/20 | J44: W9 3/27 | K44: W10 4/03 | L44: W11 4/10 | M44: W12 4/17 | N44: W13 4/24 | O44: W14 5/01 | P44: W15 5/08 | Q44: CUM
A45: NTR 1010 — Nutrition | P45: 67.25 | Q45: 67.25
A46: SOC 1010 — Intro to Sociology | P46: 91.43 | Q46: 91.43
A48: Fall 2024 (10th Grade)
A49: Course | B49: W1 8/22 | C49: W2 8/29 | D49: W3 9/05 | E49: W4 9/12 | F49: W5 9/19 | G49: W6 9/26 | H49: W7 10/03 | I49: W8 10/10 | J49: W9 10/17 | K49: W10 10/24 | L49: W11 10/31 | M49: W12 11/07 | N49: W13 11/14 | O49: W14 11/21 | P49: W15 12/05 | Q49: CUM
A50: INT 1700 — Understanding OS | P50: 70.9 | Q50: 70.9
A51: COM 1010 — Speech Communication | P51: 88 | Q51: 88
A54: TR-0019 — LAMBRIGHT, KADYN
A55: Spring 2026 (Current)
A56: Course | B56: W1 1/22 | C56: W2 1/29 | D56: W3 2/05 | E56: W4 2/12 | F56: W5 2/19 | G56: W6 2/26 | H56: W7 3/05 | I56: W8 3/19 | J56: W9 3/26 | K56: W10 4/01* | L56: W11 4/09 | M56: W12 4/16 | N56: W13 4/23 | O56: W14 4/30 | P56: W15 5/07 | Q56: CUM
A57: INT 1620 — Intro to Server Admin | Q57: 94.7
A58: INT 1540 — Intro to Cybersecurity | Q58: 100
A59: INT 2600 — Security Fundamentals | Q59: 97.6
A61: Fall 2025 (11th Grade)
A62: Course | B62: W1 8/21 | C62: W2 8/28 | D62: W3 9/04 | E62: W4 9/11 | F62: W5 9/18 | G62: W6 9/25 | H62: W7 10/02 | I62: W8 10/09 | J62: W9 10/16 | K62: W10 10/23 | L62: W11 10/30 | M62: W12 11/06 | N62: W13 11/13 | O62: W14 11/20 | P62: W15 12/04 | Q62: CUM
A63: INT 1550 — Intro to Networks: Network+ Prep | P63: 80.2 | Q63: 64.2%
A64: BIO 1110 — Environmental Biology | P64: 93.64 | Q64: 86.0%
A65: BIO 1120 — Env Biology Lab | P65: 92.94 | Q65: 65.1%
A67: Spring 2025 (10th Grade)
A68: Course | B68: W1 1/23 | C68: W2 1/30 | D68: W3 2/06 | E68: W4 2/13 | F68: W5 2/20 | G68: W6 2/27 | H68: W7 3/06 | I68: W8 3/20 | J68: W9 3/27 | K68: W10 4/03 | L68: W11 4/10 | M68: W12 4/17 | N68: W13 4/24 | O68: W14 5/01 | P68: W15 5/08 | Q68: CUM
A69: NTR 1010 — Nutrition | P69: 71.52 | Q69: 71.52
A70: SOC 1010 — Intro to Sociology | P70: 101.67 | Q70: 101.67
A72: Fall 2024 (10th Grade)
A73: Course | B73: W1 8/22 | C73: W2 8/29 | D73: W3 9/05 | E73: W4 9/12 | F73: W5 9/19 | G73: W6 9/26 | H73: W7 10/03 | I73: W8 10/10 | J73: W9 10/17 | K73: W10 10/24 | L73: W11 10/31 | M73: W12 11/07 | N73: W13 11/14 | O73: W14 11/21 | P73: W15 12/05 | Q73: CUM
A74: INT 1700 — Understanding OS | P74: 67.26 | Q74: 67.26
A75: COM 1010 — Speech Communication | P75: 86 | Q75: 86
A78: TR-0020 — NISBETH, GRACE
A79: Spring 2026 (Current)
A80: Course | B80: W1 1/22 | C80: W2 1/29 | D80: W3 2/05 | E80: W4 2/12 | F80: W5 2/19 | G80: W6 2/26 | H80: W7 3/05 | I80: W8 3/19 | J80: W9 3/26 | K80: W10 4/01* | L80: W11 4/09 | M80: W12 4/16 | N80: W13 4/23 | O80: W14 4/30 | P80: W15 5/07 | Q80: CUM
A81: INT 1620 — Intro to Server Admin | Q81: 95.5
A82: INT 1540 — Intro to Cybersecurity | Q82: 100
A83: INT 2600 — Security Fundamentals | Q83: 82.7
A85: Fall 2025 (11th Grade)
A86: Course | B86: W1 8/21 | C86: W2 8/28 | D86: W3 9/04 | E86: W4 9/11 | F86: W5 9/18 | G86: W6 9/25 | H86: W7 10/02 | I86: W8 10/09 | J86: W9 10/16 | K86: W10 10/23 | L86: W11 10/30 | M86: W12 11/06 | N86: W13 11/13 | O86: W14 11/20 | P86: W15 12/04 | Q86: CUM
A87: INT 1550 — Intro to Networks: Network+ Prep | P87: 88.95 | Q87: 73.3%
A88: BIO 1110 — Environmental Biology | P88: 93.73 | Q88: 81.9%
A89: BIO 1120 — Env Biology Lab | P89: 97.95 | Q89: 72.9%
A91: Spring 2025 (10th Grade)
A92: Course | B92: W1 1/23 | C92: W2 1/30 | D92: W3 2/06 | E92: W4 2/13 | F92: W5 2/20 | G92: W6 2/27 | H92: W7 3/06 | I92: W8 3/20 | J92: W9 3/27 | K92: W10 4/03 | L92: W11 4/10 | M92: W12 4/17 | N92: W13 4/24 | O92: W14 5/01 | P92: W15 5/08 | Q92: CUM
A93: NTR 1010 — Nutrition | P93: 91.7 | Q93: 91.7
A94: SOC 1010 — Intro to Sociology | P94: 101.67 | Q94: 101.67
A96: Fall 2024 (10th Grade)
A97: Course | B97: W1 8/22 | C97: W2 8/29 | D97: W3 9/05 | E97: W4 9/12 | F97: W5 9/19 | G97: W6 9/26 | H97: W7 10/03 | I97: W8 10/10 | J97: W9 10/17 | K97: W10 10/24 | L97: W11 10/31 | M97: W12 11/07 | N97: W13 11/14 | O97: W14 11/21 | P97: W15 12/05 | Q97: CUM
A98: INT 1700 — Understanding OS | P98: 75.11 | Q98: 75.11
A99: COM 1010 — Speech Communication | P99: 87.33 | Q99: 87.33
A102: TR-0021 — PAYTON, JADEN
A103: Spring 2026 (Current)
A104: Course | B104: W1 1/22 | C104: W2 1/29 | D104: W3 2/05 | E104: W4 2/12 | F104: W5 2/19 | G104: W6 2/26 | H104: W7 3/05 | I104: W8 3/19 | J104: W9 3/26 | K104: W10 4/01* | L104: W11 4/09 | M104: W12 4/16 | N104: W13 4/23 | O104: W14 4/30 | P104: W15 5/07 | Q104: CUM
A105: INT 1620 — Intro to Server Admin | Q105: 82.27
A106: INT 1540 — Intro to Cybersecurity | Q106: 66.67
A107: INT 2600 — Security Fundamentals | Q107: 75.04
A109: Fall 2025 (11th Grade)
A110: Course | B110: W1 8/21 | C110: W2 8/28 | D110: W3 9/04 | E110: W4 9/11 | F110: W5 9/18 | G110: W6 9/25 | H110: W7 10/02 | I110: W8 10/09 | J110: W9 10/16 | K110: W10 10/23 | L110: W11 10/30 | M110: W12 11/06 | N110: W13 11/13 | O110: W14 11/20 | P110: W15 12/04 | Q110: CUM
A111: INT 1550 — Intro to Networks: Network+ Prep | P111: 82 | Q111: 78.9%
A112: BIO 1110 — Environmental Biology | P112: 91.28 | Q112: 66.4%
A113: BIO 1120 — Env Biology Lab | P113: 84.1 | Q113: 89.6%
A115: Spring 2025 (10th Grade)
A116: Course | B116: W1 1/23 | C116: W2 1/30 | D116: W3 2/06 | E116: W4 2/13 | F116: W5 2/20 | G116: W6 2/27 | H116: W7 3/06 | I116: W8 3/20 | J116: W9 3/27 | K116: W10 4/03 | L116: W11 4/10 | M116: W12 4/17 | N116: W13 4/24 | O116: W14 5/01 | P116: W15 5/08 | Q116: CUM
A117: NTR 1010 — Nutrition | P117: 73.57 | Q117: 73.57
A118: SOC 1010 — Intro to Sociology | P118: 85 | Q118: 85
A120: Fall 2024 (10th Grade)
A121: Course | B121: W1 8/22 | C121: W2 8/29 | D121: W3 9/05 | E121: W4 9/12 | F121: W5 9/19 | G121: W6 9/26 | H121: W7 10/03 | I121: W8 10/10 | J121: W9 10/17 | K121: W10 10/24 | L121: W11 10/31 | M121: W12 11/07 | N121: W13 11/14 | O121: W14 11/21 | P121: W15 12/05 | Q121: CUM
A122: INT 1700 — Understanding OS | P122: 77.11 | Q122: 77.11
A123: COM 1010 — Speech Communication | P123: 79.33 | Q123: 79.33
A126: TR-0022 — WARD, CANAAN
...

Sheet Cohort 2028 — Grades
A1: ⬅ NAVIGATE: | B1: 📍 Nav Hub | C1: ⚡ Command | D1: 👥 2026 | E1: 👥 2027 | F1: 👥 2028 | G1: 👥 2029
A2: ElevateED — COHORT 2028 — 10th Grade Sophomores | 20 Students | Weekly Grade Tracker
A3: Talent Ready IT Program | Largo High School | Prince George's Community College
A4: Maryland Blueprint for Maryland's Future | CONFIDENTIAL — FERPA PROTECTED | February 13, 2026
A5: Current: Spring 2026 (COM 1010, INT 1700) | Prior: Fall 2025, Spring 2025 | Grades due every Thursday by 2:00 PM | PGCC Calendar synced | * = Holiday Thu, due day before
A7: TR-0023 — AHETO, EDWIN | R7: Hick - C / Team Sports D
A8: Spring 2026 (Current)
A9: Course | B9: W1 1/22 | C9: W2 1/29 | D9: W3 2/05 | E9: W4 2/12 | F9: W5 2/19 | G9: W6 2/26 | H9: W7 3/05 | I9: W8 3/19 | J9: W9 3/26 | K9: W10 4/01* | L9: W11 4/09 | M9: W12 4/16 | N9: W13 4/23 | O9: W14 4/30 | P9: W15 5/07 | Q9: CUM
A10: SOC 1010 — Introduction to Sociology | J10: 73.3% | Q10: 73.3%
A11: NTR 1010 — Introduction to Nutrition | J11: 82.3% | Q11: 82.3%
A13: Fall 2025 (10th Grade)
A14: Course | B14: W1 8/21 | C14: W2 8/28 | D14: W3 9/04 | E14: W4 9/11 | F14: W5 9/18 | G14: W6 9/25 | H14: W7 10/02 | I14: W8 10/09 | J14: W9 10/16 | K14: W10 10/23 | L14: W11 10/30 | M14: W12 11/06 | N14: W13 11/13 | O14: W14 11/20 | P14: W15 12/04 | Q14: CUM
A15: COM 1010 — Speech Communication | P15: 57 | Q15: 57
A16: INT 1700 — Understanding OS | P16: 98.5 | Q16: 98.5
A18: Spring 2025 (9th Grade)
A19: Course | B19: W1 1/23 | C19: W2 1/30 | D19: W3 2/06 | E19: W4 2/13 | F19: W5 2/20 | G19: W6 2/27 | H19: W7 3/06 | I19: W8 3/20 | J19: W9 3/27 | K19: W10 4/03 | L19: W11 4/10 | M19: W12 4/17 | N19: W13 4/24 | O19: W14 5/01 | P19: W15 5/08 | Q19: CUM
A20: INT 1010 — Intro to Info Tech | P20: 82.5 | Q20: 82.5
A23: TR-0024 — ALI, CALI | R23: English E Local State - D
A24: Spring 2026 (Current)
A25: Course | B25: W1 1/22 | C25: W2 1/29 | D25: W3 2/05 | E25: W4 2/12 | F25: W5 2/19 | G25: W6 2/26 | H25: W7 3/05 | I25: W8 3/19 | J25: W9 3/26 | K25: W10 4/01* | L25: W11 4/09 | M25: W12 4/16 | N25: W13 4/23 | O25: W14 4/30 | P25: W15 5/07 | Q25: CUM
A26: SOC 1010 — Introduction to Sociology | J26: 61.0% | Q26: 61.0%
A27: NTR 1010 — Introduction to Nutrition | J27: 80.5% | Q27: 80.5%
A29: Fall 2025 (10th Grade)
A30: Course | B30: W1 8/21 | C30: W2 8/28 | D30: W3 9/04 | E30: W4 9/11 | F30: W5 9/18 | G30: W6 9/25 | H30: W7 10/02 | I30: W8 10/09 | J30: W9 10/16 | K30: W10 10/23 | L30: W11 10/30 | M30: W12 11/06 | N30: W13 11/13 | O30: W14 11/20 | P30: W15 12/04 | Q30: CUM
A31: COM 1010 — Speech Communication | P31: 87.38 | Q31: 87.38
A32: INT 1700 — Understanding OS | P32: 82 | Q32: 82
A34: Spring 2025 (9th Grade)
A35: Course | B35: W1 1/23 | C35: W2 1/30 | D35: W3 2/06 | E35: W4 2/13 | F35: W5 2/20 | G35: W6 2/27 | H35: W7 3/06 | I35: W8 3/20 | J35: W9 3/27 | K35: W10 4/03 | L35: W11 4/10 | M35: W12 4/17 | N35: W13 4/24 | O35: W14 5/01 | P35: W15 5/08 | Q35: CUM
A36: INT 1010 — Intro to Info Tech | P36: 88 | Q36: 88
A39: TR-0025 — ANTHONY, JELANI | R39: Advance Design Application. / Teacher add zero for assignment not graded.
A40: Spring 2026 (Current) | R40: Spanish D
A41: Course | B41: W1 1/22 | C41: W2 1/29 | D41: W3 2/05 | E41: W4 2/12 | F41: W5 2/19 | G41: W6 2/26 | H41: W7 3/05 | I41: W8 3/19 | J41: W9 3/26 | K41: W10 4/01* | L41: W11 4/09 | M41: W12 4/16 | N41: W13 4/23 | O41: W14 4/30 | P41: W15 5/07 | Q41: CUM
A42: SOC 1010 — Introduction to Sociology | J42: 79.0% | Q42: 79.0%
A43: NTR 1010 — Introduction to Nutrition | J43: 67.8% | Q43: 67.8%
A45: Fall 2025 (10th Grade)
A46: Course | B46: W1 8/21 | C46: W2 8/28 | D46: W3 9/04 | E46: W4 9/11 | F46: W5 9/18 | G46: W6 9/25 | H46: W7 10/02 | I46: W8 10/09 | J46: W9 10/16 | K46: W10 10/23 | L46: W11 10/30 | M46: W12 11/06 | N46: W13 11/13 | O46: W14 11/20 | P46: W15 12/04 | Q46: CUM
A47: COM 1010 — Speech Communication | P47: 76 | Q47: 76
A48: INT 1700 — Understanding OS | P48: 75 | Q48: 75
A50: Spring 2025 (9th Grade)
A51: Course | B51: W1 1/23 | C51: W2 1/30 | D51: W3 2/06 | E51: W4 2/13 | F51: W5 2/20 | G51: W6 2/27 | H51: W7 3/06 | I51: W8 3/20 | J51: W9 3/27 | K51: W10 4/03 | L51: W11 4/10 | M51: W12 4/17 | N51: W13 4/24 | O51: W14 5/01 | P51: W15 5/08 | Q51: CUM
A52: INT 1010 — Intro to Info Tech | P52: 78.5 | Q52: 78.5
A55: TR-0026 — EGUNJOBI, OREOLUWA | R55: local State Gover - D
A56: Spring 2026 (Current) | R56: Muusicaianship E
A57: Course | B57: W1 1/22 | C57: W2 1/29 | D57: W3 2/05 | E57: W4 2/12 | F57: W5 2/19 | G57: W6 2/26 | H57: W7 3/05 | I57: W8 3/19 | J57: W9 3/26 | K57: W10 4/01* | L57: W11 4/09 | M57: W12 4/16 | N57: W13 4/23 | O57: W14 4/30 | P57: W15 5/07 | Q57: CUM
A58: SOC 1010 — Introduction to Sociology | J58: 73.3% | Q58: 73.3%
A59: NTR 1010 — Introduction to Nutrition | J59: 68.2% | Q59: 68.2%
A61: Fall 2025 (10th Grade)
A62: Course | B62: W1 8/21 | C62: W2 8/28 | D62: W3 9/04 | E62: W4 9/11 | F62: W5 9/18 | G62: W6 9/25 | H62: W7 10/02 | I62: W8 10/09 | J62: W9 10/16 | K62: W10 10/23 | L62: W11 10/30 | M62: W12 11/06 | N62: W13 11/13 | O62: W14 11/20 | P62: W15 12/04 | Q62: CUM
A63: COM 1010 — Speech Communication | P63: 74.75 | Q63: 74.75
A64: INT 1700 — Understanding OS | P64: 65 | Q64: 65
A66: Spring 2025 (9th Grade)
A67: Course | B67: W1 1/23 | C67: W2 1/30 | D67: W3 2/06 | E67: W4 2/13 | F67: W5 2/20 | G67: W6 2/27 | H67: W7 3/06 | I67: W8 3/20 | J67: W9 3/27 | K67: W10 4/03 | L67: W11 4/10 | M67: W12 4/17 | N67: W13 4/24 | O67: W14 5/01 | P67: W15 5/08 | Q67: CUM
A68: INT 1010 — Intro to Info Tech | P68: 72 | Q68: 72
A71: TR-0027 — ERHABOR, ELAION | R71: French E
A72: Spring 2026 (Current)
A73: Course | B73: W1 1/22 | C73: W2 1/29 | D73: W3 2/05 | E73: W4 2/12 | F73: W5 2/19 | G73: W6 2/26 | H73: W7 3/05 | I73: W8 3/19 | J73: W9 3/26 | K73: W10 4/01* | L73: W11 4/09 | M73: W12 4/16 | N73: W13 4/23 | O73: W14 4/30 | P73: W15 5/07 | Q73: CUM
A74: COM 1010 — Speech Communication
A75: INT 1700 — Understanding Operating Systems
A77: Fall 2025 (10th Grade)
A78: Course | B78: W1 8/21 | C78: W2 8/28 | D78: W3 9/04 | E78: W4 9/11 | F78: W5 9/18 | G78: W6 9/25 | H78: W7 10/02 | I78: W8 10/09 | J78: W9 10/16 | K78: W10 10/23 | L78: W11 10/30 | M78: W12 11/06 | N78: W13 11/13 | O78: W14 11/20 | P78: W15 12/04 | Q78: CUM
A79: COM 1010 — Speech Communication | P79: 61.23 | Q79: 61.23
A80: INT 1700 — Understanding OS | P80: 78 | Q80: 78
A82: Spring 2025 (9th Grade)
A83: Course | B83: W1 1/23 | C83: W2 1/30 | D83: W3 2/06 | E83: W4 2/13 | F83: W5 2/20 | G83: W6 2/27 | H83: W7 3/06 | I83: W8 3/20 | J83: W9 3/27 | K83: W10 4/03 | L83: W11 4/10 | M83: W12 4/17 | N83: W13 4/24 | O83: W14 5/01 | P83: W15 5/08 | Q83: CUM
A84: INT 1010 — Intro to Info Tech | P84: 80 | Q84: 80
A87: TR-0028 — FERSNER, KENNEDI | R87: Honor Roll Last Quarter
A88: Spring 2026 (Current) | R88: Biology E / Local State National EAlgebra 2 - E
A89: Course | B89: W1 1/22 | C89: W2 1/29 | D89: W3 2/05 | E89: W4 2/12 | F89: W5 2/19 | G89: W6 2/26 | H89: W7 3/05 | I89: W8 3/19 | J89: W9 3/26 | K89: W10 4/01* | L89: W11 4/09 | M89: W12 4/16 | N89: W13 4/23 | O89: W14 4/30 | P89: W15 5/07 | Q89: CUM
A90: SOC 1010 — Introduction to Sociology | J90: 73.3% | Q90: 73.3%
A91: NTR 1010 — Introduction to Nutrition | J91: 76.1% | Q91: 76.1%
A93: Fall 2025 (10th Grade)
A94: Course | B94: W1 8/21 | C94: W2 8/28 | D94: W3 9/04 | E94: W4 9/11 | F94: W5 9/18 | G94: W6 9/25 | H94: W7 10/02 | I94: W8 10/09 | J94: W9 10/16 | K94: W10 10/23 | L94: W11 10/30 | M94: W12 11/06 | N94: W13 11/13 | O94: W14 11/20 | P94: W15 12/04 | Q94: CUM
A95: COM 1010 — Speech Communication | P95: 72.62 | Q95: 72.62
A96: INT 1700 — Understanding OS | P96: 81 | Q96: 81
A98: Spring 2025 (9th Grade)
A99: Course | B99: W1 1/23 | C99: W2 1/30 | D99: W3 2/06 | E99: W4 2/13 | F99: W5 2/20 | G99: W6 2/27 | H99: W7 3/06 | I99: W8 3/20 | J99: W9 3/27 | K99: W10 4/03 | L99: W11 4/10 | M99: W12 4/17 | N99: W13 4/24 | O99: W14 5/01 | P99: W15 5/08 | Q99: CUM
A100: INT 1010 — Intro to Info Tech | P100: 85 | Q100: 85
A103: TR-0059 — FORD, CHASE
A104: Spring 2026 (Current)
A105: Course | B105: W1 1/22 | C105: W2 1/29 | D105: W3 2/05 | E105: W4 2/12 | F105: W5 2/19 | G105: W6 2/26 | H105: W7 3/05 | I105: W8 3/19 | J105: W9 3/26 | K105: W10 4/01* | L105: W11 4/09 | M105: W12 4/16 | N105: W13 4/23 | O105: W14 4/30 | P105: W15 5/07 | Q105: CUM
A106: COM 1010 — Speech Communication
A107: INT 1700 — Understanding Operating Systems
A109: Fall 2025 (10th Grade)
A110: Course | B110: W1 8/21 | C110: W2 8/28 | D110: W3 9/04 | E110: W4 9/11 | F110: W5 9/18 | G110: W6 9/25 | H110: W7 10/02 | I110: W8 10/09 | J110: W9 10/16 | K110: W10 10/23 | L110: W11 10/30 | M110: W12 11/06 | N110: W13 11/13 | O110: W14 11/20 | P110: W15 12/04 | Q110: CUM
A111: COM 1010 — Speech Communication | P111: 47.15 | Q111: 47.15
A112: INT 1700 — Understanding OS | P112: 65.25 | Q112: 65.25
A114: Spring 2025 (9th Grade)
A115: Course | B115: W1 1/23 | C115: W2 1/30 | D115: W3 2/06 | E115: W4 2/13 | F115: W5 2/20 | G115: W6 2/27 | H115: W7 3/06 | I115: W8 3/20 | J115: W9 3/27 | K115: W10 4/03 | L115: W11 4/10 | M115: W12 4/17 | N115: W13 4/24 | O115: W14 5/01 | P115: W15 5/08 | Q115: CUM
A116: INT 1010 — Intro to Info Tech | P116: 55 | Q116: 55
A119: TR-0029 — FOSTER, BRYANT | R119: Current Good A's
A120: Spring 2026 (Current)
A121: Course | B121: W1 1/22 | C121: W2 1/29 | D121: W3 2/05 | E121: W4 2/12 | F121: W5 2/19 | G121: W6 2/26 | H121: W7 3/05 | I121: W8 3/19 | J121: W9 3/26 | K121: W10 4/01* | L121: W11 4/09 | M121: W12 4/16 | N121: W13 4/23 | O121: W14 4/30 | P121: W15 5/07 | Q121: CUM
A122: SOC 1010 — Introduction to Sociology | J122: 77.1% | Q122: 77.1%
A123: NTR 1010 — Introduction to Nutrition | J123: 89.5% | Q123: 89.5%
A125: Fall 2025 (10th Grade)
A126: Course | B126: W1 8/21 | C126: W2 8/28 | D126: W3 9/04 | E126: W4 9/11 | F126: W5 9/18 | G126: W6 9/25 | H126: W7 10/02 | I126: W8 10/09 | J126: W9 10/16 | K126: W10 10/23 | L126: W11 10/30 | M126: W12 11/06 | N126: W13 11/13 | O126: W14 11/20 | P126: W15 12/04 | Q126: CUM
A127: COM 1010 — Speech Communication | P127: 87.14 | Q127: 87.14
A128: INT 1700 — Understanding OS | P128: 84 | Q128: 84
A130: Spring 2025 (9th Grade)
A131: Course | B131: W1 1/23 | C131: W2 1/30 | D131: W3 2/06 | E131: W4 2/13 | F131: W5 2/20 | G131: W6 2/27 | H131: W7 3/06 | I131: W8 3/20 | J131: W9 3/27 | K131: W10 4/03 | L131: W11 4/10 | M131: W12 4/17 | N131: W13 4/24 | O131: W14 5/01 | P131: W15 5/08 | Q131: CUM
...

Sheet Cohort 2029 — Grades
A1: ⬅ NAVIGATE: | B1: 📍 Nav Hub | C1: ⚡ Command | D1: 👥 2026 | E1: 👥 2027 | F1: 👥 2028 | G1: 👥 2029
A2: ElevateED — COHORT 2029 — 9th Grade Freshmen | 16 Students | Weekly Grade Tracker
A3: Talent Ready IT Program | Largo High School | Prince George's Community College
A4: Maryland Blueprint for Maryland's Future | CONFIDENTIAL — FERPA PROTECTED | February 13, 2026
A5: Current: Spring 2026 (INT 1111 + PAS 1000 for select students) | Prior: Fall 2025 (INT 1010) | Grades due every Thursday by 2:00 PM | PGCC Calendar synced | * = Holiday Thu, due day before
A7: TR-0042 — AKINSANYA, TIARAOLUWA
A8: Spring 2026 (Current)
A9: Course | B9: W1 1/22 | C9: W2 1/29 | D9: W3 2/05 | E9: W4 2/12 | F9: W5 2/19 | G9: W6 2/26 | H9: W7 3/05 | I9: W8 3/19 | J9: W9 3/26 | K9: W10 4/01* | L9: W11 4/09 | M9: W12 4/16 | N9: W13 4/23 | O9: W14 4/30 | P9: W15 5/07 | Q9: CUM
A10: INT 1111 — Introduction to IT II | Q10: 99.17
A12: Fall 2025 (First Semester)
A13: Course | B13: W1 8/21 | C13: W2 8/28 | D13: W3 9/04 | E13: W4 9/11 | F13: W5 9/18 | G13: W6 9/25 | H13: W7 10/02 | I13: W8 10/09 | J13: W9 10/16 | K13: W10 10/23 | L13: W11 10/30 | M13: W12 11/06 | N13: W13 11/13 | O13: W14 11/20 | P13: W15 12/04 | Q13: CUM
A14: INT 1010 — Intro to Information Technology | P14: 85.22 | Q14: 60.9%
A17: TR-0043 — ATKINS, PEYTON
A18: Spring 2026 (Current)
A19: Course | B19: W1 1/22 | C19: W2 1/29 | D19: W3 2/05 | E19: W4 2/12 | F19: W5 2/19 | G19: W6 2/26 | H19: W7 3/05 | I19: W8 3/19 | J19: W9 3/26 | K19: W10 4/01* | L19: W11 4/09 | M19: W12 4/16 | N19: W13 4/23 | O19: W14 4/30 | P19: W15 5/07 | Q19: CUM
A20: INT 1111 — Introduction to IT II | Q20: 95
A21: PAS 1000 — Personal & Academic Success | Q21: 12.25
A23: Fall 2025 (First Semester)
A24: Course | B24: W1 8/21 | C24: W2 8/28 | D24: W3 9/04 | E24: W4 9/11 | F24: W5 9/18 | G24: W6 9/25 | H24: W7 10/02 | I24: W8 10/09 | J24: W9 10/16 | K24: W10 10/23 | L24: W11 10/30 | M24: W12 11/06 | N24: W13 11/13 | O24: W14 11/20 | P24: W15 12/04 | Q24: CUM
A25: INT 1010 — Intro to Information Technology | P25: 62.61 | Q25: 89.3%
A28: TR-0044 — BELCHER, MALACHI
A29: Spring 2026 (Current)
A30: Course | B30: W1 1/22 | C30: W2 1/29 | D30: W3 2/05 | E30: W4 2/12 | F30: W5 2/19 | G30: W6 2/26 | H30: W7 3/05 | I30: W8 3/19 | J30: W9 3/26 | K30: W10 4/01* | L30: W11 4/09 | M30: W12 4/16 | N30: W13 4/23 | O30: W14 4/30 | P30: W15 5/07 | Q30: CUM
A31: INT 1111 — Introduction to IT II | Q31: 100
A33: Fall 2025 (First Semester)
A34: Course | B34: W1 8/21 | C34: W2 8/28 | D34: W3 9/04 | E34: W4 9/11 | F34: W5 9/18 | G34: W6 9/25 | H34: W7 10/02 | I34: W8 10/09 | J34: W9 10/16 | K34: W10 10/23 | L34: W11 10/30 | M34: W12 11/06 | N34: W13 11/13 | O34: W14 11/20 | P34: W15 12/04 | Q34: CUM
A35: INT 1010 — Intro to Information Technology | P35: 77.68 | Q35: 65.3%
A38: TR-0045 — DUMAS, ADDISON
A39: Spring 2026 (Current)
A40: Course | B40: W1 1/22 | C40: W2 1/29 | D40: W3 2/05 | E40: W4 2/12 | F40: W5 2/19 | G40: W6 2/26 | H40: W7 3/05 | I40: W8 3/19 | J40: W9 3/26 | K40: W10 4/01* | L40: W11 4/09 | M40: W12 4/16 | N40: W13 4/23 | O40: W14 4/30 | P40: W15 5/07 | Q40: CUM
A41: INT 1111 — Introduction to IT II | Q41: 95.27
A43: Fall 2025 (First Semester)
A44: Course | B44: W1 8/21 | C44: W2 8/28 | D44: W3 9/04 | E44: W4 9/11 | F44: W5 9/18 | G44: W6 9/25 | H44: W7 10/02 | I44: W8 10/09 | J44: W9 10/16 | K44: W10 10/23 | L44: W11 10/30 | M44: W12 11/06 | N44: W13 11/13 | O44: W14 11/20 | P44: W15 12/04 | Q44: CUM
A45: INT 1010 — Intro to Information Technology | P45: 85.78 | Q45: 78.8%
A48: TR-0046 — HARRISON, MACKENZIE
A49: Spring 2026 (Current)
A50: Course | B50: W1 1/22 | C50: W2 1/29 | D50: W3 2/05 | E50: W4 2/12 | F50: W5 2/19 | G50: W6 2/26 | H50: W7 3/05 | I50: W8 3/19 | J50: W9 3/26 | K50: W10 4/01* | L50: W11 4/09 | M50: W12 4/16 | N50: W13 4/23 | O50: W14 4/30 | P50: W15 5/07 | Q50: CUM
A51: INT 1111 — Introduction to IT II | Q51: 96.47
A53: Fall 2025 (First Semester)
A54: Course | B54: W1 8/21 | C54: W2 8/28 | D54: W3 9/04 | E54: W4 9/11 | F54: W5 9/18 | G54: W6 9/25 | H54: W7 10/02 | I54: W8 10/09 | J54: W9 10/16 | K54: W10 10/23 | L54: W11 10/30 | M54: W12 11/06 | N54: W13 11/13 | O54: W14 11/20 | P54: W15 12/04 | Q54: CUM
A55: INT 1010 — Intro to Information Technology | P55: 63.16 | Q55: 78.8%
A58: TR-0047 — HARVEY, MEZRAH
A59: Spring 2026 (Current)
A60: Course | B60: W1 1/22 | C60: W2 1/29 | D60: W3 2/05 | E60: W4 2/12 | F60: W5 2/19 | G60: W6 2/26 | H60: W7 3/05 | I60: W8 3/19 | J60: W9 3/26 | K60: W10 4/01* | L60: W11 4/09 | M60: W12 4/16 | N60: W13 4/23 | O60: W14 4/30 | P60: W15 5/07 | Q60: CUM
A61: INT 1111 — Introduction to IT II | Q61: 71.43
A63: Fall 2025 (First Semester)
A64: Course | B64: W1 8/21 | C64: W2 8/28 | D64: W3 9/04 | E64: W4 9/11 | F64: W5 9/18 | G64: W6 9/25 | H64: W7 10/02 | I64: W8 10/09 | J64: W9 10/16 | K64: W10 10/23 | L64: W11 10/30 | M64: W12 11/06 | N64: W13 11/13 | O64: W14 11/20 | P64: W15 12/04 | Q64: CUM
A65: INT 1010 — Intro to Information Technology | P65: 68.07 | Q65: 80.4%
A68: TR-0048 — HERBERT, HYON
A69: Spring 2026 (Current)
A70: Course | B70: W1 1/22 | C70: W2 1/29 | D70: W3 2/05 | E70: W4 2/12 | F70: W5 2/19 | G70: W6 2/26 | H70: W7 3/05 | I70: W8 3/19 | J70: W9 3/26 | K70: W10 4/01* | L70: W11 4/09 | M70: W12 4/16 | N70: W13 4/23 | O70: W14 4/30 | P70: W15 5/07 | Q70: CUM
A71: INT 1111 — Introduction to IT II | Q71: 83.75
A72: PAS 1000 — Personal & Academic Success | Q72: 26.88
A74: Fall 2025 (First Semester)
A75: Course | B75: W1 8/21 | C75: W2 8/28 | D75: W3 9/04 | E75: W4 9/11 | F75: W5 9/18 | G75: W6 9/25 | H75: W7 10/02 | I75: W8 10/09 | J75: W9 10/16 | K75: W10 10/23 | L75: W11 10/30 | M75: W12 11/06 | N75: W13 11/13 | O75: W14 11/20 | P75: W15 12/04 | Q75: CUM
A76: INT 1010 — Intro to Information Technology | P76: 60.85 | Q76: 69.2%
A79: TR-0049 — JOSEPH-ALEXANDER, SHILOH
A80: Spring 2026 (Current)
A81: Course | B81: W1 1/22 | C81: W2 1/29 | D81: W3 2/05 | E81: W4 2/12 | F81: W5 2/19 | G81: W6 2/26 | H81: W7 3/05 | I81: W8 3/19 | J81: W9 3/26 | K81: W10 4/01* | L81: W11 4/09 | M81: W12 4/16 | N81: W13 4/23 | O81: W14 4/30 | P81: W15 5/07 | Q81: CUM
A82: INT 1111 — Introduction to IT II | Q82: 94.29
A84: Fall 2025 (First Semester)
A85: Course | B85: W1 8/21 | C85: W2 8/28 | D85: W3 9/04 | E85: W4 9/11 | F85: W5 9/18 | G85: W6 9/25 | H85: W7 10/02 | I85: W8 10/09 | J85: W9 10/16 | K85: W10 10/23 | L85: W11 10/30 | M85: W12 11/06 | N85: W13 11/13 | O85: W14 11/20 | P85: W15 12/04 | Q85: CUM
A86: INT 1010 — Intro to Information Technology | P86: 71.58 | Q86: 85.6%
A89: TR-0050 — LASHLEY, AVA
A90: Spring 2026 (Current)
A91: Course | B91: W1 1/22 | C91: W2 1/29 | D91: W3 2/05 | E91: W4 2/12 | F91: W5 2/19 | G91: W6 2/26 | H91: W7 3/05 | I91: W8 3/19 | J91: W9 3/26 | K91: W10 4/01* | L91: W11 4/09 | M91: W12 4/16 | N91: W13 4/23 | O91: W14 4/30 | P91: W15 5/07 | Q91: CUM
A92: INT 1111 — Introduction to IT II | Q92: 96.67
A94: Fall 2025 (First Semester)
A95: Course | B95: W1 8/21 | C95: W2 8/28 | D95: W3 9/04 | E95: W4 9/11 | F95: W5 9/18 | G95: W6 9/25 | H95: W7 10/02 | I95: W8 10/09 | J95: W9 10/16 | K95: W10 10/23 | L95: W11 10/30 | M95: W12 11/06 | N95: W13 11/13 | O95: W14 11/20 | P95: W15 12/04 | Q95: CUM
A96: INT 1010 — Intro to Information Technology | P96: 72.28 | Q96: 83.9%
A99: TR-0051 — LOWERY, CADEN
A100: Spring 2026 (Current)
A101: Course | B101: W1 1/22 | C101: W2 1/29 | D101: W3 2/05 | E101: W4 2/12 | F101: W5 2/19 | G101: W6 2/26 | H101: W7 3/05 | I101: W8 3/19 | J101: W9 3/26 | K101: W10 4/01* | L101: W11 4/09 | M101: W12 4/16 | N101: W13 4/23 | O101: W14 4/30 | P101: W15 5/07 | Q101: CUM
A102: INT 1111 — Introduction to IT II | Q102: 97.27
A104: Fall 2025 (First Semester)
A105: Course | B105: W1 8/21 | C105: W2 8/28 | D105: W3 9/04 | E105: W4 9/11 | F105: W5 9/18 | G105: W6 9/25 | H105: W7 10/02 | I105: W8 10/09 | J105: W9 10/16 | K105: W10 10/23 | L105: W11 10/30 | M105: W12 11/06 | N105: W13 11/13 | O105: W14 11/20 | P105: W15 12/04 | Q105: CUM
A106: INT 1010 — Intro to Information Technology | P106: 75.56 | Q106: 100.0%
A109: TR-0052 — ONUOSA, NICHOLAS
A110: Spring 2026 (Current)
A111: Course | B111: W1 1/22 | C111: W2 1/29 | D111: W3 2/05 | E111: W4 2/12 | F111: W5 2/19 | G111: W6 2/26 | H111: W7 3/05 | I111: W8 3/19 | J111: W9 3/26 | K111: W10 4/01* | L111: W11 4/09 | M111: W12 4/16 | N111: W13 4/23 | O111: W14 4/30 | P111: W15 5/07 | Q111: CUM
A112: INT 1111 — Introduction to IT II | Q112: 92.38
A114: Fall 2025 (First Semester)
A115: Course | B115: W1 8/21 | C115: W2 8/28 | D115: W3 9/04 | E115: W4 9/11 | F115: W5 9/18 | G115: W6 9/25 | H115: W7 10/02 | I115: W8 10/09 | J115: W9 10/16 | K115: W10 10/23 | L115: W11 10/30 | M115: W12 11/06 | N115: W13 11/13 | O115: W14 11/20 | P115: W15 12/04 | Q115: CUM
A116: INT 1010 — Intro to Information Technology | P116: 88.75 | Q116: 70.4%
A119: TR-0053 — ROBINSON, MATTHEW
A120: Spring 2026 (Current)
A121: Course | B121: W1 1/22 | C121: W2 1/29 | D121: W3 2/05 | E121: W4 2/12 | F121: W5 2/19 | G121: W6 2/26 | H121: W7 3/05 | I121: W8 3/19 | J121: W9 3/26 | K121: W10 4/01* | L121: W11 4/09 | M121: W12 4/16 | N121: W13 4/23 | O121: W14 4/30 | P121: W15 5/07 | Q121: CUM
A122: INT 1111 — Introduction to IT II | Q122: 98.75
A124: Fall 2025 (First Semester)
A125: Course | B125: W1 8/21 | C125: W2 8/28 | D125: W3 9/04 | E125: W4 9/11 | F125: W5 9/18 | G125: W6 9/25 | H125: W7 10/02 | I125: W8 10/09 | J125: W9 10/16 | K125: W10 10/23 | L125: W11 10/30 | M125: W12 11/06 | N125: W13 11/13 | O125: W14 11/20 | P125: W15 12/04 | Q125: CUM
A126: INT 1010 — Intro to Information Technology | P126: 83.75 | Q126: 99.5%
A129: TR-0054 — SAUNDERS, MADELINE
A130: Spring 2026 (Current)
A131: Course | B131: W1 1/22 | C131: W2 1/29 | D131: W3 2/05 | E131: W4 2/12 | F131: W5 2/19 | G131: W6 2/26 | H131: W7 3/05 | I131: W8 3/19 | J131: W9 3/26 | K131: W10 4/01* | L131: W11 4/09 | M131: W12 4/16 | N131: W13 4/23 | O131: W14 4/30 | P131: W15 5/07 | Q131: CUM
A132: INT 1111 — Introduction to IT II | Q132: 94.87
A134: Fall 2025 (First Semester)
A135: Course | B135: W1 8/21 | C135: W2 8/28 | D135: W3 9/04 | E135: W4 9/11 | F135: W5 9/18 | G135: W6 9/25 | H135: W7 10/02 | I135: W8 10/09 | J135: W9 10/16 | K135: W10 10/23 | L135: W11 10/30 | M135: W12 11/06 | N135: W13 11/13 | O135: W14 11/20 | P135: W15 12/04 | Q135: CUM
A136: INT 1010 — Intro to Information Technology | P136: 80.74 | Q136: 71.4%
A139: TR-0055 — SHEIKH, MUHAMMAD D.
A140: Spring 2026 (Current)
...

Sheet Predictive Analytics
A1: ⬅ NAVIGATE:
A2: ElevateED — PREDICTIVE ANALYTICS ENGINE
A3: Talent Ready IT Program | Largo High School | Prince George's Community College
A4: Maryland Blueprint for Maryland's Future | CONFIDENTIAL — FERPA PROTECTED | Generated: February 13, 2026 03:41 PM
A5: 6-Factor Risk Algorithm | Trajectory Modeling | Early Warning System | Updated: February 13, 2026 03:41 PM
A6: Student ID | B6: Name | C6: Cohort | D6: Current Avg | E6: 4wk Trend | F6: Attendance | G6: Assignments | H6: IEP Factor | I6: Engagement | J6: RISK SCORE | K6: RISK LEVEL | L6: Days to At-Risk | M6: Predicted EOY | N6: Confidence
A7: TR-0001 | B7: CRICHTON III, LEONARD | C7: 2026 | D7: 0.952 | E7: 3.8 | F7: 0.95 | G7: 0.92 | H7: 0.93 | I7: 0.9 | J7: 5.8 | K7: LOW | L7: N/A | M7: 0.97 | N7: 0.88
A8: TR-0002 | B8: CROWELL, KINGSTON | C8: 2026 | D8: 0.959 | E8: 4.2 | F8: 0.97 | G8: 0.94 | H8: 0.93 | I8: 0.91 | J8: 4.6 | K8: LOW | L8: N/A | M8: 0.98 | N8: 0.9
A9: TR-0003 | B9: DAVIS, GABRIEL | C9: 2026 | D9: 0.88 | E9: 1.5 | F9: 0.88 | G9: 0.85 | H9: 0.93 | I9: 0.82 | J9: 12.3 | K9: LOW | L9: N/A | M9: 0.91 | N9: 0.82
A10: TR-0004 | B10: FERSNER, LAILAH | C10: 2026 | D10: 0.952 | E10: 2.8 | F10: 0.93 | G10: 0.95 | H10: 0.93 | I10: 0.94 | J10: 5 | K10: LOW | L10: N/A | M10: 0.97 | N10: 0.89
A11: TR-0005 | B11: FORD, JAMES | C11: 2026 | D11: 0.956 | E11: 1.2 | F11: 0.9 | G11: 0.88 | H11: 0.75 | I11: 0.85 | J11: 9.7 | K11: LOW | L11: N/A | M11: 0.96 | N11: 0.83
A12: TR-0006 | B12: FORREST, TYLEYL | C12: 2026 | D12: 1 | E12: 5.1 | F12: 0.98 | G12: 0.97 | H12: 0.93 | I12: 0.96 | J12: 0.9 | K12: LOW | L12: N/A | M12: 1 | N12: 0.92
A13: TR-0007 | B13: JALLOH, JENABU | C13: 2026 | D13: 0.896 | E13: 0.5 | F13: 0.86 | G13: 0.84 | H13: 0.93 | I13: 0.8 | J13: 12.6 | K13: LOW | L13: N/A | M13: 0.9 | N13: 0.8
A14: TR-0008 | B14: JOHNSON-BONILLA, CHRISTOPHER | C14: 2026 | D14: 0.967 | E14: 3.3 | F14: 0.95 | G14: 0.93 | H14: 0.93 | I14: 0.92 | J14: 4.8 | K14: LOW | L14: N/A | M14: 0.98 | N14: 0.89
A15: TR-0009 | B15: OLUBIYI, OLUWANIFEMI | C15: 2026 | D15: 0.993 | E15: 4.5 | F15: 0.96 | G15: 0.96 | H15: 0.93 | I15: 0.95 | J15: 2.6 | K15: LOW | L15: N/A | M15: 0.99 | N15: 0.91
A16: TR-0010 | B16: SANNI, MOFEOLUWA | C16: 2026 | D16: 0.953 | E16: 2 | F16: 0.94 | G16: 0.93 | H16: 0.93 | I16: 0.91 | J16: 5.6 | K16: LOW | L16: N/A | M16: 0.97 | N16: 0.88
A17: TR-0011 | B17: SCARLETT, OLIVIA | C17: 2026 | D17: 0.89 | E17: -1.2 | F17: 0.82 | G17: 0.8 | H17: 0.93 | I17: 0.78 | J17: 14.8 | K17: LOW | L17: N/A | M17: 0.88 | N17: 0.78
A18: TR-0012 | B18: WALLACE, JUSTIN | C18: 2026 | D18: 0.953 | E18: 3 | F18: 0.93 | G18: 0.94 | H18: 0.93 | I18: 0.9 | J18: 5.7 | K18: LOW | L18: N/A | M18: 0.97 | N18: 0.87
... A65: TR-0057 | B65: VIDAL, JOSHUA | C65: 2029 | D65: 0.693 | E65: -1 | F65: 0.74 | G65: 0.68 | H65: 0.93 | I65: 0.64 | J65: 27.7 | K65: MODERATE | L65: 26 days | M65: 0.68 | N65: 0.72

Sheet Executive Dashboard
A1: ⬅ NAVIGATE:
A2: ElevateED — EXECUTIVE REPORTING SUITE
A3: Talent Ready IT Program | Largo High School | Prince George's Community College
A4: Maryland Blueprint for Maryland's Future | CONFIDENTIAL — FERPA PROTECTED | Generated: February 13, 2026 03:41 PM
A5: Board KPIs | WoW/MoM/QoQ Trends | Benchmarking | For Director & Administrator Review
A6: TREND ANALYSIS — WEEK OVER WEEK / MONTH OVER MONTH / QUARTER OVER QUARTER
A7: Metric | B7: Current | C7: 1 Wk Ago | D7: Δ WoW | E7: 1 Mo Ago | F7: Δ MoM | G7: Last Qtr | H7: Δ QoQ
A8: Program Average | B8: 82.8% | C8: 82.1% | D8: +0.7% | E8: 79.5% | F8: +3.3% | G8: 76.2% | H8: +6.6%
A9: CCR Attainment (≥70%) | B9: 88.1% | C9: 87.3% | D9: +0.8% | E9: 84.0% | F9: +4.1% | G9: 80.5% | H9: +7.6%
A10: Honor Roll (≥90%) | B10: 37.3% | C10: 35.6% | D10: +1.7% | E10: 30.1% | F10: +7.2% | G10: 25.4% | H10: +11.9%
A11: Tier 1 Rate | B11: 55.9% | C11: 54.2% | D11: +1.7% | E11: 50.0% | F11: +5.9% | G11: 45.0% | H11: +10.9%
A12: Tier 3 Rate (target <5%) | B12: 3.4% | C12: 5.1% | D12: -1.7% | E12: 6.8% | F12: -3.4% | G12: 8.5% | H12: -5.1%
A13: Student Retention | B13: 93.7% | C13: 93.7% | D13: 0.0% | E13: 95.2% | F13: -1.5% | G13: 100% | H13: -6.3%
A14: Parent Engagement | B14: 68.0% | C14: 65.0% | D14: +3.0% | E14: 55.0% | F14: +13.0% | G14: 42.0% | H14: +26.0%
A15: Avg Risk Score | B15: 24.8 | C15: 26.1 | D15: -1.3 | E15: 30.5 | F15: -5.7 | G15: 35.2 | H15: -10.4
A18: COHORT BENCHMARKING — PERFORMANCE vs. TARGETS
A19: Cohort | B19: Current Avg | C19: Target | D19: Gap | E19: On Track % | F19: CCR % | G19: Honor % | H19: Tier 3 Count | I19: Action Needed
A20: Class of 2026 | B20: 94.7% | C20: 85% | D20: +9.7% | E20: 100% | F20: 100% | G20: 94.1% | H20: 0 | I20: Maintain — all exceeding targets
A21: Class of 2027 | B21: 76.4% | C21: 80% | D21: -3.6% | E21: 66.7% | F21: 83.3% | G21: 16.7% | H21: 1 | I21: INT 1550 avg below target — tutoring needed
A22: Class of 2028 | B22: 78.2% | C22: 80% | D22: -1.8% | E22: 80.0% | F22: 90.0% | G22: 20.0% | H22: 2 | I22: COM 1010 at-risk students need SIT meetings
A23: Class of 2029 | B23: 78.3% | C23: 80% | D23: -1.7% | E23: 56.3% | F23: 75.0% | G23: 18.8% | H23: 0 | I23: 6 students in Watch zone — study groups
A26: SYSTEM BUILD PHASES — COMPLETION TRACKER
A27: Phase | B27: Name | C27: Components | D27: Status | E27: Progress
A28: Phase 1 | B28: Data Foundation | C28: Student Master, Cohort Sheets, Grade Entry | D28: ✅ Complete | E28: 100%
A29: Phase 2 | B29: Analytics Engine | C29: Predictive Analytics, Executive Dashboard | D29: ✅ Complete | E29: 100%
A30: Phase 3 | B30: Interventions | C30: MTSS Tracker, Intervention Planner, Compliance | D30: ✅ Complete | E30: 100%
A31: Phase 4 | B31: Communications | C31: Parent Engagement, Newsletter System | D31: ✅ Complete | E31: 100%
A32: Phase 5 | B32: Automation | C32: Grade Velocity, What-If Calculator, Alerts | D32: ✅ Complete | E32: 100%
A33: Phase 6 | B33: Reporting | C33: Blueprint Metrics, PDF Reports, Print Grids | D33: ✅ Complete | E33: 100%
A34: Phase 7 | B34: Integration | C34: Google Drive Deploy, Access Control, Audit | D34: ✅ Complete | E34: 100%
A35: Phase 8 | B35: ASI Enhancements | C35: Predictive AI, Resource Planning, Compliance | D35: ✅ Complete | E35: 100%

Sheet Intervention Planner
A1: ⬅ NAVIGATE:
A2: ElevateED — STUDENT INTERVENTION PLANNER
A3: Talent Ready IT Program | Largo High School | Prince George's Community College
A4: Maryland Blueprint for Maryland's Future | CONFIDENTIAL — FERPA PROTECTED | Generated: February 13, 2026 03:41 PM
A5: Evidence-Based Plans | SIT Agenda | MTSS Alignment | Blueprint Pillar 4
A6: Plan ID | B6: Student | C6: Cohort | D6: MTSS | E6: Current | F6: Target | G6: Strategy | H6: Start | I6: Review | J6: Pre-Score | K6: Post-Score | L6: Effectiveness | M6: Status
A7: IP-001 | B7: FORD, CHASE (TR-0059) | C7: 2028 | D7: Tier 3 | E7: 47.2% | F7: 70% | G7: Daily check-in + peer tutoring + parent weekly calls | H7: Jan 13 | I7: Feb 24 | J7: 42% | K7: 47.2% | L7: ↑ Improving | M7: Active
A8: IP-002 | B8: BYFIELD, KIMANI (TR-0017) | C8: 2027 | D8: Tier 3 | E8: 57.4% | F8: 70% | G8: Academic coaching M/W/F + INT 1550 study group | H8: Jan 20 | I8: Mar 3 | J8: 53% | K8: 57.4% | L8: ↑ Improving | M8: Active
A9: IP-003 | B9: AHETO, EDWIN (TR-0023) | C9: 2028 | D9: Tier 2 | E9: 57.0% | F9: 72% | G9: Peer tutoring T/Th + COM 1010 extra credit plan | H9: Jan 27 | I9: Mar 10 | J9: 54% | K9: 57.0% | L9: ↑ Improving | M9: Active
A10: IP-004 | B10: MONROE-HOOD, JAHDAI (TR-0032) | C10: 2028 | D10: Tier 3 | E10: 58.3% | F10: 70% | G10: Study skills workshop + weekly progress contract | H10: Feb 3 | I10: Mar 17 | J10: 55% | K10: 58.3% | L10: ↑ Improving | M10: Active
A11: IP-005 | B11: AKINSANYA, TIARAOLUWA (TR-0042) | C11: 2029 | D11: Tier 2 | E11: 60.9% | F11: 75% | G11: 1:1 tutoring + structured study plan | H11: Feb 3 | I11: Mar 17 | J11: 58% | K11: 60.9% | L11: ↑ Improving | M11: Active
A12: IP-006 | B12: ERHABOR, ELAION (TR-0027) | C12: 2028 | D12: Tier 2 | E12: 61.2% | F12: 75% | G12: COM 1010 speech practice sessions + office hours | H12: Feb 10 | I12: Mar 24 | J12: 59% | K12: 61.2% | L12: → Stable | M12: Active
A13: IP-007 | B13: LAMBRIGHT, KADYN (TR-0019) | C13: 2027 | D13: Tier 1/2 | E13: 64.2% | F13: 75% | G13: Network+ lab time extension + study buddy | H13: Jan 27 | I13: Mar 10 | J13: 62% | K13: 64.2% | L13: ↑ Improving | M13: Monitoring
A14: IP-008 | B14: BELCHER, MALACHI (TR-0044) | C14: 2029 | D14: Tier 1/2 | E14: 65.3% | F14: 75% | G14: Attendance improvement plan + parent check-in | H14: Feb 10 | I14: Mar 24 | J14: 63% | K14: 65.3% | L14: → Stable | M14: Monitoring
A15: IP-009 | B15: HODGE, AMANI (TR-0018) | C15: 2027 | D15: Tier 1/2 | E15: 65.0% | F15: 75% | G15: BIO 1120 lab report support + study schedule | H15: Feb 10 | I15: Mar 24 | J15: 62% | K15: 65.0% | L15: → Stable | M15: Monitoring
A16: IP-010 | B16: HERBERT, HYON (TR-0048) | C16: 2029 | D16: Tier 1/2 | E16: 69.2% | F16: 78% | G16: INT 1010 lab completion plan + time management | H16: Feb 17 | I16: Mar 31 | J16: 67% | K16: 69.2% | L16: → Stable | M16: Monitoring

Sheet MTSS Tracker
A1: ⬅ NAVIGATE:
A2: ElevateED — MTSS INTERVENTION TRACKER
A3: Talent Ready IT Program | Largo High School | Prince George's Community College
A4: Maryland Blueprint for Maryland's Future | CONFIDENTIAL — FERPA PROTECTED | February 13, 2026 03:48 PM
A5: Blueprint Pillar 4 — Multi-Tiered System of Supports | All flagged students | Updated: February 13, 2026 03:48 PM
A6: Student ID | B6: Last Name | C6: First Name | D6: Cohort | E6: Current Avg | F6: MTSS Tier | G6: Status | H6: Intervention Type | I6: Date Flagged | J6: Coordinator Notified | K6: Parent Notified | L6: Action Plan | M6: Follow-Up | N6: Resolution
A7: TR-0059 | B7: FORD | C7: CHASE | D7: 2028 | E7: 47.2 | F7: Tier 3 | G7: Not Progressing | H7: Daily check-in + peer tutor | I7: 2026-01-13 | J7: 2026-01-13 | K7: 2026-01-14 | L7: Parent meeting scheduled 1/20. Peer tutor assigned (TR-0031 JOHNSON). | M7: Weekly review | N7: Active — improving slowly
A8: TR-0017 | B8: BYFIELD | C8: KIMANI | D8: 2027 | E8: 57.4 | F8: Tier 3 | G8: Not Progressing | H8: Academic coaching M/W/F | I8: 2026-01-20 | J8: 2026-01-20 | K8: 2026-01-21 | L8: INT 1550 study group formed. Extra lab time approved. | M8: Bi-weekly SIT | N8: Active — on trajectory
A9: TR-0023 | B9: AHETO | C9: EDWIN | D9: 2028 | E9: 57 | F9: Tier 2 | G9: At Risk | H9: Peer tutoring T/Th | I9: 2026-01-27 | J9: 2026-01-27 | K9: 2026-01-28 | L9: COM 1010 extra credit plan approved by instructor. | M9: Weekly check-in | N9: Active — improving
A10: TR-0032 | B10: MONROE-HOOD | C10: JAHDAI | D10: 2028 | E10: 58.3 | F10: Tier 3 | G10: Not Progressing | H10: Weekly progress contract | I10: 2026-02-03 | J10: 2026-02-03 | K10: 2026-02-04 | L10: Study skills workshop completed. Contract signed by student and parent. | M10: Bi-weekly SIT | N10: Active — early signs
A11: TR-0042 | B11: AKINSANYA | C11: TIARAOLUWA | D11: 2029 | E11: 60.9 | F11: Tier 2 | G11: At Risk | H11: 1:1 tutoring | I11: 2026-02-03 | J11: 2026-02-03 | K11: 2026-02-04 | L11: Structured study plan with daily INT 1010 practice. | M11: Weekly check-in | N11: Active — improving
A12: TR-0027 | B12: ERHABOR | C12: ELAION | D12: 2028 | E12: 61.2 | F12: Tier 2 | G12: At Risk | H12: Office hours + speech practice | I12: 2026-02-10 | J12: 2026-02-10 | K12: 2026-02-11 | L12: COM 1010 speech coaching sessions scheduled. | M12: Weekly check-in | N12: Active — stable
A13: TR-0019 | B13: LAMBRIGHT | C13: KADYN | D13: 2027 | E13: 64.2 | F13: Tier 1/2 | G13: Watch | H13: Study buddy assignment | I13: 2026-01-27 | J13: 2026-01-27 | K13: 2026-01-28 | L13: Paired with TR-0022 WARD for INT 1550 lab work. | M13: Bi-weekly | N13: Monitoring
A14: TR-0044 | B14: BELCHER | C14: MALACHI | D14: 2029 | E14: 65.3 | F14: Tier 1/2 | G14: Watch | H14: Attendance plan | I14: 2026-02-10 | J14: 2026-02-10 | K14: 2026-02-11 | L14: Attendance improvement contract. Parent conference completed. | M14: Weekly | N14: Monitoring
A15: TR-0018 | B15: HODGE | C15: AMANI | D15: 2027 | E15: 65 | F15: Tier 1/2 | G15: Watch | H15: Lab report support | I15: 2026-02-10 | J15: 2026-02-10 | K15: 2026-02-11 | L15: BIO 1120 lab report template provided. Study schedule created. | M15: Weekly | N15: Monitoring
A16: TR-0048 | B16: HERBERT | C16: HYON | D16: 2029 | E16: 69.2 | F16: Tier 1/2 | G16: Watch | H16: Time management | I16: 2026-02-17 | J16: 2026-02-17 | K16: 2026-02-18 | L16: INT 1010 lab completion calendar. Weekly planner provided. | M16: Bi-weekly | N16: Monitoring
A17: TR-0057 | B17: VIDAL | C17: JOSHUA | D17: 2029 | E17: 69.3 | F17: Tier 1/2 | G17: Watch | H17: Study skills | I17: 2026-02-10 | J17: 2026-02-10 | K17: 2026-02-11 | L17: Study plan with daily practice schedule. Parent aware. | M17: Bi-weekly | N17: Monitoring
A18: TR-0036 | B18: NAVARRO-MARTINEZ | C18: MARTHA | D18: 2028 | E18: 71.3 | F18: Tier 1/2 | G18: Watch | H18: Extra practice | I18: 2026-02-10 | J18: 2026-02-10 | K18: 2026-02-11 | L18: INT 1700 practice labs assigned. Monitor grades weekly. | M18: Bi-weekly | N18: Monitoring
A19: TR-0052 | B19: ONUOSA | C19: NICHOLAS | D19: 2029 | E19: 70.4 | F19: Tier 1/2 | G19: Watch | H19: Academic coaching | I19: 2026-02-17 | J19: 2026-02-17 | K19: 2026-02-18 | L19: INT 1010 concept review sessions. Weekly quiz prep. | M19: Bi-weekly | N19: Monitoring

Sheet Course Performance
A1: ⬅ NAVIGATE:
A2: ElevateED — COURSE PERFORMANCE ANALYTICS
A3: Talent Ready IT Program | Largo High School | Prince George's Community College
A4: Maryland Blueprint for Maryland's Future | CONFIDENTIAL — FERPA PROTECTED | February 13, 2026 03:48 PM
A5: 10 PGCC Courses | Pass Rate | Grade Distribution | Instructor Analysis | Fall 2025 + Spring 2026
A6: Course | B6: Section | C6: Semester | D6: Instructor | E6: Students | F6: Avg Grade | G6: Pass Rate | H6: A/B | I6: C | J6: D/F | K6: Highest | L6: Lowest
A7: Calculus | B7: Fall 2025 | C7: Fall 2025 | D7: PGCC Faculty | E7: 17 | F7: 91.9% | G7: 100% | H7: 16 | I7: 1 | J7: 0 | K7: 98.0 | L7: 78.9
A8: Psychology | B8: Fall 2025 | C8: Fall 2025 | D8: PGCC Faculty | E8: 17 | F8: 89.5% | G8: 100% | H8: 14 | I8: 3 | J8: 0 | K8: 96.7 | L8: 76.7
A9: English | B9: Fall 2025 | C9: Fall 2025 | D9: PGCC Faculty | E9: 17 | F9: 90.4% | G9: 100% | H9: 14 | I9: 2 | J9: 1 | K9: 98.5 | L9: 71.3
A10: Art | B10: Fall 2025 | C10: Fall 2025 | D10: PGCC Faculty | E10: 17 | F10: 107.0% | G10: 100% | H10: 17 | I10: 0 | J10: 0 | K10: 118.0 | L10: 91.2
A11: INT 2840 — Sys Analysis/PM | B11: LD02T | C11: Spring 2026 | D11: Prof. Bartlebaugh | E11: 17 | F11: — | G11: — | H11: — | I11: — | J11: — | K11: — | L11: —
A12: INT 2310 — Windows Server | B12: LD01 | C12: Spring 2026 | D12: Prof. Walker | E12: 17 | F12: — | G12: — | H12: — | I12: — | J12: — | K12: — | L12: —
A13: EGL 1340 — Composition II | B13: LD08 | C13: Spring 2026 | D13: Dr. Kpalukwu | E13: 17 | F13: — | G13: — | H13: — | I13: — | J13: — | K13: — | L13: —
A14: BIO 1110 — Environ Biology | B14: DL01 | C14: Fall 2025 | D14: Prof. Tracy Ring | E14: 6 | F14: 77.2% | G14: 83.3% | H14: 3 | I14: 2 | J14: 1 | K14: 86.0 | L14: 66.2
A15: BIO 1120 — Environ Bio Lab | B15: DL01 | C15: Fall 2025 | D15: Prof. Tracy Ring | E15: 6 | F15: 77.6% | G15: 83.3% | H15: 2 | I15: 3 | J15: 1 | K15: 93.0 | L15: 65.0
A16: INT 1550 — Intro Networks | B16: RD02 | C16: Fall 2025 | D16: Prof. Rasoul Ahari | E16: 6 | F16: 74.1% | G16: 66.7% | H16: 2 | I16: 2 | J16: 2 | K16: 91.5 | L16: 57.4
A17: COM 1010 — Speech Comm | B17: RD04T | C17: Fall 2025 | D17: Per Syllabus | E17: 20 | F17: 77.9% | G17: 85.0% | H17: 10 | I17: 7 | J17: 3 | K17: 94.9 | L17: 47.2
A18: INT 1700 — Operating Sys | B18: RD03T | C18: Fall 2025 | D18: Prof. James Yang | E18: 20 | F18: 80.1% | G18: 90.0% | H18: 11 | I18: 7 | J18: 2 | K18: 98.5 | L18: 61.2
A19: INT 1010 — Intro to IT | B19: RD38T | C19: Fall 2025 | D19: Prof. Adeoye | E19: 16 | F19: 78.3% | G19: 75.0% | H19: 6 | I19: 6 | J19: 4 | K19: 100.0 | L19: 60.9

Sheet Grade Velocity
A1: ⬅ NAVIGATE:
A2: ElevateED — GRADE VELOCITY — WEEK OVER WEEK CHANGE ANALYSIS
A3: Talent Ready IT Program | Largo High School | Prince George's Community College
A4: Maryland Blueprint for Maryland's Future | CONFIDENTIAL — FERPA PROTECTED | February 13, 2026 03:48 PM
A5: Acceleration/Deceleration Detection | 4-Week Moving Average | Trajectory Prediction
A6: Student ID | B6: Name | C6: Cohort | D6: Current | E6: 4wk Δ | F6: 8wk Δ | G6: Velocity | H6: Acceleration | I6: Trajectory | J6: Alert
A7: TR-0001 | B7: CRICHTON III, LEONARD | C7: 2026 | D7: 95.2 | E7: 3.8 | F7: 5.2 | G7: ↑ Rising | H7: +0.4%/wk | I7: Exceeding
A8: TR-0002 | B8: CROWELL, KINGSTON | C8: 2026 | D8: 95.9 | E8: 4.2 | F8: 6 | G8: ↑ Rising | H8: +0.5%/wk | I8: Exceeding
A9: TR-0005 | B9: FORD, JAMES | C9: 2026 | D9: 95.6 | E9: 1.2 | F9: 2.8 | G9: → Stable | H9: +0.1%/wk | I9: Steady
A10: TR-0011 | B10: SCARLETT, OLIVIA | C10: 2026 | D10: 89 | E10: -1.2 | F10: -3.5 | G10: ↓ Declining | H10: -0.3%/wk | I10: Watch | J10: ⚠ Declining 2 wks
A11: TR-0058 | B11: SCOTT, SANAA | C11: 2026 | D11: 83.4 | E11: -0.5 | F11: -1.8 | G11: ↓ Declining | H11: -0.1%/wk | I11: Watch | J11: ⚠ Below cohort avg
A12: TR-0017 | B12: BYFIELD, KIMANI | C12: 2027 | D12: 67.8 | E12: -2.1 | F12: -5.4 | G12: ↓ Declining | H12: -0.5%/wk | I12: At Risk | J12: 🔴 Rapid decline
A13: TR-0019 | B13: LAMBRIGHT, KADYN | C13: 2027 | D13: 71.8 | E13: -1.8 | F13: -4 | G13: ↓ Declining | H13: -0.4%/wk | I13: At Risk | J13: 🔴 INT 1550 failing
A14: TR-0022 | B14: WARD, CANAAN | C14: 2027 | D14: 85.6 | E14: 3.5 | F14: 6.2 | G14: ↑ Rising | H14: +0.6%/wk | I14: Exceeding
A15: TR-0059 | B15: FORD, CHASE | C15: 2028 | D15: 56.1 | E15: -4.2 | F15: -8.5 | G15: ↓↓ Falling | H15: -1.0%/wk | I15: Critical | J15: 🔴 URGENT — below 60%
A16: TR-0032 | B16: MONROE-HOOD, JAHDAI | C16: 2028 | D16: 59.8 | E16: -3 | F16: -6.2 | G16: ↓↓ Falling | H16: -0.7%/wk | I16: Critical | J16: 🔴 URGENT — near 60%
A17: TR-0023 | B17: AHETO, EDWIN | C17: 2028 | D17: 77.8 | E17: -3.5 | F17: -5 | G17: ↓ Declining | H17: -0.5%/wk | I17: At Risk | J17: ⚠ COM 1010 issue
A18: TR-0033 | B18: MORGAN, ESSOON | C18: 2028 | D18: 92.3 | E18: 3 | F18: 5.5 | G18: ↑ Rising | H18: +0.5%/wk | I18: Exceeding
A19: TR-0040 | B19: WHITAKER, XION | C19: 2028 | D19: 87.7 | E19: 2.8 | F19: 4.5 | G19: ↑ Rising | H19: +0.4%/wk | I19: On Track
A20: TR-0042 | B20: AKINSANYA, TIARAOLUWA | C20: 2029 | D20: 60.9 | E20: -2.5 | F20: -4.8 | G20: ↓ Declining | H20: -0.5%/wk | I20: At Risk | J20: 🔴 Near threshold
A21: TR-0044 | B21: BELCHER, MALACHI | C21: 2029 | D21: 65.3 | E21: -1.5 | F21: -3.2 | G21: ↓ Declining | H21: -0.3%/wk | I21: Watch | J21: ⚠ Attendance issue
A22: TR-0051 | B22: LOWERY, CADEN | C22: 2029 | D22: 100 | E22: 5 | F22: 8 | G22: ↑↑ Surging | H22: +1.0%/wk | I22: Exceeding | J22: 🌟 Top performer
A23: TR-0053 | B23: ROBINSON, MATTHEW | C23: 2029 | D23: 99.5 | E23: 4.8 | F23: 7.5 | G23: ↑↑ Surging | H23: +0.9%/wk | I23: Exceeding | J23: 🌟 Top performer
A24: TR-0048 | B24: HERBERT, HYON | C24: 2029 | D24: 69.2 | E24: -0.8 | F24: -2.5 | G24: ↓ Declining | H24: -0.2%/wk | I24: Watch | J24: ⚠ Borderline CCR
A25: TR-0057 | B25: VIDAL, JOSHUA | C25: 2029 | D25: 69.3 | E25: -1 | F25: -3 | G25: ↓ Declining | H25: -0.3%/wk | I25: Watch | J25: ⚠ Borderline CCR

Sheet Compliance Center
A1: ⬅ NAVIGATE:
A2: ElevateED — COMPLIANCE COMMAND CENTER
A3: Talent Ready IT Program | Largo High School | Prince George's Community College
A4: Maryland Blueprint for Maryland's Future | CONFIDENTIAL — FERPA PROTECTED | Generated: February 13, 2026 03:41 PM
A5: FERPA 20-Point Audit | Breach Risk Assessment | Annual Review | 20 U.S.C. § 1232g
A6: # | B6: Requirement | C6: FERPA § | D6: Status | E6: Verified | F6: By | G6: Notes
A7: 1 | B7: Student records in locked physical location | C7: §99.31 | D7: ✅ PASS | E7: 2026-02-10 | F7: C. James | G7: Locked cabinet in Largo HS Room 204
A8: 2 | B8: Digital access requires authentication | C8: §99.31 | D8: ✅ PASS | E8: 2026-02-10 | F8: C. James | G8: Google Workspace SSO — 6 authorized users
A9: 3 | B9: Access limited to legitimate educational interest | C9: §99.31 | D9: ✅ PASS | E9: 2026-02-10 | F9: C. James | G9: Role-based access control matrix active
A10: 4 | B10: Parents notified of FERPA rights annually | C10: §99.7 | D10: ✅ PASS | E10: 2025-09-01 | F10: C. James | G10: Annual notification sent with enrollment packet
A11: 5 | B11: Student data not shared with unauthorized parties | C11: §99.33 | D11: ✅ PASS | E11: 2026-02-10 | F11: C. James | G11: No third-party data sharing agreements active
A12: 6 | B12: Audit trail for all data access | C12: §99.32 | D12: ✅ PASS | E12: 2026-02-10 | F12: C. James | G12: Audit Log sheet + Google Drive activity log
A13: 7 | B13: Data breach response plan documented | C13: §99.33 | D13: ✅ PASS | E13: 2025-08-15 | F13: A. Buma | G13: Response plan on file with PGCPS compliance
A14: 8 | B14: All staff completed FERPA training | C14: §99.31 | D14: ✅ PASS | E14: 2025-08-20 | F14: C. James | G14: 6/6 authorized users trained — certificates on file
A15: 9 | B15: Student directory info opt-out available | C15: §99.37 | D15: ✅ PASS | E15: 2025-09-01 | F15: C. James | G15: Opt-out form included in enrollment packet
A16: 10 | B16: No student PII in emails (unencrypted) | C16: §99.31 | D16: ✅ PASS | E16: 2026-02-10 | F16: C. James | G16: Thursday newsletters use student first name only
A17: 11 | B17: Physical printouts secured after use | C17: §99.31 | D17: ✅ PASS | E17: 2026-02-10 | F17: C. James | G17: Shred bin in coordinator office
A18: 12 | B18: No student data on personal devices | C18: §99.31 | D18: ✅ PASS | E18: 2026-02-10 | F18: C. James | G18: Policy signed by all 6 authorized users
... A26: 20 | B26: Annual compliance review completed | C26: §99.31 | D26: ✅ PASS | E26: 2026-02-10 | F26: C. James | G26: This audit — 18 PASS, 2 REVIEW

Sheet Blueprint Metrics
A1: ⬅ NAVIGATE:
A2: ElevateED — MARYLAND BLUEPRINT METRICS
A3: Talent Ready IT Program | Largo High School | Prince George's Community College
A4: Maryland Blueprint for Maryland's Future | CONFIDENTIAL — FERPA PROTECTED | Generated: February 13, 2026 03:45 PM
A5: Pillar 3 CCR | Pillar 4 MTSS | Workforce Dev | Ed. Code Ann. §7-205.1
A6: PILLAR 3: COLLEGE & CAREER READINESS
A7: ID | B7: Indicator | C7: § | D7: Target | E7: Current | F7: Status | G7: Gap | H7: Action
A8: CCR-01 | B8: Dual enrollment pass rate ≥70% | C8: 7-205.1 | D8: 90% | E8: 88.1% | F8: ✅ On Track | G8: -1.9% | H8: Monitor 7 students near threshold
A9: CCR-02 | B9: Program completion rate | C9: 7-205.1 | D9: 85% | E9: 93.7% | F9: ✅ Exceeds | G9: +8.7% | H9: Maintain — outperforming target
A10: CCR-03 | B10: IT certification readiness | C10: 7-205.1 | D10: 75% | E10: 72.0% | F10: ⚠ Approaching | G10: -3.0% | H10: Network+ prep for Cohort 2027
A11: CCR-04 | B11: College credit accumulation | C11: 7-205.1 | D11: 12 cr/yr | E11: 14.2 cr | F11: ✅ Exceeds | G11: +2.2 cr | H11: On pace for 4-year plan
A12: CCR-05 | B12: Industry pathway alignment | C12: 7-205.1 | D12: 100% | E12: 100% | F12: ✅ Met | G12: 0% | H12: All courses map to IT pathways
A14: PILLAR 4: MORE RESOURCES FOR STUDENTS WHO NEED THEM (MTSS)
A15: ID | B15: Indicator | C15: § | D15: Target | E15: Current | F15: Status | G15: Gap | H15: Action
A16: MTSS-01 | B16: Tier 1 students maintained ≥75% | C16: 7-306 | D16: 80% | E16: 55.9% | F16: ⚠ Below | G16: -24.1% | H16: Expand Tier 1 enrichment activities
A17: MTSS-02 | B17: Tier 2/3 students with intervention plans | C17: 7-306 | D17: 100% | E17: 100% | F17: ✅ Met | G17: 0% | H17: All at-risk students have active plans
A18: MTSS-03 | B18: Intervention effectiveness (pre vs post) | C18: 7-306 | D18: 70% improve | E18: 80% | F18: ✅ Exceeds | G18: +10% | H18: 8/10 plans showing improvement
A19: MTSS-04 | B19: Parent notification within 48hrs of flag | C19: 7-306 | D19: 100% | E19: 95% | F19: ⚠ Approaching | G19: -5% | H19: 2 late notifications — process fix applied
A20: MTSS-05 | B20: SIT meeting frequency for Tier 3 | C20: 7-306 | D20: Bi-weekly | E20: Bi-weekly | F20: ✅ Met | G20: — | H20: 4 Tier 3 students reviewed every 2 weeks

Sheet Parent Engagement
A1: ⬅ NAVIGATE:
A2: ElevateED — PARENT ENGAGEMENT ANALYTICS
A3: Talent Ready IT Program | Largo High School | Prince George's Community College
A4: Maryland Blueprint for Maryland's Future | CONFIDENTIAL — FERPA PROTECTED | Generated: February 13, 2026 03:45 PM
A5: 59 Families | Engagement Scoring | Communication Log | Thursday Newsletters
A6: Student ID | B6: Student | C6: Cohort | D6: Parent/Guardian | E6: Email Status | F6: Emails Sent | G6: Opened | H6: Responded | I6: Conferences | J6: Score | K6: Level | L6: Last Contact
A7: TR-0001 | B7: CRICHTON III, LEONARD | C7: 2026 | D7: Parent of LEONARD | E7: Active | F7: 8 | G7: 2/8 | H7: 0/8 | I7: 2/2 | J7: 40 | K7: MODERATE | L7: 2026-02-10
A8: TR-0002 | B8: CROWELL, KINGSTON | C8: 2026 | D8: Parent of KINGSTON | E8: Active | F8: 7 | G8: 3/7 | H8: 1/7 | I8: 0/2 | J8: 21.4 | K8: LOW | L8: 2026-02-06
A9: TR-0003 | B9: DAVIS, GABRIEL | C9: 2026 | D9: Parent of GABRIEL | E9: Active | F9: 8 | G9: 2/8 | H9: 2/8 | I9: 2/2 | J9: 47.5 | K9: MODERATE | L9: 2026-01-30
A10: TR-0004 | B10: FERSNER, LAILAH | C10: 2026 | D10: Parent of LAILAH | E10: Active | F10: 8 | G10: 2/8 | H10: 2/8 | I10: 1/2 | J10: 32.5 | K10: LOW | L10: 2026-02-12
A11: TR-0005 | B11: FORD, JAMES | C11: 2026 | D11: Parent of JAMES | E11: Active | F11: 6 | G11: 2/6 | H11: 0/6 | I11: 0/2 | J11: 13.3 | K11: LOW | L11: 2026-01-28
A12: TR-0006 | B12: FORREST, TYLEYL | C12: 2026 | D12: Parent of TYLEYL | E12: Active | F12: 6 | G12: 6/6 | H12: 0/6 | I12: 2/2 | J12: 70 | K12: HIGH | L12: 2026-02-10
A13: TR-0007 | B13: JALLOH, JENABU | C13: 2026 | D13: Parent of JENABU | E13: Active | F13: 6 | G13: 6/6 | H13: 3/6 | I13: 0/2 | J13: 55 | K13: MODERATE | L13: 2026-02-06
A14: TR-0008 | B14: JOHNSON-BONILLA, CHRISTOPHER | C14: 2026 | D14: Parent of CHRISTOPHER | E14: Active | F14: 7 | G14: 6/7 | H14: 2/7 | I14: 0/2 | J14: 42.9 | K14: MODERATE | L14: 2026-01-30
A15: TR-0009 | B15: OLUBIYI, OLUWANIFEMI | C15: 2026 | D15: Parent of OLUWANIFEMI | E15: Active | F15: 6 | G15: 5/6 | H15: 2/6 | I15: 1/2 | J15: 58.3 | K15: MODERATE | L15: 2026-02-12
A16: TR-0010 | B16: SANNI, MOFEOLUWA | C16: 2026 | D16: Parent of MOFEOLUWA | E16: Active | F16: 6 | G16: 3/6 | H16: 2/6 | I16: 0/2 | J16: 30 | K16: LOW | L16: 2026-01-28
A17: TR-0011 | B17: SCARLETT, OLIVIA | C17: 2026 | D17: Parent of OLIVIA | E17: Active | F17: 6 | G17: 5/6 | H17: 0/6 | I17: 1/2 | J17: 48.3 | K17: MODERATE | L17: 2026-02-10
A18: TR-0012 | B18: WALLACE, JUSTIN | C18: 2026 | D18: Parent of JUSTIN | E18: Active | F18: 7 | G18: 6/7 | H18: 2/7 | I18: 0/2 | J18: 42.9 | K18: MODERATE | L18: 2026-02-06
... A65: TR-0057 | B65: VIDAL, JOSHUA | C65: 2029 | D65: Parent of JOSHUA | E65: Active | F65: 7 | G65: 5/7 | H65: 1/7 | I65: 0/2 | J65: 32.9 | K65: LOW | L65: 2026-02-12

Sheet Parent Contacts
A1: ⬅ NAVIGATE:
A2: ElevateED — PARENT CONTACTS — AUTOMATED EMAIL SYSTEM
A3: Talent Ready IT Program | Largo High School | Prince George's Community College
A4: Maryland Blueprint | CONFIDENTIAL — FERPA PROTECTED | February 13, 2026 04:50 PM
A5: 59 Families | Thursday 2:00 PM Newsletter | FERPA §99.10 — Each parent receives ONLY their student's data
A6: Student ID | B6: Student Name | C6: Cohort | D6: Grade | E6: Parent/Guardian Name | F6: Parent Email | G6: Phone | H6: Preferred Language | I6: Email Active | J6: Opt-Out | K6: Last Email Sent | L6: Notes
A7: TR-0001 | B7: CRICHTON III, LEONARD | C7: 2026 | D7: 12 | E7: Leonard Crichton II (Guardian) | F7: ⚠️ Need real email — crichton-iii@parent.pgcps.org | G7: 240-535-9274 | H7: English | I7: Yes | J7: No | K7: 2026-02-06 | L7: Alt phone: 202-706-2730
A8: TR-0002 | B8: CROWELL, KINGSTON | C8: 2026 | D8: 12 | E8: Parent of KINGSTON | F8: ⚠️ Need real email — crowell@parent.pgcps.org | G8: (301) 555-1001 | H8: English | I8: Yes | J8: No | K8: 2026-02-06
A9: TR-0003 | B9: DAVIS, GABRIEL | C9: 2026 | D9: 12 | E9: India Conwell (Guardian) | F9: ⚠️ Need real email — davis@parent.pgcps.org | G9: 202-867-3140 | H9: English | I9: Yes | J9: No | K9: 2026-02-06
A10: TR-0004 | B10: FERSNER, LAILAH | C10: 2026 | D10: 12 | E10: Tanika Thompson (Guardian) | F10: ⚠️ Need real email — fersner@parent.pgcps.org | G10: 202-297-5307 | H10: English | I10: Yes | J10: No | K10: 2026-02-06 | L10: Alt phone: 301-938-7043
A11: TR-0005 | B11: FORD, JAMES | C11: 2026 | D11: 12 | E11: Parent of JAMES | F11: ⚠️ Need real email — ford@parent.pgcps.org | G11: (301) 555-1004 | H11: English | I11: Yes | J11: No | K11: 2026-02-06
A12: TR-0006 | B12: FORREST, TYLEYL | C12: 2026 | D12: 12 | E12: Parent/Guardian of TYLEYL | F12: ⚠️ Need real email — forrest@parent.pgcps.org | G12: 240-532-9103 | H12: English | I12: Yes | J12: No | K12: 2026-02-06
A13: TR-0007 | B13: JALLOH, JENABU | C13: 2026 | D13: 12 | E13: Binta Jalloh (Guardian) | F13: ⚠️ Need real email — jalloh@parent.pgcps.org | G13: 240-381-3415 | H13: English | I13: Yes | J13: No | K13: 2026-02-06
A14: TR-0008 | B14: JOHNSON-BONILLA, CHRISTOPHER | C14: 2026 | D14: 12 | E14: Guardian of CHRISTOPHER | F14: ⚠️ Need real email — johnson-bonilla@parent.pgcps.org | G14: 301-399-3848 | H14: English | I14: Yes | J14: No | K14: 2026-02-06 | L14: Alt phone: 202-321-5144
A15: TR-0009 | B15: OLUBIYI, OLUWANIFEMI | C15: 2026 | D15: 12 | E15: Titilope Olubiyi (Guardian) | F15: ⚠️ Need real email — olubiyi@parent.pgcps.org | G15: 240-505-1297 | H15: English | I15: Yes | J15: No | K15: 2026-02-06
A16: TR-0010 | B16: SANNI, MOFEOLUWA | C16: 2026 | D16: 12 | E16: Adewale Adetimehim (Guardian) | F16: ⚠️ Need real email — sanni@parent.pgcps.org | G16: 240-758-4001 | H16: English | I16: Yes | J16: No | K16: 2026-02-06
A17: TR-0011 | B17: SCARLETT, OLIVIA | C17: 2026 | D17: 12 | E17: Guardian of OLIVIA | F17: ⚠️ Need real email — scarlett@parent.pgcps.org | G17: 301-204-9934 | H17: English | I17: Yes | J17: No | K17: 2026-02-06
A18: TR-0012 | B18: WALLACE, JUSTIN | C18: 2026 | D18: 12 | E18: Parent of JUSTIN | F18: ⚠️ Need real email — wallace@parent.pgcps.org | G18: (301) 555-1011 | H18: English | I18: Yes | J18: No | K18: 2026-02-06
A19: TR-0013 | B19: WILLIAMS, CHLOE | C19: 2026 | D19: 12 | E19: Guardian of CHLOE | F19: ⚠️ Need real email — williams@parent.pgcps.org | G19: 202-390-9118 | H19: English | I19: Yes | J19: No | K19: 2026-02-06
A20: TR-0014 | B20: WILBUR, GABRIELLE | C20: 2026 | D20: 12 | E20: Parent of GABRIELLE | F20: ⚠️ Need real email — wilbur@parent.pgcps.org | G20: (301) 555-1013 | H20: English | I20: Yes | J20: No | K20: 2026-02-06
A21: TR-0015 | B21: WINTERS, AARON | C21: 2026 | D21: 12 | E21: Parent of AARON | F21: ⚠️ Need real email — winters@parent.pgcps.org | G21: (301) 555-1014 | H21: English | I21: Yes | J21: No | K21: 2026-02-06
A22: TR-0016 | B22: ZUBAIRU, LATEEFAH | C22: 2026 | D22: 12 | E22: Guardian of LATEEFAH | F22: ⚠️ Need real email — zubairu@parent.pgcps.org | G22: 301-996-4885 | H22: English | I22: Yes | J22: No | K22: 2026-02-06 | L22: Alt phone: 301-996-5517
A23: TR-0058 | B23: SCOTT, SANAA | C23: 2026 | D23: 12 | E23: Parent of SANAA | F23: ⚠️ Need real email — scott@parent.pgcps.org | G23: (301) 555-1016 | H23: English | I23: Yes | J23: No | K23: 2026-02-06
A24: TR-0017 | B24: BYFIELD, KIMANI | C24: 2027 | D24: 11 | E24: Guardian of KIMANI | F24: ⚠️ Need real email — byfield@parent.pgcps.org | G24: 860-718-5388 | H24: English | I24: Yes | J24: No | K24: 2026-02-06
A25: TR-0018 | B25: HODGE, AMANI | C25: 2027 | D25: 11 | E25: Parent of AMANI | F25: ⚠️ Need real email — hodge@parent.pgcps.org | G25: (301) 555-1018 | H25: English | I25: Yes | J25: No | K25: 2026-02-06
A26: TR-0019 | B26: LAMBRIGHT, KADYN | C26: 2027 | D26: 11 | E26: Guardian of KADYN | F26: ⚠️ Need real email — lambright@parent.pgcps.org | G26: 301-357-1681 | H26: English | I26: Yes | J26: No | K26: 2026-02-06 | L26: Alt phone: 240-892-4496
A27: TR-0020 | B27: NISBETH, GRACE | C27: 2027 | D27: 11 | E27: Parent of GRACE | F27: ⚠️ Need real email — nisbeth@parent.pgcps.org | G27: (301) 555-1020 | H27: English | I27: Yes | J27: No | K27: 2026-02-06
A28: TR-0021 | B28: PAYTON, JADEN | C28: 2027 | D28: 11 | E28: Parent of JADEN | F28: ⚠️ Need real email — payton@parent.pgcps.org | G28: (301) 555-1021 | H28: English | I28: Yes | J28: No | K28: 2026-02-06
A29: TR-0022 | B29: WARD, CANAAN | C29: 2027 | D29: 11 | E29: Charles Ball (Guardian) | F29: ⚠️ Need real email — ward@parent.pgcps.org | G29: 301-249-1183 | H29: English | I29: Yes | J29: No | K29: 2026-02-06
A30: TR-0023 | B30: AHETO, EDWIN | C30: 2028 | D30: 10 | E30: Guardian of EDWIN | F30: ⚠️ Need real email — aheto@parent.pgcps.org | G30: 240-723-0880 | H30: English | I30: Yes | J30: No | K30: 2026-02-06 | L30: Alt phone: 301-322-2834
A31: TR-0024 | B31: ALI, CALI | C31: 2028 | D31: 10 | E31: Parent of CALI | F31: ⚠️ Need real email — ali@parent.pgcps.org | G31: (301) 555-1024 | H31: English | I31: Yes | J31: No | K31: 2026-02-06
A32: TR-0025 | B32: ANTHONY, JELANI | C32: 2028 | D32: 10 | E32: Shirley Morgan (Guardian) | F32: ⚠️ Need real email — anthony@parent.pgcps.org | G32: 202-765-9639 | H32: English | I32: Yes | J32: No | K32: 2026-02-06 | L32: Alt phone: 240-755-6271
A33: TR-0026 | B33: EGUNJOBI, OREOLUWA | C33: 2028 | D33: 10 | E33: Parent of OREOLUWA | F33: ⚠️ Need real email — egunjobi@parent.pgcps.org | G33: (301) 555-1026 | H33: English | I33: Yes | J33: No | K33: 2026-02-06
A34: TR-0027 | B34: ERHABOR, ELAION | C34: 2028 | D34: 10 | E34: Parent of ELAION | F34: ⚠️ Need real email — erhabor@parent.pgcps.org | G34: (301) 555-1027 | H34: English | I34: Yes | J34: No | K34: 2026-02-06
A35: TR-0028 | B35: FERSNER, KENNEDI | C35: 2028 | D35: 10 | E35: Larry Fersner (Guardian) | F35: ⚠️ Need real email — fersner@parent.pgcps.org | G35: 202-251-5485 | H35: English | I35: Yes | J35: No | K35: 2026-02-06 | L35: Alt phone: 202-297-5307
A36: TR-0059 | B36: FORD, CHASE | C36: 2028 | D36: 10 | E36: Parent of CHASE | F36: ⚠️ Need real email — ford@parent.pgcps.org | G36: (301) 555-1029 | H36: English | I36: Yes | J36: No | K36: 2026-02-06
A37: TR-0029 | B37: FOSTER, BRYANT | C37: 2028 | D37: 10 | E37: Guardian of BRYANT | F37: ⚠️ Need real email — foster@parent.pgcps.org | G37: 757-435-4994 | H37: English | I37: Yes | J37: No | K37: 2026-02-06
A38: TR-0030 | B38: GOMEZ, CHRISTIAN | C38: 2028 | D38: 10 | E38: Parent of CHRISTIAN | F38: ⚠️ Need real email — gomez@parent.pgcps.org | G38: (301) 555-1031 | H38: English | I38: Yes | J38: No | K38: 2026-02-06
A39: TR-0031 | B39: JOHNSON, LIAM | C39: 2028 | D39: 10 | E39: Guardian of LIAM | F39: ⚠️ Need real email — johnson@parent.pgcps.org | G39: 301-943-1201 | H39: English | I39: Yes | J39: No | K39: 2026-02-06 | L39: Alt phone: 202-570-2909
A40: TR-0032 | B40: MONROE-HOOD, JAHDAI | C40: 2028 | D40: 10 | E40: Guardian of JAHDAI | F40: ⚠️ Need real email — monroe-hood@parent.pgcps.org | G40: 202-910-3207 | H40: English | I40: Yes | J40: No | K40: 2026-02-06 | L40: Alt phone: 240-501-5083
A41: TR-0033 | B41: MORGAN, ESSOON | C41: 2028 | D41: 10 | E41: Parent of ESSOON | F41: ⚠️ Need real email — morgan@parent.pgcps.org | G41: (301) 555-1034 | H41: English | I41: Yes | J41: No | K41: 2026-02-06
A42: TR-0034 | B42: MOSES, EMERIC | C42: 2028 | D42: 10 | E42: Guardian of EMERIC | F42: ⚠️ Need real email — moses@parent.pgcps.org | G42: 301-399-3848 | H42: English | I42: Yes | J42: No | K42: 2026-02-06
A43: TR-0035 | B43: MUNGWA, RODRIKARL | C43: 2028 | D43: 10 | E43: Guardian of RODRIKARL | F43: ⚠️ Need real email — mungwa@parent.pgcps.org | G43: 240-547-7908 | H43: English | I43: Yes | J43: No | K43: 2026-02-06
A44: TR-0036 | B44: NAVARRO-MARTINEZ, MARTHA | C44: 2028 | D44: 10 | E44: Guardian of MARTHA | F44: ⚠️ Need real email — navarro-martinez@parent.pgcps.org | G44: 719-329-4524 | H44: Spanish | I44: Yes | J44: No | K44: 2026-02-06
A45: TR-0037 | B45: SOLOMON, GISELLE | C45: 2028 | D45: 10 | E45: Chavall Solomon (Guardian) | F45: ⚠️ Need real email — solomon@parent.pgcps.org | G45: 301-922-9465 | H45: English | I45: Yes | J45: No | K45: 2026-02-06 | L45: Alt phone: 240-424-1210
A46: TR-0038 | B46: WALTERS, JAEV'HAN | C46: 2028 | D46: 10 | E46: Guardian of JAEV'HAN | F46: ⚠️ Need real email — walters@parent.pgcps.org | G46: 910-640-8099 | H46: English | I46: Yes | J46: No | K46: 2026-02-06
A47: TR-0039 | B47: WASHINGTON, JOSHUA | C47: 2028 | D47: 10 | E47: Seanice Lyons (Guardian) | F47: ⚠️ Need real email — washington@parent.pgcps.org | G47: 240-472-5780 | H47: English | I47: Yes | J47: No | K47: 2026-02-06 | L47: Alt phone: 240-460-8183
A48: TR-0040 | B48: WHITAKER, XION | C48: 2028 | D48: 10 | E48: Michael Dozier (Guardian) | F48: ⚠️ Need real email — whitaker@parent.pgcps.org | G48: 202-340-5385 | H48: English | I48: Yes | J48: No | K48: 2026-02-06 | L48: Alt phone: 301-806-3658
A49: TR-0041 | B49: WHITTED, BRAYLEN | C49: 2028 | D49: 10 | E49: Alexeus Whitted (Guardian) | F49: ⚠️ Need real email — whitted@parent.pgcps.org | G49: 301-343-9119 | H49: English | I49: Yes | J49: No | K49: 2026-02-06
A50: TR-0042 | B50: AKINSANYA, TIARAOLUWA | C50: 2029 | D50: 9 | E50: Guardian of TIARAOLUWA | F50: ⚠️ Need real email — akinsanya@parent.pgcps.org | G50: 240-936-3701 | H50: English | I50: Yes | J50: No | K50: 2026-02-06 | L50: Alt phone: 301-768-0555
A51: TR-0043 | B51: ATKINS, PEYTON | C51: 2029 | D51: 9 | E51: Parent of PEYTON | F51: ⚠️ Need real email — atkins@parent.pgcps.org | G51: (301) 555-1044 | H51: English | I51: Yes | J51: No | K51: 2026-02-06
A52: TR-0044 | B52: BELCHER, MALACHI | C52: 2029 | D52: 9 | E52: Guardian of MALACHI | F52: ⚠️ Need real email — belcher@parent.pgcps.org | G52: 301-332-3497 | H52: English | I52: Yes | J52: No | K52: 2026-02-06
A53: TR-0045 | B53: DUMAS, ADDISON | C53: 2029 | D53: 9 | E53: Cynthia Dumas (Guardian) | F53: ⚠️ Need real email — dumas@parent.pgcps.org | G53: 202-431-8117 | H53: English | I53: Yes | J53: No | K53: 2026-02-06
A54: TR-0046 | B54: HARRISON, MACKENZIE | C54: 2029 | D54: 9 | E54: Janet Wilson (Guardian) | F54: ⚠️ Need real email — harrison@parent.pgcps.org | G54: 202-793-1754 | H54: English | I54: Yes | J54: No | K54: 2026-02-06 | L54: Alt phone: 240-838-1514
A55: TR-0047 | B55: HARVEY, MEZRAH | C55: 2029 | D55: 9 | E55: Parent of MEZRAH | F55: ⚠️ Need real email — harvey@parent.pgcps.org | G55: (301) 555-1048 | H55: English | I55: Yes | J55: No | K55: 2026-02-06
A56: TR-0048 | B56: HERBERT, HYON | C56: 2029 | D56: 9 | E56: Bonni Wilson (Guardian) | F56: ⚠️ Need real email — herbert@parent.pgcps.org | G56: 240-789-1100 | H56: English | I56: Yes | J56: No | K56: 2026-02-06
A57: TR-0049 | B57: JOSEPH-ALEXANDER, SHILOH | C57: 2029 | D57: 9 | E57: Stacie Moore (Guardian) | F57: ⚠️ Need real email — joseph-alexander@parent.pgcps.org | G57: 202-412-1030 | H57: English | I57: Yes | J57: No | K57: 2026-02-06 | L57: Alt phone: 240-535-3851
A58: TR-0050 | B58: LASHLEY, AVA | C58: 2029 | D58: 9 | E58: Guardian of AVA | F58: ⚠️ Need real email — lashley@parent.pgcps.org | G58: 757-374-7278 | H58: English | I58: Yes | J58: No | K58: 2026-02-06 | L58: Alt phone: 301-213-0402
A59: TR-0051 | B59: LOWERY, CADEN | C59: 2029 | D59: 9 | E59: Parent of CADEN | F59: ⚠️ Need real email — lowery@parent.pgcps.org | G59: (301) 555-1052 | H59: English | I59: Yes | J59: No | K59: 2026-02-06
A60: TR-0052 | B60: ONUOSA, NICHOLAS | C60: 2029 | D60: 9 | E60: Naomi Onuosa (Guardian) | F60: ⚠️ Need real email — onuosa@parent.pgcps.org | G60: 240-355-9926 | H60: English | I60: Yes | J60: No | K60: 2026-02-06 | L60: Alt phone: 202-679-7917
A61: TR-0053 | B61: ROBINSON, MATTHEW | C61: 2029 | D61: 9 | E61: Parent of MATTHEW | F61: ⚠️ Need real email — robinson@parent.pgcps.org | G61: (301) 555-1054 | H61: English | I61: Yes | J61: No | K61: 2026-02-06
A62: TR-0054 | B62: SAUNDERS, MADELINE | C62: 2029 | D62: 9 | E62: Guardian of MADELINE | F62: ⚠️ Need real email — saunders@parent.pgcps.org | G62: 301-242-1058 | H62: English | I62: Yes | J62: No | K62: 2026-02-06
A63: TR-0055 | B63: SHEIKH, MUHAMMAD D. | C63: 2029 | D63: 9 | E63: Shawal Sheikh (Guardian) | F63: ⚠️ Need real email — sheikh@parent.pgcps.org | G63: 240-416-7216 | H63: English | I63: Yes | J63: No | K63: 2026-02-06
A64: TR-0056 | B64: SHINABA, MUHAMMAD M. | C64: 2029 | D64: 9 | E64: Guardian of MUHAMMAD M. | F64: ⚠️ Need real email — shinaba@parent.pgcps.org | G64: 240-547-8603 | H64: English | I64: Yes | J64: No | K64: 2026-02-06 | L64: Alt phone: 240-838-0614
A65: TR-0057 | B65: VIDAL, JOSHUA | C65: 2029 | D65: 9 | E65: Guardian of JOSHUA | F65: ⚠️ Need real email — vidal@parent.pgcps.org | G65: 240-480-2544 | H65: English | I65: Yes | J65: No | K65: 2026-02-06

Sheet Email Log
A1: ⬅ NAVIGATE:
A2: ElevateED — EMAIL LOG — FERPA §99.32 DISCLOSURE TRACKING
A3: Talent Ready IT Program | Largo High School | Prince George's Community College
A4: Maryland Blueprint | CONFIDENTIAL — FERPA PROTECTED | February 13, 2026 04:50 PM
A5: Every parent email logged | Thursday 2:00 PM batches | Delivery status tracking | Retention: 5 years
A6: Timestamp | B6: Batch ID | C6: Student ID | D6: Student Name | E6: Parent Email | F6: Subject | G6: Status | H6: Opened | I6: Error | J6: Sent By
A7: 2026-02-06 14:00 | B7: BATCH-2026-0206 | C7: TR-0001 | D7: CRICHTON III, LEONARD | E7: parent.crichtoniii@email.com | F7: Talent Ready Program: LEONARD's Weekly Grade Report | G7: Delivered | H7: No | J7: System (Auto)
A8: 2026-02-06 14:00 | B8: BATCH-2026-0206 | C8: TR-0002 | D8: CROWELL, KINGSTON | E8: parent.crowell@email.com | F8: Talent Ready Program: KINGSTON's Weekly Grade Report | G8: Delivered | H8: No | J8: System (Auto)
A9: 2026-02-06 14:00 | B9: BATCH-2026-0206 | C9: TR-0003 | D9: DAVIS, GABRIEL | E9: parent.davis@email.com | F9: Talent Ready Program: GABRIEL's Weekly Grade Report | G9: Delivered | H9: Yes | J9: System (Auto)
A10: 2026-02-06 14:00 | B10: BATCH-2026-0206 | C10: TR-0004 | D10: FERSNER, LAILAH | E10: parent.fersner@email.com | F10: Talent Ready Program: LAILAH's Weekly Grade Report | G10: Delivered | H10: No | J10: System (Auto)
A11: 2026-02-06 14:00 | B11: BATCH-2026-0206 | C11: TR-0005 | D11: FORD, JAMES | E11: parent.ford@email.com | F11: Talent Ready Program: JAMES's Weekly Grade Report | G11: Delivered | H11: No | J11: System (Auto)
A12: 2026-02-06 14:00 | B12: BATCH-2026-0206 | C12: TR-0006 | D12: FORREST, TYLEYL | E12: parent.forrest@email.com | F12: Talent Ready Program: TYLEYL's Weekly Grade Report | G12: Delivered | H12: Yes | J12: System (Auto)
A13: 2026-02-06 14:00 | B13: BATCH-2026-0206 | C13: TR-0007 | D13: JALLOH, JENABU | E13: parent.jalloh@email.com | F13: Talent Ready Program: JENABU's Weekly Grade Report | G13: Failed | H13: No | I13: Invalid email address | J13: System (Auto)
A14: 2026-02-06 14:00 | B14: BATCH-2026-0206 | C14: TR-0008 | D14: JOHNSON-BONILLA, CHRISTOPHER | E14: parent.johnsonbonilla@email.com | F14: Talent Ready Program: CHRISTOPHER's Weekly Grade Report | G14: Delivered | H14: Yes | J14: System (Auto)
A15: 2026-02-06 14:00 | B15: BATCH-2026-0206 | C15: TR-0009 | D15: OLUBIYI, OLUWANIFEMI | E15: parent.olubiyi@email.com | F15: Talent Ready Program: OLUWANIFEMI's Weekly Grade Report | G15: Delivered | H15: No | J15: System (Auto)
A16: 2026-02-06 14:00 | B16: BATCH-2026-0206 | C16: TR-0010 | D16: SANNI, MOFEOLUWA | E16: parent.sanni@email.com | F16: Talent Ready Program: MOFEOLUWA's Weekly Grade Report | G16: Delivered | H16: Yes | J16: System (Auto)
A17: 2026-02-06 14:00 | B17: BATCH-2026-0206 | C17: TR-0011 | D17: SCARLETT, OLIVIA | E17: parent.scarlett@email.com | F17: Talent Ready Program: OLIVIA's Weekly Grade Report | G17: Failed | H17: No | I17: Invalid email address | J17: System (Auto)
A18: 2026-02-06 14:00 | B18: BATCH-2026-0206 | C18: TR-0012 | D18: WALLACE, JUSTIN | E18: parent.wallace@email.com | F18: Talent Ready Program: JUSTIN's Weekly Grade Report | G18: Delivered | H18: Yes | J18: System (Auto)
A19: 2026-02-06 14:00 | B19: BATCH-2026-0206 | C19: TR-0013 | D19: WILLIAMS, CHLOE | E19: parent.williams@email.com | F19: Talent Ready Program: CHLOE's Weekly Grade Report | G19: Delivered | H19: No | J19: System (Auto)
A20: 2026-02-06 14:00 | B20: BATCH-2026-0206 | C20: TR-0014 | D20: WILBUR, GABRIELLE | E20: parent.wilbur@email.com | F20: Talent Ready Program: GABRIELLE's Weekly Grade Report | G20: Delivered | H20: No | J20: System (Auto)
A21: 2026-02-06 14:00 | B21: BATCH-2026-0206 | C21: TR-0015 | D21: WINTERS, AARON | E21: parent.winters@email.com | F21: Talent Ready Program: AARON's Weekly Grade Report | G21: Delivered | H21: No | J21: System (Auto)
A22: 2026-02-06 14:00 | B22: BATCH-2026-0206 | C22: TR-0016 | D22: ZUBAIRU, LATEEFAH | E22: parent.zubairu@email.com | F22: Talent Ready Program: LATEEFAH's Weekly Grade Report | G22: Delivered | H22: Yes | J22: System (Auto)
A23: 2026-02-06 14:00 | B23: BATCH-2026-0206 | C23: TR-0058 | D23: SCOTT, SANAA | E23: parent.scott@email.com | F23: Talent Ready Program: SANAA's Weekly Grade Report | G23: Delivered | H23: Yes | J23: System (Auto)
A24: 2026-02-06 14:00 | B24: BATCH-2026-0206 | C24: TR-0017 | D24: BYFIELD, KIMANI | E24: parent.byfield@email.com | F24: Talent Ready Program: KIMANI's Weekly Grade Report | G24: Delivered | H24: Yes | J24: System (Auto)
A25: 2026-02-06 14:00 | B25: BATCH-2026-0206 | C25: TR-0018 | D25: HODGE, AMANI | E25: parent.hodge@email.com | F25: Talent Ready Program: AMANI's Weekly Grade Report | G25: Delivered | H25: Yes | J25: System (Auto)
A26: 2026-02-06 14:00 | B26: BATCH-2026-0206 | C26: TR-0019 | D26: LAMBRIGHT, KADYN | E26: parent.lambright@email.com | F26: Talent Ready Program: KADYN's Weekly Grade Report | G26: Delivered | H26: Yes | J26: System (Auto)
A27: 2026-02-06 14:00 | B27: BATCH-2026-0206 | C27: TR-0020 | D27: NISBETH, GRACE | E27: parent.nisbeth@email.com | F27: Talent Ready Program: GRACE's Weekly Grade Report | G27: Delivered | H27: Yes | J27: System (Auto)
A28: 2026-02-06 14:00 | B28: BATCH-2026-0206 | C28: TR-0021 | D28: PAYTON, JADEN | E28: parent.payton@email.com | F28: Talent Ready Program: JADEN's Weekly Grade Report | G28: Delivered | H28: No | J28: System (Auto)
A29: 2026-02-06 14:00 | B29: BATCH-2026-0206 | C29: TR-0022 | D29: WARD, CANAAN | E29: parent.ward@email.com | F29: Talent Ready Program: CANAAN's Weekly Grade Report | G29: Delivered | H29: No | J29: System (Auto)
... A57: 2026-02-06 14:00 | B57: BATCH-2026-0206 | C57: TR-0049 | D57: JOSEPH-ALEXANDER, SHILOH | E57: parent.josephalexander@email.com | F57: Talent Ready Program: SHILOH's Weekly Grade Report | G57: Delivered | H57: Yes | J57: System (Auto)
A58: 2026-02-06 14:00 | B58: BATCH-2026-0206 | C58: TR-0050 | D58: LASHLEY, AVA | E58: parent.lashley@email.com | F58: Talent Ready Program: AVA's Weekly Grade Report | G58: Failed | H58: No | I58: Invalid email address | J58: System (Auto)
A59: 2026-02-06 14:00 | B59: BATCH-2026-0206 | C59: TR-0051 | D59: LOWERY, CADEN | E59: parent.lowery@email.com | F59: Talent Ready Program: CADEN's Weekly Grade Report | G59: Delivered | H59: Yes | J59: System (Auto)
A60: 2026-02-06 14:00 | B60: BATCH-2026-0206 | C60: TR-0052 | D60: ONUOSA, NICHOLAS | E60: parent.onuosa@email.com | F60: Talent Ready Program: NICHOLAS's Weekly Grade Report | G60: Delivered | H60: No | J60: System (Auto)
A61: 2026-02-06 14:00 | B61: BATCH-2026-0206 | C61: TR-0053 | D61: ROBINSON, MATTHEW | E61: parent.robinson@email.com | F61: Talent Ready Program: MATTHEW's Weekly Grade Report | G61: Delivered | H61: No | J61: System (Auto)
A62: 2026-02-06 14:00 | B62: BATCH-2026-0206 | C62: TR-0054 | D62: SAUNDERS, MADELINE | E62: parent.saunders@email.com | F62: Talent Ready Program: MADELINE's Weekly Grade Report | G62: Delivered | H62: Yes | J62: System (Auto)
A63: 2026-02-06 14:00 | B63: BATCH-2026-0206 | C63: TR-0055 | D63: SHEIKH, MUHAMMAD D. | E63: parent.sheikh@email.com | F63: Talent Ready Program: MUHAMMAD D.'s Weekly Grade Report | G63: Delivered | H63: Yes | J63: System (Auto)
A64: 2026-02-06 14:00 | B64: BATCH-2026-0206 | C64: TR-0056 | D64: SHINABA, MUHAMMAD M. | E64: parent.shinaba@email.com | F64: Talent Ready Program: MUHAMMAD M.'s Weekly Grade Report | G64: Delivered | H64: Yes | J64: System (Auto)
A65: 2026-02-06 14:00 | B65: BATCH-2026-0206 | C65: TR-0057 | D65: VIDAL, JOSHUA | E65: parent.vidal@email.com | F65: Talent Ready Program: JOSHUA's Weekly Grade Report | G65: Delivered | H65: Yes | J65: System (Auto)
A66: 2026-01-30 14:00 | B66: BATCH-2026-0130 | C66: TR-0001 | D66: CRICHTON III, LEONARD | E66: parent.crichtoniii@email.com | F66: Talent Ready Program: LEONARD's Weekly Grade Report | G66: Delivered | H66: No | J66: System (Auto)
A67: 2026-01-30 14:00 | B67: BATCH-2026-0130 | C67: TR-0002 | D67: CROWELL, KINGSTON | E67: parent.crowell@email.com | F67: Talent Ready Program: KINGSTON's Weekly Grade Report | G67: Delivered | H67: Yes | J67: System (Auto)
A68: 2026-01-30 14:00 | B68: BATCH-2026-0130 | C68: TR-0003 | D68: DAVIS, GABRIEL | E68: parent.davis@email.com | F68: Talent Ready Program: GABRIEL's Weekly Grade Report | G68: Delivered | H68: Yes | J68: System (Auto)
A69: 2026-01-30 14:00 | B69: BATCH-2026-0130 | C69: TR-0004 | D69: FERSNER, LAILAH | E69: parent.fersner@email.com | F69: Talent Ready Program: LAILAH's Weekly Grade Report | G69: Delivered | H69: Yes | J69: System (Auto)
A70: 2026-01-30 14:00 | B70: BATCH-2026-0130 | C70: TR-0005 | D70: FORD, JAMES | E70: parent.ford@email.com | F70: Talent Ready Program: JAMES's Weekly Grade Report | G70: Delivered | H70: No | J70: System (Auto)
... A142: 2026-01-23 14:00 | B142: BATCH-2026-0123 | C142: TR-0017 | D142: BYFIELD, KIMANI | E142: parent.byfield@email.com | F142: Talent Ready Program: KIMANI's Weekly Grade Report | G142: Delivered | H142: Yes | J142: System (Auto)
A143: 2026-01-23 14:00 | B143: BATCH-2026-0123 | C143: TR-0018 | D143: HODGE, AMANI | E143: parent.hodge@email.com | F143: Talent Ready Program: AMANI's Weekly Grade Report | G143: Failed | H143: No | I143: Invalid email address | J143: System (Auto)
A144: 2026-01-23 14:00 | B144: BATCH-2026-0123 | C144: TR-0019 | D144: LAMBRIGHT, KADYN | E144: parent.lambright@email.com | F144: Talent Ready Program: KADYN's Weekly Grade Report | G144: Delivered | H144: No | J144: System (Auto)
A145: 2026-01-23 14:00 | B145: BATCH-2026-0123 | C145: TR-0020 | D145: NISBETH, GRACE | E145: parent.nisbeth@email.com | F145: Talent Ready Program: GRACE's Weekly Grade Report | G145: Delivered | H145: Yes | J145: System (Auto)
A146: 2026-01-23 14:00 | B146: BATCH-2026-0123 | C146: TR-0021 | D146: PAYTON, JADEN | E146: parent.payton@email.com | F146: Talent Ready Program: JADEN's Weekly Grade Report | G146: Delivered | H146: No | J146: System (Auto)
A147: 2026-01-23 14:00 | B147: BATCH-2026-0123 | C147: TR-0022 | D147: WARD, CANAAN | E147: parent.ward@email.com | F147: Talent Ready Program: CANAAN's Weekly Grade Report | G147: Delivered | H147: Yes | J147: System (Auto)
A148: 2026-01-23 14:00 | B148: BATCH-2026-0123 | C148: TR-0023 | D148: AHETO, EDWIN | E148: parent.aheto@email.com | F148: Talent Ready Program: EDWIN's Weekly Grade Report | G148: Delivered | H148: Yes | J148: System (Auto)
A149: 2026-01-23 14:00 | B149: BATCH-2026-0123 | C149: TR-0024 | D149: ALI, CALI | E149: parent.ali@email.com | F149: Talent Ready Program: CALI's Weekly Grade Report | G149: Delivered | H149: No | J149: System (Auto)
A150: 2026-01-23 14:00 | B150: BATCH-2026-0123 | C150: TR-0025 | D150: ANTHONY, JELANI | E150: parent.anthony@email.com | F150: Talent Ready Program: JELANI's Weekly Grade Report | G150: Delivered | H150: No | J150: System (Auto)
A151: 2026-01-23 14:00 | B151: BATCH-2026-0123 | C151: TR-0026 | D151: EGUNJOBI, OREOLUWA | E151: parent.egunjobi@email.com | F151: Talent Ready Program: OREOLUWA's Weekly Grade Report | G151: Delivered | H151: Yes | J151: System (Auto)
A152: 2026-01-23 14:00 | B152: BATCH-2026-0123 | C152: TR-0027 | D152: ERHABOR, ELAION | E152: parent.erhabor@email.com | F152: Talent Ready Program: ELAION's Weekly Grade Report | G152: Delivered | H152: No | J152: System (Auto)
A153: 2026-01-23 14:00 | B153: BATCH-2026-0123 | C153: TR-0028 | D153: FERSNER, KENNEDI | E153: parent.fersner@email.com | F153: Talent Ready Program: KENNEDI's Weekly Grade Report | G153: Delivered | H153: No | J153: System (Auto)
A154: 2026-01-23 14:00 | B154: BATCH-2026-0123 | C154: TR-0059 | D154: FORD, CHASE | E154: parent.ford@email.com | F154: Talent Ready Program: CHASE's Weekly Grade Report | G154: Failed | H154: No | I154: Invalid email address | J154: System (Auto)
A155: 2026-01-23 14:00 | B155: BATCH-2026-0123 | C155: TR-0029 | D155: FOSTER, BRYANT | E155: parent.foster@email.com | F155: Talent Ready Program: BRYANT's Weekly Grade Report | G155: Delivered | H155: Yes | J155: System (Auto)
A156: 2026-01-23 14:00 | B156: BATCH-2026-0123 | C156: TR-0030 | D156: GOMEZ, CHRISTIAN | E156: parent.gomez@email.com | F156: Talent Ready Program: CHRISTIAN's Weekly Grade Report | G156: Delivered | H156: Yes | J156: System (Auto)
A157: 2026-01-23 14:00 | B157: BATCH-2026-0123 | C157: TR-0031 | D157: JOHNSON, LIAM | E157: parent.johnson@email.com | F157: Talent Ready Program: LIAM's Weekly Grade Report | G157: Delivered | H157: Yes | J157: System (Auto)
A158: 2026-01-23 14:00 | B158: BATCH-2026-0123 | C158: TR-0032 | D158: MONROE-HOOD, JAHDAI | E158: parent.monroehood@email.com | F158: Talent Ready Program: JAHDAI's Weekly Grade Report | G158: Failed | H158: No | I158: Invalid email address | J158: System (Auto)
A159: 2026-01-23 14:00 | B159: BATCH-2026-0123 | C159: TR-0033 | D159: MORGAN, ESSOON | E159: parent.morgan@email.com | F159: Talent Ready Program: ESSOON's Weekly Grade Report | G159: Delivered | H159: Yes | J159: System (Auto)
A160: 2026-01-23 14:00 | B160: BATCH-2026-0123 | C160: TR-0034 | D160: MOSES, EMERIC | E160: parent.moses@email.com | F160: Talent Ready Program: EMERIC's Weekly Grade Report | G160: Delivered | H160: Yes | J160: System (Auto)
A161: 2026-01-23 14:00 | B161: BATCH-2026-0123 | C161: TR-0035 | D161: MUNGWA, RODRIKARL | E161: parent.mungwa@email.com | F161: Talent Ready Program: RODRIKARL's Weekly Grade Report | G161: Delivered | H161: Yes | J161: System (Auto)
A162: 2026-01-23 14:00 | B162: BATCH-2026-0123 | C162: TR-0036 | D162: NAVARRO-MARTINEZ, MARTHA | E162: parent.navarromartinez@email.com | F162: Talent Ready Program: MARTHA's Weekly Grade Report | G162: Delivered | H162: No | J162: System (Auto)
A163: 2026-01-23 14:00 | B163: BATCH-2026-0123 | C163: TR-0037 | D163: SOLOMON, GISELLE | E163: parent.solomon@email.com | F163: Talent Ready Program: GISELLE's Weekly Grade Report | G163: Delivered | H163: Yes | J163: System (Auto)
A164: 2026-01-23 14:00 | B164: BATCH-2026-0123 | C164: TR-0038 | D164: WALTERS, JAEV'HAN | E164: parent.walters@email.com | F164: Talent Ready Program: JAEV'HAN's Weekly Grade Report | G164: Delivered | H164: Yes | J164: System (Auto)
A165: 2026-01-23 14:00 | B165: BATCH-2026-0123 | C165: TR-0039 | D165: WASHINGTON, JOSHUA | E165: parent.washington@email.com | F165: Talent Ready Program: JOSHUA's Weekly Grade Report | G165: Delivered | H165: No | J165: System (Auto)
A166: 2026-01-23 14:00 | B166: BATCH-2026-0123 | C166: TR-0040 | D166: WHITAKER, XION | E166: parent.whitaker@email.com | F166: Talent Ready Program: XION's Weekly Grade Report | G166: Delivered | H166: No | J166: System (Auto)
A167: 2026-01-23 14:00 | B167: BATCH-2026-0123 | C167: TR-0041 | D167: WHITTED, BRAYLEN | E167: parent.whitted@email.com | F167: Talent Ready Program: BRAYLEN's Weekly Grade Report | G167: Delivered | H167: Yes | J167: System (Auto)
A168: 2026-01-23 14:00 | B168: BATCH-2026-0123 | C168: TR-0042 | D168: AKINSANYA, TIARAOLUWA | E168: parent.akinsanya@email.com | F168: Talent Ready Program: TIARAOLUWA's Weekly Grade Report | G168: Delivered | H168: Yes | J168: System (Auto)
A169: 2026-01-23 14:00 | B169: BATCH-2026-0123 | C169: TR-0043 | D169: ATKINS, PEYTON | E169: parent.atkins@email.com | F169: Talent Ready Program: PEYTON's Weekly Grade Report | G169: Delivered | H169: Yes | J169: System (Auto)
A170: 2026-01-23 14:00 | B170: BATCH-2026-0123 | C170: TR-0044 | D170: BELCHER, MALACHI | E170: parent.belcher@email.com | F170: Talent Ready Program: MALACHI's Weekly Grade Report | G170: Delivered | H170: Yes | J170: System (Auto)
A171: 2026-01-23 14:00 | B171: BATCH-2026-0123 | C171: TR-0045 | D171: DUMAS, ADDISON | E171: parent.dumas@email.com | F171: Talent Ready Program: ADDISON's Weekly Grade Report | G171: Delivered | H171: Yes | J171: System (Auto)
A172: 2026-01-23 14:00 | B172: BATCH-2026-0123 | C172: TR-0046 | D172: HARRISON, MACKENZIE | E172: parent.harrison@email.com | F172: Talent Ready Program: MACKENZIE's Weekly Grade Report | G172: Failed | H172: No | I172: Invalid email address | J172: System (Auto)
A173: 2026-01-23 14:00 | B173: BATCH-2026-0123 | C173: TR-0047 | D173: HARVEY, MEZRAH | E173: parent.harvey@email.com | F173: Talent Ready Program: MEZRAH's Weekly Grade Report | G173: Delivered | H173: No | J173: System (Auto)
A174: 2026-01-23 14:00 | B174: BATCH-2026-0123 | C174: TR-0048 | D174: HERBERT, HYON | E174: parent.herbert@email.com | F174: Talent Ready Program: HYON's Weekly Grade Report | G174: Delivered | H174: Yes | J174: System (Auto)
A175: 2026-01-23 14:00 | B175: BATCH-2026-0123 | C175: TR-0049 | D175: JOSEPH-ALEXANDER, SHILOH | E175: parent.josephalexander@email.com | F175: Talent Ready Program: SHILOH's Weekly Grade Report | G175: Delivered | H175: Yes | J175: System (Auto)
A176: 2026-01-23 14:00 | B176: BATCH-2026-0123 | C176: TR-0050 | D176: LASHLEY, AVA | E176: parent.lashley@email.com | F176: Talent Ready Program: AVA's Weekly Grade Report | G176: Delivered | H176: Yes | J176: System (Auto)
A177: 2026-01-23 14:00 | B177: BATCH-2026-0123 | C177: TR-0051 | D177: LOWERY, CADEN | E177: parent.lowery@email.com | F177: Talent Ready Program: CADEN's Weekly Grade Report | G177: Delivered | H177: Yes | J177: System (Auto)
A178: 2026-01-23 14:00 | B178: BATCH-2026-0123 | C178: TR-0052 | D178: ONUOSA, NICHOLAS | E178: parent.onuosa@email.com | F178: Talent Ready Program: NICHOLAS's Weekly Grade Report | G178: Delivered | H178: No | J178: System (Auto)
A179: 2026-01-23 14:00 | B179: BATCH-2026-0123 | C179: TR-0053 | D179: ROBINSON, MATTHEW | E179: parent.robinson@email.com | F179: Talent Ready Program: MATTHEW's Weekly Grade Report | G179: Delivered | H179: Yes | J179: System (Auto)
A180: 2026-01-23 14:00 | B180: BATCH-2026-0123 | C180: TR-0054 | D180: SAUNDERS, MADELINE | E180: parent.saunders@email.com | F180: Talent Ready Program: MADELINE's Weekly Grade Report | G180: Delivered | H180: Yes | J180: System (Auto)
A181: 2026-01-23 14:00 | B181: BATCH-2026-0123 | C181: TR-0055 | D181: SHEIKH, MUHAMMAD D. | E181: parent.sheikh@email.com | F181: Talent Ready Program: MUHAMMAD D.'s Weekly Grade Report | G181: Delivered | H181: No | J181: System (Auto)
A182: 2026-01-23 14:00 | B182: BATCH-2026-0123 | C182: TR-0056 | D182: SHINABA, MUHAMMAD M. | E182: parent.shinaba@email.com | F182: Talent Ready Program: MUHAMMAD M.'s Weekly Grade Report | G182: Delivered | H182: No | J182: System (Auto)
A183: 2026-01-23 14:00 | B183: BATCH-2026-0123 | C183: TR-0057 | D183: VIDAL, JOSHUA | E183: parent.vidal@email.com | F183: Talent Ready Program: JOSHUA's Weekly Grade Report | G183: Delivered | H183: Yes | J183: System (Auto)

Sheet Syllabus Calendar
A1: ⬅ NAVIGATE:
A2: ElevateED — SYLLABUS ASSIGNMENT CALENDAR — ALL 10 PGCC COURSES
A3: Talent Ready IT Program | Largo High School | Prince George's Community College
A4: Maryland Blueprint for Maryland's Future | CONFIDENTIAL — FERPA PROTECTED | February 13, 2026 03:50 PM
A5: Extracted from official PGCC syllabi | Fall 2025 + Spring 2026 | Proactive assignment tracking
A6: Week | B6: Date Range | C6: Course | D6: Cohort | E6: Assignment/Topic | F6: Category | G6: Points | H6: Due Date | I6: Status | J6: Notes | K6: Days Until Due | L6: Priority Alert
A7: 1 | B7: 1/20-1/25 | C7: INT 2840 | D7: 2026 | E7: Class Orientation, Intro Discussion Board | F7: Discussion | G7: 10 | H7: 1/20 | I7: ✅ Complete | K7: — | L7: ✅ Complete
A8: 1 | B8: 1/20-1/25 | C8: INT 2840 | D8: 2026 | E8: MBTI Email | F8: Assignment | G8: 10 | H8: 1/22 | I8: ✅ Complete | K8: — | L8: ✅ Complete
A9: 1 | B9: 1/20-1/25 | C9: INT 2840 | D9: 2026 | E9: Journal 1 Assignment | F9: Journal | G9: 10 | H9: 1/25 | I9: ✅ Complete | K9: — | L9: ✅ Complete
A10: 2 | B10: 1/26-2/1 | C10: INT 2840 | D10: 2026 | E10: Research Paper Topic | F10: Assignment | G10: 5 | H10: 2/1 | I10: ✅ Complete | K10: — | L10: ✅ Complete
A11: 2 | B11: 1/26-2/1 | C11: INT 2840 | D11: 2026 | E11: Resume and Cover Letter | F11: Assignment | G11: 20 | H11: 2/1 | I11: ✅ Complete | K11: — | L11: ✅ Complete
A12: 2 | B12: 1/26-2/1 | C12: INT 2840 | D12: 2026 | E12: Journal 2 Assignment | F12: Journal | G12: 15 | H12: 2/1 | I12: ✅ Complete | K12: — | L12: ✅ Complete
A13: 3 | B13: 2/2-2/8 | C13: INT 2840 | D13: 2026 | E13: Journal 3 Assignment | F13: Journal | G13: 15 | H13: 2/8 | I13: ✅ Complete | K13: — | L13: ✅ Complete
A14: 4 | B14: 2/9-2/15 | C14: INT 2840 | D14: 2026 | E14: Journal 4 Assignment | F14: Journal | G14: 15 | H14: 2/15 | I14: ⏳ Current | J14: Due this week | K14: =IF(H13="","",MAX(0,DATEVALUE(H13&"/2026")-TODAY())) -> 0 | L14: =IF(K13="","",IF(K13<=0,"⚠ OVERDUE",IF(K13<=3,"🔴 DUE NOW",IF(K13<=7,"🟠 THIS WEEK",IF(K13<=14,"🟡 NEXT 2 WEEKS","📋 Scheduled"))))) -> 📋 Scheduled
A15: 4 | B15: 2/9-2/15 | C15: INT 2840 | D15: 2026 | E15: Outline for Research Paper | F15: Assignment | G15: 5 | H15: 2/15 | I15: ⏳ Current | J15: Due this week | K15: =IF(H14="","",MAX(0,DATEVALUE(H14&"/2026")-TODAY())) -> 0 | L15: =IF(K14="","",IF(K14<=0,"⚠ OVERDUE",IF(K14<=3,"🔴 DUE NOW",IF(K14<=7,"🟠 THIS WEEK",IF(K14<=14,"🟡 NEXT 2 WEEKS","📋 Scheduled"))))) -> ⚠ OVERDUE
A16: 5 | B16: 2/16-2/22 | C16: INT 2840 | D16: 2026 | E16: Exam 1 (Chapters 1-4) | F16: Exam | G16: 150 | H16: 2/16 | I16: 📅 Upcoming | J16: MAJOR — 15% of grade | K16: =IF(H15="","",MAX(0,DATEVALUE(H15&"/2026")-TODAY())) -> 0 | L16: =IF(K15="","",IF(K15<=0,"⚠ OVERDUE",IF(K15<=3,"🔴 DUE NOW",IF(K15<=7,"🟠 THIS WEEK",IF(K15<=14,"🟡 NEXT 2 WEEKS","📋 Scheduled"))))) -> ⚠ OVERDUE
A17: 5 | B17: 2/16-2/22 | C17: INT 2840 | D17: 2026 | E17: Journal 5 Assignment | F17: Journal | G17: 15 | H17: 2/22 | I17: 📅 Upcoming | K17: =IF(H16="","",MAX(0,DATEVALUE(H16&"/2026")-TODAY())) -> 0 | L17: =IF(K16="","",IF(K16<=0,"⚠ OVERDUE",IF(K16<=3,"🔴 DUE NOW",IF(K16<=7,"🟠 THIS WEEK",IF(K16<=14,"🟡 NEXT 2 WEEKS","📋 Scheduled"))))) -> ⚠ OVERDUE
A18: 5 | B18: 2/16-2/22 | C18: INT 2840 | D18: 2026 | E18: Annotated Bibliography | F18: Assignment | G18: 5 | H18: 2/22 | I18: 📅 Upcoming | K18: =IF(H17="","",MAX(0,DATEVALUE(H17&"/2026")-TODAY())) -> 0 | L18: =IF(K17="","",IF(K17<=0,"⚠ OVERDUE",IF(K17<=3,"🔴 DUE NOW",IF(K17<=7,"🟠 THIS WEEK",IF(K17<=14,"🟡 NEXT 2 WEEKS","📋 Scheduled"))))) -> ⚠ OVERDUE
A19: 6 | B19: 2/23-3/1 | C19: INT 2840 | D19: 2026 | E19: Journal 6 Assignment | F19: Journal | G19: 15 | H19: 3/1 | I19: 📅 Upcoming | K19: =IF(H18="","",MAX(0,DATEVALUE(H18&"/2026")-TODAY())) -> 0 | L19: =IF(K18="","",IF(K18<=0,"⚠ OVERDUE",IF(K18<=3,"🔴 DUE NOW",IF(K18<=7,"🟠 THIS WEEK",IF(K18<=14,"🟡 NEXT 2 WEEKS","📋 Scheduled"))))) -> ⚠ OVERDUE
A20: 6 | B20: 2/23-3/1 | C20: INT 2840 | D20: 2026 | E20: Evaluation Matrix | F20: Assignment | G20: 5 | H20: 3/1 | I20: 📅 Upcoming | K20: =IF(H19="","",MAX(0,DATEVALUE(H19&"/2026")-TODAY())) -> 0 | L20: =IF(K19="","",IF(K19<=0,"⚠ OVERDUE",IF(K19<=3,"🔴 DUE NOW",IF(K19<=7,"🟠 THIS WEEK",IF(K19<=14,"🟡 NEXT 2 WEEKS","📋 Scheduled"))))) -> ⚠ OVERDUE
A21: 7 | B21: 3/2-3/8 | C21: INT 2840 | D21: 2026 | E21: Group Project Checkpoint #1 | F21: Project | G21: 0 | H21: 3/3 | I21: 📅 Upcoming | J21: Team checkpoint | K21: =IF(H20="","",MAX(0,DATEVALUE(H20&"/2026")-TODAY())) -> 0 | L21: =IF(K20="","",IF(K20<=0,"⚠ OVERDUE",IF(K20<=3,"🔴 DUE NOW",IF(K20<=7,"🟠 THIS WEEK",IF(K20<=14,"🟡 NEXT 2 WEEKS","📋 Scheduled"))))) -> ⚠ OVERDUE
A22: 7 | B22: 3/2-3/8 | C22: INT 2840 | D22: 2026 | E22: Journal 7 Assignment | F22: Journal | G22: 15 | H22: 3/8 | I22: 📅 Upcoming | K22: =IF(H21="","",MAX(0,DATEVALUE(H21&"/2026")-TODAY())) -> 0 | L22: =IF(K21="","",IF(K21<=0,"⚠ OVERDUE",IF(K21<=3,"🔴 DUE NOW",IF(K21<=7,"🟠 THIS WEEK",IF(K21<=14,"🟡 NEXT 2 WEEKS","📋 Scheduled"))))) -> ⚠ OVERDUE
A23: 7 | B23: 3/2-3/8 | C23: INT 2840 | D23: 2026 | E23: Research Paper | F23: Paper | G23: 100 | H23: 3/8 | I23: 📅 Upcoming | J23: MAJOR — 10% of grade | K23: =IF(H22="","",MAX(0,DATEVALUE(H22&"/2026")-TODAY())) -> 0 | L23: =IF(K22="","",IF(K22<=0,"⚠ OVERDUE",IF(K22<=3,"🔴 DUE NOW",IF(K22<=7,"🟠 THIS WEEK",IF(K22<=14,"🟡 NEXT 2 WEEKS","📋 Scheduled"))))) -> ⚠ OVERDUE
A24: 8 | B24: 3/16-3/19 | C24: INT 2840 | D24: 2026 | E24: Exam 2 (Chapters 5-8) | F24: Exam | G24: 150 | H24: 3/16 | I24: 📅 Upcoming | J24: MAJOR — 15% of grade | K24: =IF(H23="","",MAX(0,DATEVALUE(H23&"/2026")-TODAY())) -> 0 | L24: =IF(K23="","",IF(K23<=0,"⚠ OVERDUE",IF(K23<=3,"🔴 DUE NOW",IF(K23<=7,"🟠 THIS WEEK",IF(K23<=14,"🟡 NEXT 2 WEEKS","📋 Scheduled"))))) -> ⚠ OVERDUE
A25: 8 | B25: 3/16-3/19 | C25: INT 2840 | D25: 2026 | E25: Research Paper Presentations | F25: Presentation | G25: 0 | H25: 3/19 | I25: 📅 Upcoming | K25: =IF(H24="","",MAX(0,DATEVALUE(H24&"/2026")-TODAY())) -> 0 | L25: =IF(K24="","",IF(K24<=0,"⚠ OVERDUE",IF(K24<=3,"🔴 DUE NOW",IF(K24<=7,"🟠 THIS WEEK",IF(K24<=14,"🟡 NEXT 2 WEEKS","📋 Scheduled"))))) -> ⚠ OVERDUE
A26: 15 | B26: 5/4 | C26: INT 2840 | D26: 2026 | E26: RFP Binder Due | F26: Project | G26: 250 | H26: 5/4 | I26: 📅 Upcoming | J26: MAJOR — 25% of grade | K26: =IF(H25="","",MAX(0,DATEVALUE(H25&"/2026")-TODAY())) -> 0 | L26: =IF(K25="","",IF(K25<=0,"⚠ OVERDUE",IF(K25<=3,"🔴 DUE NOW",IF(K25<=7,"🟠 THIS WEEK",IF(K25<=14,"🟡 NEXT 2 WEEKS","📋 Scheduled"))))) -> ⚠ OVERDUE
A27: 16 | B27: 5/5 | C27: INT 2840 | D27: 2026 | E27: Present Team Project + Final Eval | F27: Presentation | G27: 250 | H27: 5/5 | I27: 📅 Upcoming | J27: MAJOR — 25% of grade | K27: =IF(H26="","",MAX(0,DATEVALUE(H26&"/2026")-TODAY())) -> 40 | L27: =IF(K26="","",IF(K26<=0,"⚠ OVERDUE",IF(K26<=3,"🔴 DUE NOW",IF(K26<=7,"🟠 THIS WEEK",IF(K26<=14,"🟡 NEXT 2 WEEKS","📋 Scheduled"))))) -> ⚠ OVERDUE
A28: 1 | B28: 1/20-1/25 | C28: INT 2310 | D28: 2026 | E28: Module 1: Intro Windows Server — Labs, Quiz | F28: Lab/Quiz | G28: 0 | H28: 1/25 | I28: ✅ Complete | K28: — | L28: ✅ Complete
A29: 2 | B29: 1/26-2/1 | C29: INT 2310 | D29: 2026 | E29: Module 2: Active Directory — Labs, Quiz | F29: Lab/Quiz | G29: 0 | H29: 2/1 | I29: ✅ Complete | K29: — | L29: ✅ Complete
A30: 3 | B30: 2/2-2/8 | C30: INT 2310 | D30: 2026 | E30: Module 3: Managing AD Accounts — Labs, Quiz | F30: Lab/Quiz | G30: 0 | H30: 2/8 | I30: ✅ Complete | K30: — | L30: ✅ Complete
A31: 4 | B31: 2/9-2/15 | C31: INT 2310 | D31: 2026 | E31: Module 4: Configuring Group Policies — Labs, Quiz | F31: Lab/Quiz | G31: 0 | H31: 2/15 | I31: ⏳ Current | J31: Due this week | K31: =IF(H30="","",MAX(0,DATEVALUE(H30&"/2026")-TODAY())) -> 0 | L31: =IF(K30="","",IF(K30<=0,"⚠ OVERDUE",IF(K30<=3,"🔴 DUE NOW",IF(K30<=7,"🟠 THIS WEEK",IF(K30<=14,"🟡 NEXT 2 WEEKS","📋 Scheduled"))))) -> 📋 Scheduled
A32: 5 | B32: 2/16-2/22 | C32: INT 2310 | D32: 2026 | E32: Module 5: Configuring Domains — Test 1 (Ch 1-4) | F32: Exam | G32: 0 | H32: 2/22 | I32: 📅 Upcoming | J32: MAJOR EXAM | K32: =IF(H31="","",MAX(0,DATEVALUE(H31&"/2026")-TODAY())) -> 0 | L32: =IF(K31="","",IF(K31<=0,"⚠ OVERDUE",IF(K31<=3,"🔴 DUE NOW",IF(K31<=7,"🟠 THIS WEEK",IF(K31<=14,"🟡 NEXT 2 WEEKS","📋 Scheduled"))))) -> ⚠ OVERDUE
A33: 6 | B33: 2/23-3/1 | C33: INT 2310 | D33: 2026 | E33: Module 6: Manage Server Hybrid Env — Labs, Quiz | F33: Lab/Quiz | G33: 0 | H33: 3/1 | I33: 📅 Upcoming | K33: =IF(H32="","",MAX(0,DATEVALUE(H32&"/2026")-TODAY())) -> 0 | L33: =IF(K32="","",IF(K32<=0,"⚠ OVERDUE",IF(K32<=3,"🔴 DUE NOW",IF(K32<=7,"🟠 THIS WEEK",IF(K32<=14,"🟡 NEXT 2 WEEKS","📋 Scheduled"))))) -> ⚠ OVERDUE
A34: 14 | B34: 5/5 | C34: INT 2310 | D34: 2026 | E34: Final Exam (9:30 AM) | F34: Exam | G34: 0 | H34: 5/5 | I34: 📅 Upcoming | J34: MAJOR EXAM — 50% weight | K34: =IF(H33="","",MAX(0,DATEVALUE(H33&"/2026")-TODAY())) -> 0 | L34: =IF(K33="","",IF(K33<=0,"⚠ OVERDUE",IF(K33<=3,"🔴 DUE NOW",IF(K33<=7,"🟠 THIS WEEK",IF(K33<=14,"🟡 NEXT 2 WEEKS","📋 Scheduled"))))) -> ⚠ OVERDUE
A35: 3 | B35: 2/2-2/4 | C35: EGL 1340 | D35: 2026 | E35: Writing Assignment #1: Resume/Cover Letter (Assigned) | F35: Assignment | G35: 100 | H35: 2/11 | I35: ✅ Complete | J35: 15% of grade | K35: — | L35: ✅ Complete
A36: 4 | B36: 2/9-2/11 | C36: EGL 1340 | D36: 2026 | E36: Writing Assignment #1 Due | F36: Assignment | G36: 100 | H36: 2/11 | I36: ✅ Complete | K36: — | L36: ✅ Complete
A37: 5 | B37: 2/17-2/19 | C37: EGL 1340 | D37: 2026 | E37: Writing Assignment #2: Report Writing (Assigned) | F37: Assignment | G37: 100 | H37: 3/4 | I37: ⏳ Current | J37: 15% of grade | K37: =IF(H36="","",MAX(0,DATEVALUE(H36&"/2026")-TODAY())) -> 0 | L37: =IF(K36="","",IF(K36<=0,"⚠ OVERDUE",IF(K36<=3,"🔴 DUE NOW",IF(K36<=7,"🟠 THIS WEEK",IF(K36<=14,"🟡 NEXT 2 WEEKS","📋 Scheduled"))))) -> 📋 Scheduled
A38: 7 | B38: 3/2-3/4 | C38: EGL 1340 | D38: 2026 | E38: Writing Assignment #2 Due | F38: Assignment | G38: 100 | H38: 3/4 | I38: 📅 Upcoming | K38: =IF(H37="","",MAX(0,DATEVALUE(H37&"/2026")-TODAY())) -> 0 | L38: =IF(K37="","",IF(K37<=0,"⚠ OVERDUE",IF(K37<=3,"🔴 DUE NOW",IF(K37<=7,"🟠 THIS WEEK",IF(K37<=14,"🟡 NEXT 2 WEEKS","📋 Scheduled"))))) -> ⚠ OVERDUE
A39: 8 | B39: 3/9-3/11 | C39: EGL 1340 | D39: 2026 | E39: Writing Assignment #3: Proposal (Group) | F39: Group | G39: 100 | H39: 4/1 | I39: 📅 Upcoming | J39: 25% of grade | K39: =IF(H38="","",MAX(0,DATEVALUE(H38&"/2026")-TODAY())) -> 0 | L39: =IF(K38="","",IF(K38<=0,"⚠ OVERDUE",IF(K38<=3,"🔴 DUE NOW",IF(K38<=7,"🟠 THIS WEEK",IF(K38<=14,"🟡 NEXT 2 WEEKS","📋 Scheduled"))))) -> ⚠ OVERDUE
A40: 11 | B40: 3/30-4/1 | C40: EGL 1340 | D40: 2026 | E40: Proposal Writing #3 Due | F40: Group | G40: 100 | H40: 4/1 | I40: 📅 Upcoming | K40: =IF(H39="","",MAX(0,DATEVALUE(H39&"/2026")-TODAY())) -> 7 | L40: =IF(K39="","",IF(K39<=0,"⚠ OVERDUE",IF(K39<=3,"🔴 DUE NOW",IF(K39<=7,"🟠 THIS WEEK",IF(K39<=14,"🟡 NEXT 2 WEEKS","📋 Scheduled"))))) -> ⚠ OVERDUE
A41: 13 | B41: 4/14-4/16 | C41: EGL 1340 | D41: 2026 | E41: Writing Assignment #4: PowerPoint (Group) | F41: Group | G41: 100 | H41: 5/6 | I41: 📅 Upcoming | J41: 25% of grade | K41: =IF(H40="","",MAX(0,DATEVALUE(H40&"/2026")-TODAY())) -> 7 | L41: =IF(K40="","",IF(K40<=0,"⚠ OVERDUE",IF(K40<=3,"🔴 DUE NOW",IF(K40<=7,"🟠 THIS WEEK",IF(K40<=14,"🟡 NEXT 2 WEEKS","📋 Scheduled"))))) -> 🟠 THIS WEEK
A42: 16 | B42: 5/4-5/6 | C42: EGL 1340 | D42: 2026 | E42: Group PowerPoint/Oral Presentation Due | F42: Presentation | G42: 100 | H42: 5/6 | I42: 📅 Upcoming | J42: FINAL — 25% of grade | K42: =IF(H41="","",MAX(0,DATEVALUE(H41&"/2026")-TODAY())) -> 42 | L42: =IF(K41="","",IF(K41<=0,"⚠ OVERDUE",IF(K41<=3,"🔴 DUE NOW",IF(K41<=7,"🟠 THIS WEEK",IF(K41<=14,"🟡 NEXT 2 WEEKS","📋 Scheduled"))))) -> 🟠 THIS WEEK
A43: — | B43: Fall 2025 | C43: BIO 1110 | D43: 2027 | E43: Environmental Biology — Full semester coursework | F43: Mixed | G43: 0 | H43: Dec 2025 | I43: ✅ Complete | J43: Grade: See Cohort 2027 | K43: — | L43: ✅ Complete
A44: — | B44: Fall 2025 | C44: BIO 1120 | D44: 2027 | E44: Environmental Biology Lab — Full semester labs | F44: Lab | G44: 0 | H44: Dec 2025 | I44: ✅ Complete | J44: Grade: See Cohort 2027 | K44: — | L44: ✅ Complete
A45: — | B45: Fall 2025 | C45: INT 1550 | D45: 2027 | E45: Intro to Networks: Network+ Prep — Full semester | F45: Mixed | G45: 0 | H45: Dec 2025 | I45: ✅ Complete | J45: Grade: See Cohort 2027 | K45: — | L45: ✅ Complete
A46: — | B46: Fall 2025 | C46: COM 1010 | D46: 2028 | E46: Speech Communication — Full semester coursework | F46: Mixed | G46: 0 | H46: Dec 2025 | I46: ✅ Complete | J46: Grade: See Cohort 2028 | K46: — | L46: ✅ Complete
A47: — | B47: Fall 2025 | C47: INT 1700 | D47: 2028 | E47: Understanding Operating Systems — Full semester | F47: Mixed | G47: 0 | H47: Dec 2025 | I47: ✅ Complete | J47: Grade: See Cohort 2028 | K47: — | L47: ✅ Complete
A48: — | B48: Fall 2025 | C48: INT 1010 | D48: 2029 | E48: Introduction to Information Technology — Full semester | F48: Mixed | G48: 0 | H48: Dec 2025 | I48: ✅ Complete | J48: Grade: See Cohort 2029 | K48: — | L48: ✅ Complete

Sheet Assignment Grades
A1: ⬅ NAVIGATE:
A2: ElevateED — ASSIGNMENT-LEVEL GRADE DECOMPOSITION — ASI Enhancement #3
A3: Talent Ready IT Program | Largo High School | Prince George's Community College
A4: Maryland Blueprint for Maryland's Future | CONFIDENTIAL — FERPA PROTECTED | February 13, 2026 04:05 PM
A5: Individual assignments per student per course | Category breakdowns | Pattern detection | Spring 2026
A6: INT 2840 — System Analysis/Project Mgmt | Prof. Bartlebaugh | 1000 pts Total
D7: Journal | E7: Journal | F7: Journal | G7: Journal | H7: Assignment | I7: Assignment | J7: Assignment | K7: Assignment | L7: Exam | M7: Journal | N7: Journal | O7: Assignment | P7: Journal | Q7: Paper | R7: Exam | S7: Project
D8: 10 pts | E8: 15 pts | F8: 15 pts | G8: 15 pts | H8: 5 pts | I8: 20 pts | J8: 5 pts | K8: 5 pts | L8: 150 pts | M8: 15 pts | N8: 15 pts | O8: 5 pts | P8: 15 pts | Q8: 100 pts | R8: 150 pts | S8: 0 pts
D9: Due 1/25 | E9: Due 2/1 | F9: Due 2/8 | G9: Due 2/15 | H9: Due 2/1 | I9: Due 2/1 | J9: Due 2/15 | K9: Due 2/22 | L9: Due 2/16 | M9: Due 2/22 | N9: Due 3/1 | O9: Due 3/1 | P9: Due 3/8 | Q9: Due 3/8 | R9: Due 3/16 | S9: Due 3/3
A10: Student ID | B10: Last Name | C10: First Name | D10: Journal 1 | E10: Journal 2 | F10: Journal 3 | G10: Journal 4 | H10: Research Topic | I10: Resume/CL | J10: Paper Outline | K10: Annot Bib | L10: Exam 1 | M10: Journal 5 | N10: Journal 6 | O10: Eval Matrix | P10: Journal 7 | Q10: Research Paper | R10: Exam 2 | S10: Checkpoint 1 | T10: Points Earned | U10: Points Possible | V10: Percentage | W10: Category: Journals | X10: Category: Exams | Y10: Category: Assignments | Z10: Category: Papers
A11: TR-0001 | B11: CRICHTON III | C11: LEONARD | D11: 7.4 | E11: 12.8 | F11: 12.8 | G11: 14.4 | H11: 3.7 | I11: 15.3 | T11: =SUM(D10:S10) -> 0 | U11: 540 | V11: =IF(U11>0,T11/U11,"") -> 0 | W11: =IF(COUNT(D10,E10,F10,G10,M10,N10,P10)>0,AVERAGE(D10,E10,F10,G10,M10,N10,P10),"") | X11: =IF(COUNT(L10,R10)>0,AVERAGE(L10,R10),"") | Y11: =IF(COUNT(H10,I10,J10,K10,O10)>0,AVERAGE(H10,I10,J10,K10,O10),"") | Z11: =IF(COUNT(Q10)>0,AVERAGE(Q10),"")
A12: TR-0002 | B12: CROWELL | C12: KINGSTON | D12: 8.8 | E12: 13 | F12: 14 | G12: 13 | H12: 4.6 | I12: 18.6 | T12: =SUM(D11:S11) -> 66.4 | U12: 540 | V12: =IF(U11>0,T11/U11,"") -> 0 | W12: =IF(COUNT(D11,E11,F11,G11,M11,N11,P11)>0,AVERAGE(D11,E11,F11,G11,M11,N11,P11),"") -> 11.85 | X12: =IF(COUNT(L11,R11)>0,AVERAGE(L11,R11),"") | Y12: =IF(COUNT(H11,I11,J11,K11,O11)>0,AVERAGE(H11,I11,J11,K11,O11),"") -> 9.5 | Z12: =IF(COUNT(Q11)>0,AVERAGE(Q11),"")
A13: TR-0003 | B13: DAVIS | C13: GABRIEL | D13: 9.3 | E13: 13.1 | F13: 11.6 | G13: 13.3 | H13: 3.7 | I13: 18.9 | T13: =SUM(D12:S12) -> 72 | U13: 540 | V13: =IF(U12>0,T12/U12,"") -> 0.12296296 | W13: =IF(COUNT(D12,E12,F12,G12,M12,N12,P12)>0,AVERAGE(D12,E12,F12,G12,M12,N12,P12),"") -> 12.2 | X13: =IF(COUNT(L12,R12)>0,AVERAGE(L12,R12),"") | Y13: =IF(COUNT(H12,I12,J12,K12,O12)>0,AVERAGE(H12,I12,J12,K12,O12),"") -> 11.6 | Z13: =IF(COUNT(Q12)>0,AVERAGE(Q12),"")
A14: TR-0004 | B14: FERSNER | C14: LAILAH | D14: 8.3 | E14: 14.2 | F14: 13.6 | G14: 13.6 | H14: 3.8 | I14: 15.5 | T14: =SUM(D13:S13) -> 69.9 | U14: 540 | V14: =IF(U13>0,T13/U13,"") -> 0.13333333 | W14: =IF(COUNT(D13,E13,F13,G13,M13,N13,P13)>0,AVERAGE(D13,E13,F13,G13,M13,N13,P13),"") -> 11.825 | X14: =IF(COUNT(L13,R13)>0,AVERAGE(L13,R13),"") | Y14: =IF(COUNT(H13,I13,J13,K13,O13)>0,AVERAGE(H13,I13,J13,K13,O13),"") -> 11.3 | Z14: =IF(COUNT(Q13)>0,AVERAGE(Q13),"")
A15: TR-0005 | B15: FORD | C15: JAMES | D15: 9.9 | E15: 14.7 | F15: 14.1 | G15: 15 | H15: 4.3 | I15: 14.5 | T15: =SUM(D14:S14) -> 69 | U15: 540 | V15: =IF(U14>0,T14/U14,"") -> 0.12944444 | W15: =IF(COUNT(D14,E14,F14,G14,M14,N14,P14)>0,AVERAGE(D14,E14,F14,G14,M14,N14,P14),"") -> 12.425 | X15: =IF(COUNT(L14,R14)>0,AVERAGE(L14,R14),"") | Y15: =IF(COUNT(H14,I14,J14,K14,O14)>0,AVERAGE(H14,I14,J14,K14,O14),"") -> 9.65 | Z15: =IF(COUNT(Q14)>0,AVERAGE(Q14),"")
A16: TR-0006 | B16: FORREST | C16: TYLEYL | D16: 8 | E16: 13 | F16: 11.8 | G16: 12.6 | H16: 4.8 | I16: 18.2 | T16: =SUM(D15:S15) -> 72.5 | U16: 540 | V16: =IF(U15>0,T15/U15,"") -> 0.12777778 | W16: =IF(COUNT(D15,E15,F15,G15,M15,N15,P15)>0,AVERAGE(D15,E15,F15,G15,M15,N15,P15),"") -> 13.425 | X16: =IF(COUNT(L15,R15)>0,AVERAGE(L15,R15),"") | Y16: =IF(COUNT(H15,I15,J15,K15,O15)>0,AVERAGE(H15,I15,J15,K15,O15),"") -> 9.4 | Z16: =IF(COUNT(Q15)>0,AVERAGE(Q15),"")
A17: TR-0007 | B17: JALLOH | C17: JENABU | D17: 8.7 | E17: 10.6 | F17: 13.7 | G17: 12.1 | H17: 4.1 | I17: 16.4 | T17: =SUM(D16:S16) -> 68.4 | U17: 540 | V17: =IF(U16>0,T16/U16,"") -> 0.13425926 | W17: =IF(COUNT(D16,E16,F16,G16,M16,N16,P16)>0,AVERAGE(D16,E16,F16,G16,M16,N16,P16),"") -> 11.35 | X17: =IF(COUNT(L16,R16)>0,AVERAGE(L16,R16),"") | Y17: =IF(COUNT(H16,I16,J16,K16,O16)>0,AVERAGE(H16,I16,J16,K16,O16),"") -> 11.5 | Z17: =IF(COUNT(Q16)>0,AVERAGE(Q16),"")
A18: TR-0008 | B18: JOHNSON-BONILLA | C18: CHRISTOPHER | D18: 8.8 | E18: 12.7 | F18: 11 | G18: 12.8 | H18: 4.6 | I18: 17.6 | T18: =SUM(D17:S17) -> 65.6 | U18: 540 | V18: =IF(U17>0,T17/U17,"") -> 0.12666667 | W18: =IF(COUNT(D17,E17,F17,G17,M17,N17,P17)>0,AVERAGE(D17,E17,F17,G17,M17,N17,P17),"") -> 11.275 | X18: =IF(COUNT(L17,R17)>0,AVERAGE(L17,R17),"") | Y18: =IF(COUNT(H17,I17,J17,K17,O17)>0,AVERAGE(H17,I17,J17,K17,O17),"") -> 10.25 | Z18: =IF(COUNT(Q17)>0,AVERAGE(Q17),"")
A19: TR-0009 | B19: OLUBIYI | C19: OLUWANIFEMI | D19: 8.5 | E19: 14.6 | F19: 11.7 | G19: 12.4 | H19: 4.9 | I19: 16.9 | T19: =SUM(D18:S18) -> 67.5 | U19: 540 | V19: =IF(U18>0,T18/U18,"") -> 0.12148148 | W19: =IF(COUNT(D18,E18,F18,G18,M18,N18,P18)>0,AVERAGE(D18,E18,F18,G18,M18,N18,P18),"") -> 11.325 | X19: =IF(COUNT(L18,R18)>0,AVERAGE(L18,R18),"") | Y19: =IF(COUNT(H18,I18,J18,K18,O18)>0,AVERAGE(H18,I18,J18,K18,O18),"") -> 11.1 | Z19: =IF(COUNT(Q18)>0,AVERAGE(Q18),"")
A20: TR-0010 | B20: SANNI | C20: MOFEOLUWA | D20: 8.6 | E20: 10.6 | F20: 11.5 | G20: 11.1 | H20: 3.6 | I20: 18.2 | T20: =SUM(D19:S19) -> 69 | U20: 540 | V20: =IF(U19>0,T19/U19,"") -> 0.125 | W20: =IF(COUNT(D19,E19,F19,G19,M19,N19,P19)>0,AVERAGE(D19,E19,F19,G19,M19,N19,P19),"") -> 11.8 | X20: =IF(COUNT(L19,R19)>0,AVERAGE(L19,R19),"") | Y20: =IF(COUNT(H19,I19,J19,K19,O19)>0,AVERAGE(H19,I19,J19,K19,O19),"") -> 10.9 | Z20: =IF(COUNT(Q19)>0,AVERAGE(Q19),"")
A21: TR-0011 | B21: SCARLETT | C21: OLIVIA | D21: 9.7 | E21: 11 | F21: 13.3 | G21: 12.6 | H21: 4.2 | I21: 15.4 | T21: =SUM(D20:S20) -> 63.6 | U21: 540 | V21: =IF(U20>0,T20/U20,"") -> 0.12777778 | W21: =IF(COUNT(D20,E20,F20,G20,M20,N20,P20)>0,AVERAGE(D20,E20,F20,G20,M20,N20,P20),"") -> 10.45 | X21: =IF(COUNT(L20,R20)>0,AVERAGE(L20,R20),"") | Y21: =IF(COUNT(H20,I20,J20,K20,O20)>0,AVERAGE(H20,I20,J20,K20,O20),"") -> 10.9 | Z21: =IF(COUNT(Q20)>0,AVERAGE(Q20),"")
A22: TR-0012 | B22: WALLACE | C22: JUSTIN | D22: 9.7 | E22: 13.3 | F22: 12.6 | G22: 12.6 | H22: 4.9 | I22: 19.9 | T22: =SUM(D21:S21) -> 66.2 | U22: 540 | V22: =IF(U21>0,T21/U21,"") -> 0.11777778 | W22: =IF(COUNT(D21,E21,F21,G21,M21,N21,P21)>0,AVERAGE(D21,E21,F21,G21,M21,N21,P21),"") -> 11.65 | X22: =IF(COUNT(L21,R21)>0,AVERAGE(L21,R21),"") | Y22: =IF(COUNT(H21,I21,J21,K21,O21)>0,AVERAGE(H21,I21,J21,K21,O21),"") -> 9.8 | Z22: =IF(COUNT(Q21)>0,AVERAGE(Q21),"")
A23: TR-0013 | B23: WILLIAMS | C23: CHLOE | D23: 8.6 | E23: 13 | F23: 13.5 | G23: 11.9 | H23: 4.7 | I23: 17 | T23: =SUM(D22:S22) -> 73 | U23: 540 | V23: =IF(U22>0,T22/U22,"") -> 0.12259259 | W23: =IF(COUNT(D22,E22,F22,G22,M22,N22,P22)>0,AVERAGE(D22,E22,F22,G22,M22,N22,P22),"") -> 12.05 | X23: =IF(COUNT(L22,R22)>0,AVERAGE(L22,R22),"") | Y23: =IF(COUNT(H22,I22,J22,K22,O22)>0,AVERAGE(H22,I22,J22,K22,O22),"") -> 12.4 | Z23: =IF(COUNT(Q22)>0,AVERAGE(Q22),"")
... A27: TR-0058 | B27: SCOTT | C27: SANAA | D27: 9.7 | E27: 14.2 | F27: 11.9 | G27: 14.6 | H27: 3.6 | I27: 18.1 | T27: =SUM(D26:S26) -> 69.5 | U27: 540 | V27: =IF(U26>0,T26/U26,"") -> 0.13222222 | W27: =IF(COUNT(D26,E26,F26,G26,M26,N26,P26)>0,AVERAGE(D26,E26,F26,G26,M26,N26,P26),"") -> 11.875 | X27: =IF(COUNT(L26,R26)>0,AVERAGE(L26,R26),"") | Y27: =IF(COUNT(H26,I26,J26,K26,O26)>0,AVERAGE(H26,I26,J26,K26,O26),"") -> 11 | Z27: =IF(COUNT(Q26)>0,AVERAGE(Q26),"")
A1003: TR-0034 | B1003: MOSES, EMERIC | C1003: 2028 | D1003: NTR-1010 | E1003: Intro to Nutrition | F1003: Chapter 01 Quiz | G1003: Assignments | H1003: Feb 2 | I1003: 18.33 | J1003: 25 | K1003: 73.3% | L1003: Graded
A1004: TR-0034 | B1004: MOSES, EMERIC | C1004: 2028 | D1004: NTR-1010 | E1004: Intro to Nutrition | F1004: M1: Diet Assessment Part 1 | G1004: Assignments | H1004: Feb 2 | I1004: 10 | J1004: 10 | K1004: 100% | L1004: Graded
A1005: TR-0034 | B1005: MOSES, EMERIC | C1005: 2028 | D1005: NTR-1010 | E1005: Intro to Nutrition | F1005: Chapter 02 Quiz: Nutrition Tools | G1005: Assignments | H1005: Feb 9 | I1005: 23.33 | J1005: 25 | K1005: 93.3% | L1005: Graded
A1006: TR-0034 | B1006: MOSES, EMERIC | C1006: 2028 | D1006: NTR-1010 | E1006: Intro to Nutrition | F1006: M2: Diet Assessment Part 2 | G1006: Assignments | H1006: Feb 9 | I1006: 40 | J1006: 40 | K1006: 100% | L1006: Graded
A1007: TR-0034 | B1007: MOSES, EMERIC | C1007: 2028 | D1007: NTR-1010 | E1007: Intro to Nutrition | F1007: Chapter 03 Quiz: Remarkable Body | G1007: Assignments | H1007: Feb 17 | J1007: 25 | K1007: 93.33% | L1007: Graded
A1008: TR-0034 | B1008: MOSES, EMERIC | C1008: 2028 | D1008: NTR-1010 | E1008: Intro to Nutrition | F1008: M3: NTR Exam 1 | G1008: Exams | H1008: Feb 18 | I1008: 71 | J1008: 100 | K1008: 71% | L1008: Graded
A1009: TR-0034 | B1009: MOSES, EMERIC | C1009: 2028 | D1009: NTR-1010 | E1009: Intro to Nutrition | F1009: Ch04 D&W+ Diet Assessment: Carbs | G1009: Assignments | H1009: Mar 2 | J1009: 25 | K1009: 60% | L1009: Graded
A1010: TR-0034 | B1010: MOSES, EMERIC | C1010: 2028 | D1010: NTR-1010 | E1010: Intro to Nutrition | F1010: Ch04 Quiz: Carbohydrates | G1010: Assignments | H1010: Mar 2 | I1010: 23.33 | J1010: 25 | K1010: 93.3% | L1010: Graded
A1011: TR-0034 | B1011: MOSES, EMERIC | C1011: 2028 | D1011: NTR-1010 | E1011: Intro to Nutrition | F1011: Ch05 Closer Look: Lipids | G1011: Assignments | H1011: Mar 16 | J1011: 25 | K1011: 95.24% | L1011: Graded
A1012: TR-0034 | B1012: MOSES, EMERIC | C1012: 2028 | D1012: NTR-1010 | E1012: Intro to Nutrition | F1012: Ch06 Case Study: Making Meatless Work | G1012: Assignments | H1012: Mar 23 | J1012: 35 | K1012: MISSING | L1012: Missing
A1013: TR-0034 | B1013: MOSES, EMERIC | C1013: 2028 | D1013: NTR-1010 | E1013: Intro to Nutrition | F1013: Ch06 Quiz: Proteins | G1013: Assignments | H1013: Mar 23 | J1013: 25 | K1013: MISSING | L1013: Missing
A1014: TR-0034 | B1014: MOSES, EMERIC | C1014: 2028 | D1014: NTR-1010 | E1014: Intro to Nutrition | F1014: M6: NTR Exam 2 | G1014: Exams | H1014: Mar 25 | J1014: 100 | K1014: MISSING | L1014: Missing
A1015: TR-0034 | B1015: MOSES, EMERIC | C1015: 2028 | D1015: SOC-1010 | E1015: Introduction to Sociology | F1015: Getting Started: Introductions | G1015: Discussion | H1015: Feb 1 | I1015: 5 | J1015: 5 | K1015: 100% | L1015: Graded
A1016: TR-0034 | B1016: MOSES, EMERIC | C1016: 2028 | D1016: SOC-1010 | E1016: Introduction to Sociology | F1016: SAA1 | G1016: Assignments | H1016: Feb 22 | I1016: 45 | J1016: 50 | K1016: 90% | L1016: Graded
A1017: TR-0034 | B1017: MOSES, EMERIC | C1017: 2028 | D1017: SOC-1010 | E1017: Introduction to Sociology | F1017: Exam 1: Ch 1-2 Sociological Imagination | G1017: EXAMS | H1017: Mar 8 | I1017: 27 | J1017: 50 | K1017: 54% | L1017: Graded
A1018: TR-0034 | B1018: MOSES, EMERIC | C1018: 2028 | D1018: SOC-1010 | E1018: Introduction to Sociology | F1018: SAA2 | G1018: Assignments | H1018: Mar 29 | J1018: 50 | K1018: MISSING | L1018: Missing
A1019: TR-0034 | B1019: MOSES, EMERIC | C1019: 2028 | D1019: SOC-1010 | E1019: Introduction to Sociology | F1019: Exam 2: Chapters 3-5 | G1019: EXAMS | H1019: Mar 30 | J1019: 50 | K1019: MISSING | L1019: Missing
A1020: TR-0004 | B1020: FERSNER, LAILAH | C1020: 2026 | D1020: INT-2310 | E1020: Windows Server Admin | F1020: Introduction Discussion | G1020: Discussions | H1020: Jan 22 | I1020: 10 | J1020: 10 | K1020: 100% | L1020: Graded
A1021: TR-0004 | B1021: FERSNER, LAILAH | C1021: 2026 | D1021: INT-2310 | E1021: Windows Server Admin | F1021: Quiz: Module 01 Windows Server Hybrid | G1021: Assignments | H1021: Feb 3 | K1021: 100% | L1021: Graded
A1022: TR-0004 | B1022: FERSNER, LAILAH | C1022: 2026 | D1022: INT-2310 | E1022: Windows Server Admin | F1022: Groups Lab | G1022: Assignments | H1022: Feb 12 | I1022: 14 | J1022: 20 | K1022: 70% | L1022: Graded
A1023: TR-0004 | B1023: FERSNER, LAILAH | C1023: 2026 | D1023: INT-2310 | E1023: Windows Server Admin | F1023: Group Scopes | G1023: Assignments | H1023: Feb 17 | I1023: 15 | J1023: 20 | K1023: 75% | L1023: Graded
A1024: TR-0004 | B1024: FERSNER, LAILAH | C1024: 2026 | D1024: INT-2310 | E1024: Windows Server Admin | F1024: Group Policy | G1024: Assignments | H1024: Feb 23 | I1024: T | J1024: 30 | K1024: Pending | L1024: Pending
A1025: TR-0004 | B1025: FERSNER, LAILAH | C1025: 2026 | D1025: INT-2310 | E1025: Windows Server Admin | F1025: Live VM Lab 1-1: Installing WS2019 | G1025: Assignments | K1025: 84% | L1025: Graded
A1026: TR-0004 | B1026: FERSNER, LAILAH | C1026: 2026 | D1026: INT-2310 | E1026: Windows Server Admin | F1026: Quiz: Module 02 Discover AD | G1026: Assignments | K1026: 98.68% | L1026: Graded
A1027: TR-0004 | B1027: FERSNER, LAILAH | C1027: 2026 | D1027: INT-2310 | E1027: Windows Server Admin | F1027: Quiz: Module 03 Managing AD Accounts | G1027: Assignments | K1027: 100% | L1027: Graded
A1028: TR-0004 | B1028: FERSNER, LAILAH | C1028: 2026 | D1028: INT-2310 | E1028: Windows Server Admin | F1028: Quiz: Module 04 Configuring Group Policies | G1028: Assignments | K1028: 100% | L1028: Graded
A1029: TR-0004 | B1029: FERSNER, LAILAH | C1029: 2026 | D1029: INT-2310 | E1029: Windows Server Admin | F1029: Live VM Lab 1-2 / 1-4 Azure | G1029: Assignments | K1029: 100% | L1029: Graded
A1030: TR-0004 | B1030: FERSNER, LAILAH | C1030: 2026 | D1030: INT-2310 | E1030: Windows Server Admin | F1030: Live VM Labs 2-1, 3-1, 3-3, 4-1, 4-2 | G1030: Assignments | K1030: 100% | L1030: Graded
A1031: TR-0004 | B1031: FERSNER, LAILAH | C1031: 2026 | D1031: INT-2310 | E1031: Windows Server Admin | F1031: Simulation 2-1/2-2: Working with AD | G1031: Assignments | K1031: 100% | L1031: Graded
A1032: TR-0004 | B1032: FERSNER, LAILAH | C1032: 2026 | D1032: INT-2840 | E1032: System Analysis/Project Mgmt | F1032: Introductions | G1032: Discussions | H1032: Jan 20 | I1032: 10 | J1032: 10 | K1032: 100% | L1032: Graded
A1033: TR-0004 | B1033: FERSNER, LAILAH | C1033: 2026 | D1033: INT-2840 | E1033: System Analysis/Project Mgmt | F1033: MBIT | G1033: Assignments | H1033: Jan 22 | I1033: 10 | J1033: 10 | K1033: 100% | L1033: Graded
A1034: TR-0004 | B1034: FERSNER, LAILAH | C1034: 2026 | D1034: INT-2840 | E1034: System Analysis/Project Mgmt | F1034: Journal 1 | G1034: Assignments | H1034: Jan 25 | I1034: 10 | J1034: 10 | K1034: 100% | L1034: Graded
A1035: TR-0004 | B1035: FERSNER, LAILAH | C1035: 2026 | D1035: INT-2840 | E1035: System Analysis/Project Mgmt | F1035: Journal 2 | G1035: Assignments | H1035: Feb 1 | I1035: 14 | J1035: 15 | K1035: 93.3% | L1035: Graded
A1036: TR-0004 | B1036: FERSNER, LAILAH | C1036: 2026 | D1036: INT-2840 | E1036: System Analysis/Project Mgmt | F1036: Research Paper Topics Discussion | G1036: Discussions | H1036: Feb 1 | I1036: 0 | J1036: 5 | K1036: 0% | L1036: Graded
A1037: TR-0004 | B1037: FERSNER, LAILAH | C1037: 2026 | D1037: INT-2840 | E1037: System Analysis/Project Mgmt | F1037: Journal 3 | G1037: Assignments | H1037: Feb 8 | I1037: 14 | J1037: 15 | K1037: 93.3% | L1037: Graded
A1038: TR-0004 | B1038: FERSNER, LAILAH | C1038: 2026 | D1038: INT-2840 | E1038: System Analysis/Project Mgmt | F1038: Journal 4 | G1038: Assignments | H1038: Feb 15 | I1038: 13 | J1038: 15 | K1038: 86.7% | L1038: Graded
A1039: TR-0004 | B1039: FERSNER, LAILAH | C1039: 2026 | D1039: INT-2840 | E1039: System Analysis/Project Mgmt | F1039: Outline | G1039: Assignments | H1039: Feb 15 | I1039: 5 | J1039: 5 | K1039: 100% | L1039: Graded
A1040: TR-0004 | B1040: FERSNER, LAILAH | C1040: 2026 | D1040: INT-2840 | E1040: System Analysis/Project Mgmt | F1040: Exam 1 | G1040: Quizzes | H1040: Feb 17 | I1040: 150 | J1040: 155 | K1040: 96.77% | L1040: Graded
A1041: TR-0004 | B1041: FERSNER, LAILAH | C1041: 2026 | D1041: INT-2840 | E1041: System Analysis/Project Mgmt | F1041: Annotated Bibliography | G1041: Assignments | H1041: Feb 22 | I1041: 5 | J1041: 5 | K1041: 100% | L1041: Graded
A1042: TR-0004 | B1042: FERSNER, LAILAH | C1042: 2026 | D1042: INT-2840 | E1042: System Analysis/Project Mgmt | F1042: Evaluation Matrix | G1042: Assignments | H1042: Mar 1 | I1042: 5 | J1042: 5 | K1042: 100% | L1042: Graded
A1043: TR-0004 | B1043: FERSNER, LAILAH | C1043: 2026 | D1043: INT-2840 | E1043: System Analysis/Project Mgmt | F1043: Journal 7 | G1043: Assignments | H1043: Mar 8 | J1043: 15 | K1043: MISSING | L1043: Missing
A1044: TR-0004 | B1044: FERSNER, LAILAH | C1044: 2026 | D1044: INT-2840 | E1044: System Analysis/Project Mgmt | F1044: Research Paper | G1044: Assignments | H1044: Mar 8 | J1044: 100 | K1044: MISSING | L1044: Missing
A1045: TR-0004 | B1045: FERSNER, LAILAH | C1045: 2026 | D1045: EGL-1340 | E1045: Comp II: Writing Tech Topics | F1045: Resume and Cover Letter Writing | G1045: Resume/CL | H1045: Feb 15 | I1045: 95 | J1045: 100 | K1045: 95% | L1045: Graded
A1046: TR-0004 | B1046: FERSNER, LAILAH | C1046: 2026 | D1046: EGL-1340 | E1046: Comp II: Writing Tech Topics | F1046: Memo/Report Writing | G1046: Memo/Report | H1046: Mar 4 | I1046: T | J1046: 100 | K1046: Pending | L1046: Pending

Sheet Weekly Intake
A1: ⬅ NAVIGATE:
A2: ElevateED — 📥 WEEKLY INTAKE — Grade Extraction Landing Zone | Pending Approval
A3: Talent Ready IT Program | Largo High School | Prince George's Community College
A4: Maryland Blueprint for Maryland's Future | CONFIDENTIAL — FERPA PROTECTED | Generated: March 24, 2026 09:00 AM
A5: GradeExtractor.gs writes here every Thursday 9:00 AM | Review → set Approved=Y → GradeApprover.gs pushes to Cohort Grids
A6: Intake ID | B6: PDF Timestamp | C6: Week # | D6: Week Date | E6: Student ID | F6: Student Name | G6: Cohort | H6: Course Code | I6: Course Name | J6: Assignment Name | K6: Category | L6: Due Date | M6: Submitted Date | N6: Score Earned | O6: Score Total | P6: Percentage | Q6: Status | R6: Missing? | S6: Late Report? | T6: Approved | U6: Approved By | V6: Approved At | W6: Pushed To Grid | X6: Notes
A7: WI-001 | B7: 3/23/26 8:44 AM | C7: W9 | D7: 3/26/2026 | E7: TR-0034 | F7: MOSES, EMERIC | G7: 2028 | H7: NTR-1010 | I7: Intro to Nutrition | J7: Chapter 01 Quiz: Food Choices and Human Health | K7: Assignments | L7: Feb 2 | N7: 18.33 | O7: 25 | P7: 73.3% | Q7: Graded | R7: No | S7: Yes | X7: Late report — received 3/23; back-dated W9
A8: WI-002 | B8: 3/23/26 8:44 AM | C8: W9 | D8: 3/26/2026 | E8: TR-0034 | F8: MOSES, EMERIC | G8: 2028 | H8: NTR-1010 | I8: Intro to Nutrition | J8: M1: Diet Assessment Part 1 | K8: Assignments | L8: Feb 2 | M8: Feb 1 | N8: 10 | O8: 10 | P8: 100% | Q8: Graded | R8: No | S8: Yes | X8: On time
A9: WI-003 | B9: 3/23/26 8:44 AM | C9: W9 | D9: 3/26/2026 | E9: TR-0034 | F9: MOSES, EMERIC | G9: 2028 | H9: NTR-1010 | I9: Intro to Nutrition | J9: Chapter 02 Quiz: Nutrition Tools - Standards | K9: Assignments | L9: Feb 9 | N9: 23.33 | O9: 25 | P9: 93.3% | Q9: Graded | R9: No | S9: Yes
A10: WI-004 | B10: 3/23/26 8:44 AM | C10: W9 | D10: 3/26/2026 | E10: TR-0034 | F10: MOSES, EMERIC | G10: 2028 | H10: NTR-1010 | I10: Intro to Nutrition | J10: M2: Diet Assessment Part 2 | K10: Assignments | L10: Feb 9 | M10: Feb 9 | N10: 40 | O10: 40 | P10: 100% | Q10: Graded | R10: No | S10: Yes | X10: On time
A11: WI-005 | B11: 3/23/26 8:44 AM | C11: W9 | D11: 3/26/2026 | E11: TR-0034 | F11: MOSES, EMERIC | G11: 2028 | H11: NTR-1010 | I11: Intro to Nutrition | J11: Chapter 03 Quiz: The Remarkable Body | K11: Assignments | L11: Feb 17 | O11: 25 | P11: 93.33% | Q11: Graded | R11: No | S11: Yes
A12: WI-006 | B12: 3/23/26 8:44 AM | C12: W9 | D12: 3/26/2026 | E12: TR-0034 | F12: MOSES, EMERIC | G12: 2028 | H12: NTR-1010 | I12: Intro to Nutrition | J12: M3: NTR Exam 1 | K12: Exams | L12: Feb 18 | M12: Feb 18 | N12: 71 | O12: 100 | P12: 71% | Q12: Graded | R12: No | S12: Yes | X12: Below passing threshold
A13: WI-007 | B13: 3/23/26 8:44 AM | C13: W9 | D13: 3/26/2026 | E13: TR-0034 | F13: MOSES, EMERIC | G13: 2028 | H13: NTR-1010 | I13: Intro to Nutrition | J13: Chapter 04 D&W+ Client Diet Assessment | K13: Assignments | L13: Mar 2 | O13: 25 | P13: 60% | Q13: Graded | R13: No | S13: Yes
A14: WI-008 | B14: 3/23/26 8:44 AM | C14: W9 | D14: 3/26/2026 | E14: TR-0034 | F14: MOSES, EMERIC | G14: 2028 | H14: NTR-1010 | I14: Intro to Nutrition | J14: Chapter 04 Quiz: The Carbohydrates | K14: Assignments | L14: Mar 2 | N14: 23.33 | O14: 25 | P14: 93.3% | Q14: Graded | R14: No | S14: Yes
A15: WI-009 | B15: 3/23/26 8:44 AM | C15: W9 | D15: 3/26/2026 | E15: TR-0034 | F15: MOSES, EMERIC | G15: 2028 | H15: NTR-1010 | I15: Intro to Nutrition | J15: Chapter 05 A Closer Look: Types/Functions Lipids | K15: Assignments | L15: Mar 16 | O15: 25 | P15: 95.24% | Q15: Graded | R15: No | S15: Yes
A16: WI-010 | B16: 3/23/26 8:44 AM | C16: W9 | D16: 3/26/2026 | E16: TR-0034 | F16: MOSES, EMERIC | G16: 2028 | H16: NTR-1010 | I16: Intro to Nutrition | J16: Chapter 05 Quiz: The Lipids | K16: Assignments | L16: Mar 16 | N16: 23.33 | O16: 25 | Q16: Graded | R16: No | S16: Yes
A17: WI-011 | B17: 3/23/26 8:44 AM | C17: W9 | D17: 3/26/2026 | E17: TR-0034 | F17: MOSES, EMERIC | G17: 2028 | H17: NTR-1010 | I17: Intro to Nutrition | J17: Chapter 06 Case Study: Making Meatless Work | K17: Assignments | L17: Mar 23 | O17: 35 | Q17: Missing | R17: Yes | S17: Yes | X17: ⚠️ Missing — 0 days until due
A18: WI-012 | B18: 3/23/26 8:44 AM | C18: W9 | D18: 3/26/2026 | E18: TR-0034 | F18: MOSES, EMERIC | G18: 2028 | H18: NTR-1010 | I18: Intro to Nutrition | J18: Chapter 06 Quiz: The Proteins | K18: Assignments | L18: Mar 23 | O18: 25 | Q18: Missing | R18: Yes | S18: Yes | X18: ⚠️ Missing
A19: WI-013 | B19: 3/23/26 8:44 AM | C19: W9 | D19: 3/26/2026 | E19: TR-0034 | F19: MOSES, EMERIC | G19: 2028 | H19: NTR-1010 | I19: Intro to Nutrition | J19: M6: NTR Exam 2 | K19: Exams | L19: Mar 25 | O19: 100 | Q19: Missing | R19: Yes | S19: Yes | X19: ⚠️ Exam missing
A20: WI-014 | B20: 3/23/26 8:44 AM | C20: W9 | D20: 3/26/2026 | E20: TR-0034 | F20: MOSES, EMERIC | G20: 2028 | H20: NTR-1010 | I20: Intro to Nutrition | J20: *** COURSE TOTAL *** | K20: SUMMARY | N20: 287 | O20: 345 | P20: 83.19% | Q20: OVERALL | R20: No | S20: Yes | X20: Assignments 88.16% | Exams 71%
A21: WI-015 | B21: 3/23/26 8:44 AM | C21: W9 | D21: 3/26/2026 | E21: TR-0034 | F21: MOSES, EMERIC | G21: 2028 | H21: SOC-1010 | I21: Introduction to Sociology | J21: Getting Started: Introductions Discussion | K21: Discussion | L21: Feb 1 | M21: Jan 29 | N21: 5 | O21: 5 | P21: 100% | Q21: Graded | R21: No | S21: Yes
A22: WI-016 | B22: 3/23/26 8:44 AM | C22: W9 | D22: 3/26/2026 | E22: TR-0034 | F22: MOSES, EMERIC | G22: 2028 | H22: SOC-1010 | I22: Introduction to Sociology | J22: SAA1 | K22: Assignments | L22: Feb 22 | M22: Feb 22 | N22: 45 | O22: 50 | P22: 90% | Q22: Graded | R22: No | S22: Yes
A23: WI-017 | B23: 3/23/26 8:44 AM | C23: W9 | D23: 3/26/2026 | E23: TR-0034 | F23: MOSES, EMERIC | G23: 2028 | H23: SOC-1010 | I23: Introduction to Sociology | J23: Exam 1: Ch 1-2 Sociological Imagination | K23: EXAMS | L23: Mar 8 | M23: Mar 8 | N23: 27 | O23: 50 | P23: 54% | Q23: Graded | R23: No | S23: Yes | X23: ⚠️ BELOW PASSING — 54%
A24: WI-018 | B24: 3/23/26 8:44 AM | C24: W9 | D24: 3/26/2026 | E24: TR-0034 | F24: MOSES, EMERIC | G24: 2028 | H24: SOC-1010 | I24: Introduction to Sociology | J24: SAA2 | K24: Assignments | L24: Mar 29 | O24: 50 | Q24: Missing | R24: Yes | S24: Yes | X24: ⚠️ Missing
A25: WI-019 | B25: 3/23/26 8:44 AM | C25: W9 | D25: 3/26/2026 | E25: TR-0034 | F25: MOSES, EMERIC | G25: 2028 | H25: SOC-1010 | I25: Introduction to Sociology | J25: Exam 2: Chapters 3-5 | K25: EXAMS | L25: Mar 30 | O25: 50 | Q25: Missing | R25: Yes | S25: Yes | X25: ⚠️ Exam missing — due Mar 30
A26: WI-020 | B26: 3/23/26 8:44 AM | C26: W9 | D26: 3/26/2026 | E26: TR-0034 | F26: MOSES, EMERIC | G26: 2028 | H26: SOC-1010 | I26: Introduction to Sociology | J26: SAA2 Culture Field Assignment Discussion | K26: Assignments | L26: Mar 30 | O26: 5 | Q26: Missing | R26: Yes | S26: Yes | X26: ⚠️ Missing
A27: WI-021 | B27: 3/23/26 8:44 AM | C27: W9 | D27: 3/26/2026 | E27: TR-0034 | F27: MOSES, EMERIC | G27: 2028 | H27: SOC-1010 | I27: Introduction to Sociology | J27: *** COURSE TOTAL *** | K27: SUMMARY | N27: 77 | O27: 105 | P27: 73.33% | Q27: OVERALL | R27: No | S27: Yes | X27: Discussions 100% | Assignments 90% | Exams 54%
